Workbook

Sheet Explanation and FAQ
A1: Country Risk Premiums
A2: To estimate the equity risk premium for a country, I start with a mature market premium and add an additional country risk premium, based upon the risk of the country in question.
A3: Use the look up table in the next worksheet, to look up the statistics for an individual country or region.
A5: Step 1: Estimating mature market risk premium
A6: To estimate the mature market risk premium, I start with the implied equity risk premium for the S&P 500. To see the latest estimate for this number, go to my website and you can download the excel spreadsheet containing the implied premium
A7: Link to site: | B7: http://www.damodaran.com
A8: Historical monthly ERP: | B8: https://pages.stern.nyu.edu/~adamodar/pc/implprem/ERPbymonth.xls
A9: Until the January 2025 update, I used the S&P's equity risk premium as the mature market premium, drawing on the Moody's Aaa rating for the United States.
A10: On May 16, 2025, Moody's downgraded the US from Aaa to Aa1. To get the mature market premium, I now subtract the US's country risk premium (based on its rating and the relative equity market volatility) from the S&P's eRP
A11: Mature market premium = ERP for the S&P 500 minus (Default spread for US sovereign rating × Relative Equity Volatility)
A12: In January 2026, for example, when the implied ERP for the S&P 500 was 4.59% (over the adjusted dollar riskfree rate), the US had a rating of Aa1 and the default spread for that rating was 0.23% and the relative equity market volatility was 1.52
A13: Mature market premium = 4.61% - (0.23% × 1.52) = 4.23%
A15: Step 2: Estimate the default spread for the country in question. I offer two choices, one based upon the local currency sovereign rating for the country from Moody's and the other is the CDS spread for the country (if one exists)
A16: Moody's ratings: | B16: http://www.moodys.com | D16: (You will have to register, but it is free. Look under sovereign ratings)
A17: Ratings to spreads: | B17: Based upon my estimates of typical spreads for each ratings class. I compute these by averaging CDS spreads and sovereign US$ bond spreads by ratings class, at the start of every year.
A18: CDS spreads: | B18: Bloomberg
A19: If you cannot find a country on this list, it is because that country does not have a sovereign rating or a sovereign CDS spread. Try the PRS worksheet in this spreadsheet for an alternate estimate.
A21: Step 3: Convert the default spread into a country risk premium
A22: With sovereign ratings default spreads, you have two choices:
A23: Choice 1: Use the default spread as the measure of the additional country risk premium. To make this choice, go into the ERP worksheet and set cell E5 to 1.00.
A24: Choice 2: Scale the default spread up to reflect the higher risk of equity in the market, relative to the default spread. I used the ratio of the S&P Emerging Market Equity Index std deviation to the iShares Emerging Market Bond Index standard deviation
A25: With CDS spreads, I compute the base number in two steps
A26: Substep 1: Since the base equity premium is for a mature market (assumed to be default free), I net out the CDS spread for Switzerland (the lowest sovereign CDS) from each country's CDS to get a net spread.
A27: Substep 2: I apply the scaling factor that you chose for the default spreads to this number to get a country risk premium. The default scaling is set at the my most recent year's estimate, but you can change it to 1, if you would
A28: prefer not to scale the default spread.
A30: Step 4: Compute a total equity risk premium
A31: Add the mature market premium from step 1 to the country risk premium from step 3 to get a total equity risk premium.
A33: Step 5: Compute regional averages and regional weighted averages
... A35: For the weighted averages, I use the World Bank GDP estimates from the most recent year.
I36: https://data.worldbank.org/indicator/NY.GDP.MKTP.CD
A37: If you are interested in a fuller explanation of these concepts, try these references:
A38: My paper on equity risk premiums:
A39: My paper on country risk premiums: | E39: https://papers.ssrn.com/sol3/papers.cfm?abstract_id=4398884
A40: Watch my lectures on country risk premiums: | E40: https://papers.ssrn.com/sol3/papers.cfm?abstract_id=4509578
E41: https://www.youtube.com/watch?v=aIRPvY2SQ94
E42: https://www.youtube.com/watch?v=D3IGn6tH03c

Sheet Summary of Most Recent Update
B1: Update Notes
A2: Mature Marlet Premium | B2: The starting point for the mature market premiums is the implied equity risk premium for the S&P 500. You can review the calcualtion in this spreadsheet. (https://pages.stern.nyu.edu/~adamodar/pc/implprem/ERPJan26.xlsx). I net out a riskfree rate in US dollars, which is the treasury bond rate adjusted for the default spread for the US, to get an equity risk premium for the US. I then back out the US default spread to get a mature market premium.
A3: US ERP | B3: ERP for US = Implled Expected Return on US stocks - (US 10-yr T.Bond - Default spread for US)
A4: Mature market ERP | B4: Mature market ERP = ERP for US - Default spread for US
A5: Sovereign Ratings | B5: The ratings (Moody's and S&P) have been updated to reflect the most recent ratings. (See Ratings Worksheet)
A6: Default Spreads | B6: The change in default spreads is computed by looking at percentage changes in sovereign CDS spreads over the period. (See Default Spreads for Ratings worksheet)
A7: Relative Equity Market Volatility | B7: The biggest change in this update is in this measure. For the last few years, I have used the coefficient of variation in emerging market bond yields and the standard deviation of returns in emerging market equities. In this iteration, I have replaced the former with the standard defiation in emerging market sovereign bond ETF returns, thus creating more consistency in the calcuatlions. While this change does not create a substantive shift in the numbers in this iteration, I think it is a more solid basis for computing this value in future ones.
A8: Bottom Line | B8: The combination of a lower base mature market premium and lower sovereign default spreads has led to lower equity risk premiums across the board, a climb down from historically high numbers at the start of the year.

Sheet Country Lookup
A1: To look up the equity risk premium for a country, use this worksheet
A2: Country | B2: Turkey | D2: If you cannot find a country on this list, it is because that country does not have a sovereign rating
D3: or a sovereign CDS spread. Try the PRS worksheet in this spreadsheet for an alternate estimate.
A4: Moody's sovereign rating | B4: =VLOOKUP(B2,'Ratings worksheet'!$A$2:$C$159,3, FALSE()) -> Ba3 | C4: Local currency
A5: S&P sovereign rating | B5: =VLOOKUP(B2,'Ratings worksheet'!$A$2:$C$159,2, FALSE()) -> BB- | C5: Local currency
A6: CDS spread | B6: =VLOOKUP(B2,'10-year CDS Spreads'!A2:D158,3, FALSE()) -> 0.0299
A7: Excess CDS spread (over Swiss CDS) | B7: =IF(B6="NA","NA",VLOOKUP(B2,'ERPs by country'!A9:I165,9,FALSE())/'ERPs by country'!E6) -> 0.0285
A9: Country Default Spread (based on rating) | B9: =VLOOKUP(B2,'ERPs by country'!A9:I165,4,FALSE()) -> 0.030563925
A10: Country Risk Premium (Rating) | B10: =VLOOKUP(B2,'ERPs by country'!A9:I165,6,FALSE()) -> 0.046560415
A11: Equity Risk Premium (Rating) | B11: =VLOOKUP(B2,'ERPs by country'!A9:I165,5,FALSE()) -> 0.088860415
A13: Country Risk Premium (CDS) | B13: =VLOOKUP(B2,'ERPs by country'!A9:I165,9,FALSE()) -> 0.043416277
A14: Equity Risk Premium (CDS) | B14: =VLOOKUP(B2,'ERPs by country'!A9:I165,8,FALSE()) -> 0.085716277
A16: To look up the equity risk premium for a region, use this worksheet
A17: Region | B17: Asia
A19: Country Risk Premium (simple average)) | B19: =VLOOKUP(B17,'Regional Simple Averages'!$A$5:$E$13,3,FALSE()) -> 0.048341934
A20: Total Equity Risk Premium (simple average) | B20: =VLOOKUP(B17,'Regional Simple Averages'!$A$5:$E$13,4,FALSE()) -> 0.090641934
A22: Country Risk Premium (GDP weighted) | B22: =VLOOKUP(B17,'Regional Weighted Averages'!A171:C179,3,FALSE()) -> 0.014923236
A23: Total Equity Risk Premium (GDP weighted) | B23: =VLOOKUP(B17,'Regional Weighted Averages'!A171:C179,2,FALSE()) -> 0.057223236
A25: To construct your own regional ERP, use the data on GDP and ERP for countries in the Regional Weighted Averages Worksheet
A27: For countries not on the list above, try this frontier market list
A28: Country | B28: Zimbabwe
A30: PRS Score | B30: =VLOOKUP(B28,'PRS Worksheet'!A162:E182,2,FALSE()) -> 58.5
A31: ERP based on PRS Score | B31: =VLOOKUP(B28,'PRS Worksheet'!A162:E182,5,FALSE()) -> 0.1588532

Sheet ERPs by country
A1: Country and Equity Risk Premiums
A2: Date of update: | B2: 44561 | C2: (Updated Feb 16 for sovereign ratings
A3: Enter the current risk premium for a mature equity market | E3: 0.0423 | F3: Implied ERP for S&P 500 with adjusted dollar riskfree rate (for US Aa1 rating
A4: Enter the current risk premium for the US = | E4: 0.0446 | F4: US equity risk premium computed using implied ERP approach
A5: Do you want to adjust the country default spread for the additional volatility of the equity market to get to a country premium? | E5: Yes
A6: If yes, enter the multiplier to use on the default spread (See worksheet for volatility numbers for selected emerging markets) | E6: ='Relative Equity Volatility'!D7 -> 1.5233781 | F6: See "Relative Equity Volatilty" worksheet
A8: Country | B8: Africa | C8: Moody's rating | D8: Rating-based Default Spread | E8: Total Equity Risk Premium | F8: Country Risk Premium | G8: Sovereign CDS, net of Swiss CDS | H8: Total Equity Risk Premium2 | I8: Country Risk Premium3 | J8: Has to be sorted in ascending order
A9: ='Sovereign Ratings (Moody''s,S&P)'!A2 -> Abu Dhabi | B9: =VLOOKUP(A9,'Regional lookup table'!$A$2:$B$162,2,FALSE()) -> Middle East | C9: =VLOOKUP(A9,'Sovereign Ratings (Moody''s,S&P)'!$A$2:$D$158,4,FALSE()) -> Aa2 | D9: =VLOOKUP(C9,$J$10:$K$32,2,FALSE())/10000 -> 0.0041950485 | E9: =$E$3+F9 -> 0.048690645 | F9: =IF($E$5="Yes",D9*$E$6,D9) -> 0.0063906452 | G9: =VLOOKUP(A9,'10-year CDS Spreads'!$A$2:$D$158,4,FALSE()) -> 0.0046 | H9: =IF(I9="NA","NA",$E$3+I9) -> 0.049307539 | I9: =IF(G9="NA","NA",G9*$E$6) -> 0.0070075394 | J9: Rating | K9: Default spread in basis points
A10: ='Sovereign Ratings (Moody''s,S&P)'!A3 -> Albania | B10: =VLOOKUP(A10,'Regional lookup table'!$A$2:$B$162,2,FALSE()) -> Eastern Europe & Russia | C10: =VLOOKUP(A10,'Sovereign Ratings (Moody''s,S&P)'!$A$2:$D$158,4,FALSE()) -> Ba3 | D10: =VLOOKUP(C10,$J$10:$K$32,2,FALSE())/10000 -> 0.030563925 | E10: =$E$3+F10 -> 0.088860415 | F10: =IF($E$5="Yes",D10*$E$6,D10) -> 0.046560415 | G10: =VLOOKUP(A10,'10-year CDS Spreads'!$A$2:$D$158,4,FALSE()) -> NA | H10: =IF(I10="NA","NA",$E$3+I10) -> NA | I10: =IF(G10="NA","NA",G10*$E$6) -> NA | J10: A1 | K10: =C191 -> 59.929264
A11: ='Sovereign Ratings (Moody''s,S&P)'!A4 -> Andorra (Principality of) | B11: =VLOOKUP(A11,'Regional lookup table'!$A$2:$B$162,2,FALSE()) -> Western Europe | C11: =VLOOKUP(A11,'Sovereign Ratings (Moody''s,S&P)'!$A$2:$D$158,4,FALSE()) -> Baa1 | D11: =VLOOKUP(C11,$J$10:$K$32,2,FALSE())/10000 -> 0.013583967 | E11: =$E$3+F11 -> 0.062993518 | F11: =IF($E$5="Yes",D11*$E$6,D11) -> 0.020693518 | G11: =VLOOKUP(A11,'10-year CDS Spreads'!$A$2:$D$158,4,FALSE()) -> NA | H11: =IF(I11="NA","NA",$E$3+I11) -> NA | I11: =IF(G11="NA","NA",G11*$E$6) -> NA | J11: A2 | K11: =C192 -> 71.915117
A12: ='Sovereign Ratings (Moody''s,S&P)'!A5 -> Angola | B12: =VLOOKUP(A12,'Regional lookup table'!$A$2:$B$162,2,FALSE()) -> Africa | C12: =VLOOKUP(A12,'Sovereign Ratings (Moody''s,S&P)'!$A$2:$D$158,4,FALSE()) -> B3 | D12: =VLOOKUP(C12,$J$10:$K$32,2,FALSE())/10000 -> 0.055234805 | E12: =$E$3+F12 -> 0.12644349 | F12: =IF($E$5="Yes",D12*$E$6,D12) -> 0.084143495 | G12: =VLOOKUP(A12,'10-year CDS Spreads'!$A$2:$D$158,4,FALSE()) -> 0.061 | H12: =IF(I12="NA","NA",$E$3+I12) -> 0.13522607 | I12: =IF(G12="NA","NA",G12*$E$6) -> 0.092926066 | J12: A3 | K12: =C193 -> 101.87975
A13: ='Sovereign Ratings (Moody''s,S&P)'!A6 -> Argentina | B13: =VLOOKUP(A13,'Regional lookup table'!$A$2:$B$162,2,FALSE()) -> Central and South America | C13: =VLOOKUP(A13,'Sovereign Ratings (Moody''s,S&P)'!$A$2:$D$158,4,FALSE()) -> Caa1 | D13: =VLOOKUP(C13,$J$10:$K$32,2,FALSE())/10000 -> 0.063724785 | E13: =$E$3+F13 -> 0.13937694 | F13: =IF($E$5="Yes",D13*$E$6,D13) -> 0.097076943 | G13: =VLOOKUP(A13,'10-year CDS Spreads'!$A$2:$D$158,4,FALSE()) -> NA | H13: =IF(I13="NA","NA",$E$3+I13) -> NA | I13: =IF(G13="NA","NA",G13*$E$6) -> NA | J13: Aa1 | K13: =C194 -> 23.336792
A14: ='Sovereign Ratings (Moody''s,S&P)'!A7 -> Armenia | B14: =VLOOKUP(A14,'Regional lookup table'!$A$2:$B$162,2,FALSE()) -> Eastern Europe & Russia | C14: =VLOOKUP(A14,'Sovereign Ratings (Moody''s,S&P)'!$A$2:$D$158,4,FALSE()) -> Ba3 | D14: =VLOOKUP(C14,$J$10:$K$32,2,FALSE())/10000 -> 0.030563925 | E14: =$E$3+F14 -> 0.088860415 | F14: =IF($E$5="Yes",D14*$E$6,D14) -> 0.046560415 | G14: =VLOOKUP(A14,'10-year CDS Spreads'!$A$2:$D$158,4,FALSE()) -> NA | H14: =IF(I14="NA","NA",$E$3+I14) -> NA | I14: =IF(G14="NA","NA",G14*$E$6) -> NA | J14: Aa2 | K14: =C195 -> 41.950485
A15: ='Sovereign Ratings (Moody''s,S&P)'!A8 -> Aruba | B15: =VLOOKUP(A15,'Regional lookup table'!$A$2:$B$162,2,FALSE()) -> Caribbean | C15: =VLOOKUP(A15,'Sovereign Ratings (Moody''s,S&P)'!$A$2:$D$158,4,FALSE()) -> Baa3 | D15: =VLOOKUP(C15,$J$10:$K$32,2,FALSE())/10000 -> 0.018677954 | E15: =$E$3+F15 -> 0.070753587 | F15: =IF($E$5="Yes",D15*$E$6,D15) -> 0.028453587 | G15: =VLOOKUP(A15,'10-year CDS Spreads'!$A$2:$D$158,4,FALSE()) -> NA | H15: =IF(I15="NA","NA",$E$3+I15) -> NA | I15: =IF(G15="NA","NA",G15*$E$6) -> NA | J15: Aa3 | K15: =C196 -> 50.939875
A16: ='Sovereign Ratings (Moody''s,S&P)'!A9 -> Australia | B16: =VLOOKUP(A16,'Regional lookup table'!$A$2:$B$162,2,FALSE()) -> Australia & New Zealand | C16: =VLOOKUP(A16,'Sovereign Ratings (Moody''s,S&P)'!$A$2:$D$158,4,FALSE()) -> Aaa | D16: =VLOOKUP(C16,$J$10:$K$32,2,FALSE())/10000 -> 0 | E16: =$E$3+F16 -> 0.0423 | F16: =IF($E$5="Yes",D16*$E$6,D16) -> 0 | G16: =VLOOKUP(A16,'10-year CDS Spreads'!$A$2:$D$158,4,FALSE()) -> 0.0005 | H16: =IF(I16="NA","NA",$E$3+I16) -> 0.043061689 | I16: =IF(G16="NA","NA",G16*$E$6) -> 0.00076168907 | J16: Aaa | K16: =C197 -> 0
A17: ='Sovereign Ratings (Moody''s,S&P)'!A10 -> Austria | B17: =VLOOKUP(A17,'Regional lookup table'!$A$2:$B$162,2,FALSE()) -> Western Europe | C17: =VLOOKUP(A17,'Sovereign Ratings (Moody''s,S&P)'!$A$2:$D$158,4,FALSE()) -> Aa1 | D17: =VLOOKUP(C17,$J$10:$K$32,2,FALSE())/10000 -> 0.0023336792 | E17: =$E$3+F17 -> 0.045855076 | F17: =IF($E$5="Yes",D17*$E$6,D17) -> 0.0035550758 | G17: =VLOOKUP(A17,'10-year CDS Spreads'!$A$2:$D$158,4,FALSE()) -> 0.0014 | H17: =IF(I17="NA","NA",$E$3+I17) -> 0.044432729 | I17: =IF(G17="NA","NA",G17*$E$6) -> 0.0021327294 | J17: B1 | K17: =C198 -> 382.54847
A18: ='Sovereign Ratings (Moody''s,S&P)'!A11 -> Azerbaijan | B18: =VLOOKUP(A18,'Regional lookup table'!$A$2:$B$162,2,FALSE()) -> Eastern Europe & Russia | C18: =VLOOKUP(A18,'Sovereign Ratings (Moody''s,S&P)'!$A$2:$D$158,4,FALSE()) -> Baa3 | D18: =VLOOKUP(C18,$J$10:$K$32,2,FALSE())/10000 -> 0.018677954 | E18: =$E$3+F18 -> 0.070753587 | F18: =IF($E$5="Yes",D18*$E$6,D18) -> 0.028453587 | G18: =VLOOKUP(A18,'10-year CDS Spreads'!$A$2:$D$158,4,FALSE()) -> NA | H18: =IF(I18="NA","NA",$E$3+I18) -> NA | I18: =IF(G18="NA","NA",G18*$E$6) -> NA | J18: B2 | K18: =C199 -> 467.44826
A19: ='Sovereign Ratings (Moody''s,S&P)'!A12 -> Bahamas | B19: =VLOOKUP(A19,'Regional lookup table'!$A$2:$B$162,2,FALSE()) -> Caribbean | C19: =VLOOKUP(A19,'Sovereign Ratings (Moody''s,S&P)'!$A$2:$D$158,4,FALSE()) -> B1 | D19: =VLOOKUP(C19,$J$10:$K$32,2,FALSE())/10000 -> 0.038254847 | E19: =$E$3+F19 -> 0.1005766 | F19: =IF($E$5="Yes",D19*$E$6,D19) -> 0.058276598 | G19: =VLOOKUP(A19,'10-year CDS Spreads'!$A$2:$D$158,4,FALSE()) -> NA | H19: =IF(I19="NA","NA",$E$3+I19) -> NA | I19: =IF(G19="NA","NA",G19*$E$6) -> NA | J19: B3 | K19: =C200 -> 552.34805
A20: ='Sovereign Ratings (Moody''s,S&P)'!A13 -> Bahrain | B20: =VLOOKUP(A20,'Regional lookup table'!$A$2:$B$162,2,FALSE()) -> Middle East | C20: =VLOOKUP(A20,'Sovereign Ratings (Moody''s,S&P)'!$A$2:$D$158,4,FALSE()) -> B2 | D20: =VLOOKUP(C20,$J$10:$K$32,2,FALSE())/10000 -> 0.046744826 | E20: =$E$3+F20 -> 0.11351005 | F20: =IF($E$5="Yes",D20*$E$6,D20) -> 0.071210046 | G20: =VLOOKUP(A20,'10-year CDS Spreads'!$A$2:$D$158,4,FALSE()) -> 0.0233 | H20: =IF(I20="NA","NA",$E$3+I20) -> 0.07779471 | I20: =IF(G20="NA","NA",G20*$E$6) -> 0.03549471 | J20: Ba1 | K20: =C201 -> 212.74889
A21: ='Sovereign Ratings (Moody''s,S&P)'!A14 -> Bangladesh | B21: =VLOOKUP(A21,'Regional lookup table'!$A$2:$B$162,2,FALSE()) -> Asia | C21: =VLOOKUP(A21,'Sovereign Ratings (Moody''s,S&P)'!$A$2:$D$158,4,FALSE()) -> B2 | D21: =VLOOKUP(C21,$J$10:$K$32,2,FALSE())/10000 -> 0.046744826 | E21: =$E$3+F21 -> 0.11351005 | F21: =IF($E$5="Yes",D21*$E$6,D21) -> 0.071210046 | G21: =VLOOKUP(A21,'10-year CDS Spreads'!$A$2:$D$158,4,FALSE()) -> NA | H21: =IF(I21="NA","NA",$E$3+I21) -> NA | I21: =IF(G21="NA","NA",G21*$E$6) -> NA | J21: Ba2 | K21: =C202 -> 255.69819
... A27: ='Sovereign Ratings (Moody''s,S&P)'!A20 -> Bermuda | B27: =VLOOKUP(A27,'Regional lookup table'!$A$2:$B$162,2,FALSE()) -> Caribbean | C27: =VLOOKUP(A27,'Sovereign Ratings (Moody''s,S&P)'!$A$2:$D$158,4,FALSE()) -> A2 | D27: =VLOOKUP(C27,$J$10:$K$32,2,FALSE())/10000 -> 0.0071915117 | E27: =$E$3+F27 -> 0.053255392 | F27: =IF($E$5="Yes",D27*$E$6,D27) -> 0.010955392 | G27: =VLOOKUP(A27,'10-year CDS Spreads'!$A$2:$D$158,4,FALSE()) -> NA | H27: =IF(I27="NA","NA",$E$3+I27) -> NA | I27: =IF(G27="NA","NA",G27*$E$6) -> NA | J27: Ca | K27: =C208 -> 1019.7963
A28: ='Sovereign Ratings (Moody''s,S&P)'!A21 -> Bolivia | B28: =VLOOKUP(A28,'Regional lookup table'!$A$2:$B$162,2,FALSE()) -> Central and South America | C28: =VLOOKUP(A28,'Sovereign Ratings (Moody''s,S&P)'!$A$2:$D$158,4,FALSE()) -> Ca | D28: =VLOOKUP(C28,$J$10:$K$32,2,FALSE())/10000 -> 0.10197963 | E28: =$E$3+F28 -> 0.19765354 | F28: =IF($E$5="Yes",D28*$E$6,D28) -> 0.15535354 | G28: =VLOOKUP(A28,'10-year CDS Spreads'!$A$2:$D$158,4,FALSE()) -> NA | H28: =IF(I28="NA","NA",$E$3+I28) -> NA | I28: =IF(G28="NA","NA",G28*$E$6) -> NA | J28: =B209 -> Caa1 | K28: =C209 -> 637.24785
A29: ='Sovereign Ratings (Moody''s,S&P)'!A22 -> Bosnia and Herzegovina | B29: =VLOOKUP(A29,'Regional lookup table'!$A$2:$B$162,2,FALSE()) -> Eastern Europe & Russia | C29: =VLOOKUP(A29,'Sovereign Ratings (Moody''s,S&P)'!$A$2:$D$158,4,FALSE()) -> B3 | D29: =VLOOKUP(C29,$J$10:$K$32,2,FALSE())/10000 -> 0.055234805 | E29: =$E$3+F29 -> 0.12644349 | F29: =IF($E$5="Yes",D29*$E$6,D29) -> 0.084143495 | G29: =VLOOKUP(A29,'10-year CDS Spreads'!$A$2:$D$158,4,FALSE()) -> NA | H29: =IF(I29="NA","NA",$E$3+I29) -> NA | I29: =IF(G29="NA","NA",G29*$E$6) -> NA | J29: =B210 -> Caa2 | K29: =C210 -> 765.09694
A30: ='Sovereign Ratings (Moody''s,S&P)'!A23 -> Botswana | B30: =VLOOKUP(A30,'Regional lookup table'!$A$2:$B$162,2,FALSE()) -> Africa | C30: =VLOOKUP(A30,'Sovereign Ratings (Moody''s,S&P)'!$A$2:$D$158,4,FALSE()) -> Baa1 | D30: =VLOOKUP(C30,$J$10:$K$32,2,FALSE())/10000 -> 0.013583967 | E30: =$E$3+F30 -> 0.062993518 | F30: =IF($E$5="Yes",D30*$E$6,D30) -> 0.020693518 | G30: =VLOOKUP(A30,'10-year CDS Spreads'!$A$2:$D$158,4,FALSE()) -> NA | H30: =IF(I30="NA","NA",$E$3+I30) -> NA | I30: =IF(G30="NA","NA",G30*$E$6) -> NA | J30: =B211 -> Caa3 | K30: =C211 -> 849.99673
A31: ='Sovereign Ratings (Moody''s,S&P)'!A24 -> Brazil | B31: =VLOOKUP(A31,'Regional lookup table'!$A$2:$B$162,2,FALSE()) -> Central and South America | C31: =VLOOKUP(A31,'Sovereign Ratings (Moody''s,S&P)'!$A$2:$D$158,4,FALSE()) -> Ba1 | D31: =VLOOKUP(C31,$J$10:$K$32,2,FALSE())/10000 -> 0.021274889 | E31: =$E$3+F31 -> 0.0747097 | F31: =IF($E$5="Yes",D31*$E$6,D31) -> 0.0324097 | G31: =VLOOKUP(A31,'10-year CDS Spreads'!$A$2:$D$158,4,FALSE()) -> 0.0221 | H31: =IF(I31="NA","NA",$E$3+I31) -> 0.075966657 | I31: =IF(G31="NA","NA",G31*$E$6) -> 0.033666657 | J31: NR | K31: =C212 -> NA
A32: ='Sovereign Ratings (Moody''s,S&P)'!A25 -> Bulgaria | B32: =VLOOKUP(A32,'Regional lookup table'!$A$2:$B$162,2,FALSE()) -> Eastern Europe & Russia | C32: =VLOOKUP(A32,'Sovereign Ratings (Moody''s,S&P)'!$A$2:$D$158,4,FALSE()) -> Baa1 | D32: =VLOOKUP(C32,$J$10:$K$32,2,FALSE())/10000 -> 0.013583967 | E32: =$E$3+F32 -> 0.062993518 | F32: =IF($E$5="Yes",D32*$E$6,D32) -> 0.020693518 | G32: =VLOOKUP(A32,'10-year CDS Spreads'!$A$2:$D$158,4,FALSE()) -> 0.0063 | H32: =IF(I32="NA","NA",$E$3+I32) -> 0.051897282 | I32: =IF(G32="NA","NA",G32*$E$6) -> 0.0095972822
A33: ='Sovereign Ratings (Moody''s,S&P)'!A26 -> Burkina Faso | B33: =VLOOKUP(A33,'Regional lookup table'!$A$2:$B$162,2,FALSE()) -> Africa | C33: =VLOOKUP(A33,'Sovereign Ratings (Moody''s,S&P)'!$A$2:$D$158,4,FALSE()) -> Caa1 | D33: =VLOOKUP(C33,$J$10:$K$32,2,FALSE())/10000 -> 0.063724785 | E33: =$E$3+F33 -> 0.13937694 | F33: =IF($E$5="Yes",D33*$E$6,D33) -> 0.097076943 | G33: =VLOOKUP(A33,'10-year CDS Spreads'!$A$2:$D$158,4,FALSE()) -> NA | H33: =IF(I33="NA","NA",$E$3+I33) -> NA | I33: =IF(G33="NA","NA",G33*$E$6) -> NA
A34: ='Sovereign Ratings (Moody''s,S&P)'!A27 -> Cambodia | B34: =VLOOKUP(A34,'Regional lookup table'!$A$2:$B$162,2,FALSE()) -> Asia | C34: =VLOOKUP(A34,'Sovereign Ratings (Moody''s,S&P)'!$A$2:$D$158,4,FALSE()) -> B2 | D34: =VLOOKUP(C34,$J$10:$K$32,2,FALSE())/10000 -> 0.046744826 | E34: =$E$3+F34 -> 0.11351005 | F34: =IF($E$5="Yes",D34*$E$6,D34) -> 0.071210046 | G34: =VLOOKUP(A34,'10-year CDS Spreads'!$A$2:$D$158,4,FALSE()) -> NA | H34: =IF(I34="NA","NA",$E$3+I34) -> NA | I34: =IF(G34="NA","NA",G34*$E$6) -> NA
A35: ='Sovereign Ratings (Moody''s,S&P)'!A28 -> Cameroon | B35: =VLOOKUP(A35,'Regional lookup table'!$A$2:$B$162,2,FALSE()) -> Africa | C35: =VLOOKUP(A35,'Sovereign Ratings (Moody''s,S&P)'!$A$2:$D$158,4,FALSE()) -> Caa1 | D35: =VLOOKUP(C35,$J$10:$K$32,2,FALSE())/10000 -> 0.063724785 | E35: =$E$3+F35 -> 0.13937694 | F35: =IF($E$5="Yes",D35*$E$6,D35) -> 0.097076943 | G35: =VLOOKUP(A35,'10-year CDS Spreads'!$A$2:$D$158,4,FALSE()) -> 0.0673 | H35: =IF(I35="NA","NA",$E$3+I35) -> 0.14482335 | I35: =IF(G35="NA","NA",G35*$E$6) -> 0.10252335
A36: ='Sovereign Ratings (Moody''s,S&P)'!A29 -> Canada | B36: =VLOOKUP(A36,'Regional lookup table'!$A$2:$B$162,2,FALSE()) -> North America | C36: =VLOOKUP(A36,'Sovereign Ratings (Moody''s,S&P)'!$A$2:$D$158,4,FALSE()) -> Aaa | D36: =VLOOKUP(C36,$J$10:$K$32,2,FALSE())/10000 -> 0 | E36: =$E$3+F36 -> 0.0423 | F36: =IF($E$5="Yes",D36*$E$6,D36) -> 0 | G36: =VLOOKUP(A36,'10-year CDS Spreads'!$A$2:$D$158,4,FALSE()) -> 0.0019 | H36: =IF(I36="NA","NA",$E$3+I36) -> 0.045194418 | I36: =IF(G36="NA","NA",G36*$E$6) -> 0.0028944185
A37: ='Sovereign Ratings (Moody''s,S&P)'!A30 -> Cape Verde | B37: =VLOOKUP(A37,'Regional lookup table'!$A$2:$B$162,2,FALSE()) -> Africa | C37: =VLOOKUP(A37,'Sovereign Ratings (Moody''s,S&P)'!$A$2:$D$158,4,FALSE()) -> B2 | D37: =VLOOKUP(C37,$J$10:$K$32,2,FALSE())/10000 -> 0.046744826 | E37: =$E$3+F37 -> 0.11351005 | F37: =IF($E$5="Yes",D37*$E$6,D37) -> 0.071210046 | G37: =VLOOKUP(A37,'10-year CDS Spreads'!$A$2:$D$158,4,FALSE()) -> NA | H37: =IF(I37="NA","NA",$E$3+I37) -> NA | I37: =IF(G37="NA","NA",G37*$E$6) -> NA
A38: ='Sovereign Ratings (Moody''s,S&P)'!A31 -> Cayman Islands | B38: =VLOOKUP(A38,'Regional lookup table'!$A$2:$B$162,2,FALSE()) -> Caribbean | C38: =VLOOKUP(A38,'Sovereign Ratings (Moody''s,S&P)'!$A$2:$D$158,4,FALSE()) -> Aa3 | D38: =VLOOKUP(C38,$J$10:$K$32,2,FALSE())/10000 -> 0.0050939875 | E38: =$E$3+F38 -> 0.050060069 | F38: =IF($E$5="Yes",D38*$E$6,D38) -> 0.0077600691 | G38: =VLOOKUP(A38,'10-year CDS Spreads'!$A$2:$D$158,4,FALSE()) -> NA | H38: =IF(I38="NA","NA",$E$3+I38) -> NA | I38: =IF(G38="NA","NA",G38*$E$6) -> NA
A39: ='Sovereign Ratings (Moody''s,S&P)'!A32 -> Chile | B39: =VLOOKUP(A39,'Regional lookup table'!$A$2:$B$162,2,FALSE()) -> Central and South America | C39: =VLOOKUP(A39,'Sovereign Ratings (Moody''s,S&P)'!$A$2:$D$158,4,FALSE()) -> A2 | D39: =VLOOKUP(C39,$J$10:$K$32,2,FALSE())/10000 -> 0.0071915117 | E39: =$E$3+F39 -> 0.053255392 | F39: =IF($E$5="Yes",D39*$E$6,D39) -> 0.010955392 | G39: =VLOOKUP(A39,'10-year CDS Spreads'!$A$2:$D$158,4,FALSE()) -> 0.0073 | H39: =IF(I39="NA","NA",$E$3+I39) -> 0.05342066 | I39: =IF(G39="NA","NA",G39*$E$6) -> 0.01112066
A40: ='Sovereign Ratings (Moody''s,S&P)'!A33 -> China | B40: =VLOOKUP(A40,'Regional lookup table'!$A$2:$B$162,2,FALSE()) -> Asia | C40: =VLOOKUP(A40,'Sovereign Ratings (Moody''s,S&P)'!$A$2:$D$158,4,FALSE()) -> A1 | D40: =VLOOKUP(C40,$J$10:$K$32,2,FALSE())/10000 -> 0.0059929264 | E40: =$E$3+F40 -> 0.051429493 | F40: =IF($E$5="Yes",D40*$E$6,D40) -> 0.0091294931 | G40: =VLOOKUP(A40,'10-year CDS Spreads'!$A$2:$D$158,4,FALSE()) -> 0.005 | H40: =IF(I40="NA","NA",$E$3+I40) -> 0.049916891 | I40: =IF(G40="NA","NA",G40*$E$6) -> 0.0076168907
A41: ='Sovereign Ratings (Moody''s,S&P)'!A34 -> Colombia | B41: =VLOOKUP(A41,'Regional lookup table'!$A$2:$B$162,2,FALSE()) -> Central and South America | C41: =VLOOKUP(A41,'Sovereign Ratings (Moody''s,S&P)'!$A$2:$D$158,4,FALSE()) -> Baa3 | D41: =VLOOKUP(C41,$J$10:$K$32,2,FALSE())/10000 -> 0.018677954 | E41: =$E$3+F41 -> 0.070753587 | F41: =IF($E$5="Yes",D41*$E$6,D41) -> 0.028453587 | G41: =VLOOKUP(A41,'10-year CDS Spreads'!$A$2:$D$158,4,FALSE()) -> 0.032 | H41: =IF(I41="NA","NA",$E$3+I41) -> 0.0910481 | I41: =IF(G41="NA","NA",G41*$E$6) -> 0.0487481
A42: ='Sovereign Ratings (Moody''s,S&P)'!A35 -> Congo (Democratic Republic of) | B42: =VLOOKUP(A42,'Regional lookup table'!$A$2:$B$162,2,FALSE()) -> Africa | C42: =VLOOKUP(A42,'Sovereign Ratings (Moody''s,S&P)'!$A$2:$D$158,4,FALSE()) -> B3 | D42: =VLOOKUP(C42,$J$10:$K$32,2,FALSE())/10000 -> 0.055234805 | E42: =$E$3+F42 -> 0.12644349 | F42: =IF($E$5="Yes",D42*$E$6,D42) -> 0.084143495 | G42: =VLOOKUP(A42,'10-year CDS Spreads'!$A$2:$D$158,4,FALSE()) -> NA | H42: =IF(I42="NA","NA",$E$3+I42) -> NA | I42: =IF(G42="NA","NA",G42*$E$6) -> NA
A43: ='Sovereign Ratings (Moody''s,S&P)'!A36 -> Congo (Republic of) | B43: =VLOOKUP(A43,'Regional lookup table'!$A$2:$B$162,2,FALSE()) -> Africa | C43: =VLOOKUP(A43,'Sovereign Ratings (Moody''s,S&P)'!$A$2:$D$158,4,FALSE()) -> Caa2 | D43: =VLOOKUP(C43,$J$10:$K$32,2,FALSE())/10000 -> 0.076509694 | E43: =$E$3+F43 -> 0.1588532 | F43: =IF($E$5="Yes",D43*$E$6,D43) -> 0.1165532 | G43: =VLOOKUP(A43,'10-year CDS Spreads'!$A$2:$D$158,4,FALSE()) -> NA | H43: =IF(I43="NA","NA",$E$3+I43) -> NA | I43: =IF(G43="NA","NA",G43*$E$6) -> NA
... A159: ='Sovereign Ratings (Moody''s,S&P)'!A152 -> United Kingdom | B159: =VLOOKUP(A159,'Regional lookup table'!$A$2:$B$162,2,FALSE()) -> Western Europe | C159: =VLOOKUP(A159,'Sovereign Ratings (Moody''s,S&P)'!$A$2:$D$158,4,FALSE()) -> Aa3 | D159: =VLOOKUP(C159,$J$10:$K$32,2,FALSE())/10000 -> 0.0050939875 | E159: =$E$3+F159 -> 0.050060069 | F159: =IF($E$5="Yes",D159*$E$6,D159) -> 0.0077600691 | G159: =VLOOKUP(A159,'10-year CDS Spreads'!$A$2:$D$158,4,FALSE()) -> 0.0023 | H159: =IF(I159="NA","NA",$E$3+I159) -> 0.04580377 | I159: =IF(G159="NA","NA",G159*$E$6) -> 0.0035037697
A160: ='Sovereign Ratings (Moody''s,S&P)'!A153 -> United States | B160: =VLOOKUP(A160,'Regional lookup table'!$A$2:$B$162,2,FALSE()) -> North America | C160: =VLOOKUP(A160,'Sovereign Ratings (Moody''s,S&P)'!$A$2:$D$158,4,FALSE()) -> Aa1 | D160: =VLOOKUP(C160,$J$10:$K$32,2,FALSE())/10000 -> 0.0023336792 | E160: =E4 -> 0.0446 | F160: =IF($E$5="Yes",D160,D160) -> 0.0023336792 | G160: =VLOOKUP(A160,'10-year CDS Spreads'!$A$2:$D$158,4,FALSE()) -> 0.003 | H160: =IF(I160="NA","NA",$E$3+I160) -> 0.046870134 | I160: =IF(G160="NA","NA",G160*$E$6) -> 0.0045701344
A161: ='Sovereign Ratings (Moody''s,S&P)'!A154 -> Uruguay | B161: =VLOOKUP(A161,'Regional lookup table'!$A$2:$B$162,2,FALSE()) -> Central and South America | C161: =VLOOKUP(A161,'Sovereign Ratings (Moody''s,S&P)'!$A$2:$D$158,4,FALSE()) -> Baa1 | D161: =VLOOKUP(C161,$J$10:$K$32,2,FALSE())/10000 -> 0.013583967 | E161: =$E$3+F161 -> 0.062993518 | F161: =IF($E$5="Yes",D161*$E$6,D161) -> 0.020693518 | G161: =VLOOKUP(A161,'10-year CDS Spreads'!$A$2:$D$158,4,FALSE()) -> 0.0063 | H161: =IF(I161="NA","NA",$E$3+I161) -> 0.051897282 | I161: =IF(G161="NA","NA",G161*$E$6) -> 0.0095972822
A162: ='Sovereign Ratings (Moody''s,S&P)'!A155 -> Uzbekistan | B162: =VLOOKUP(A162,'Regional lookup table'!$A$2:$B$162,2,FALSE()) -> Eastern Europe & Russia | C162: =VLOOKUP(A162,'Sovereign Ratings (Moody''s,S&P)'!$A$2:$D$158,4,FALSE()) -> Ba3 | D162: =VLOOKUP(C162,$J$10:$K$32,2,FALSE())/10000 -> 0.030563925 | E162: =$E$3+F162 -> 0.088860415 | F162: =IF($E$5="Yes",D162*$E$6,D162) -> 0.046560415 | G162: =VLOOKUP(A162,'10-year CDS Spreads'!$A$2:$D$158,4,FALSE()) -> #N/A | H162: =IF(I162="NA","NA",$E$3+I162) -> #N/A | I162: =IF(G162="NA","NA",G162*$E$6) -> #N/A
A163: ='Sovereign Ratings (Moody''s,S&P)'!A156 -> Venezuela | B163: =VLOOKUP(A163,'Regional lookup table'!$A$2:$B$162,2,FALSE()) -> Central and South America | C163: =VLOOKUP(A163,'Sovereign Ratings (Moody''s,S&P)'!$A$2:$D$158,4,FALSE()) -> C | D163: =VLOOKUP(C163,$J$10:$K$32,2,FALSE())/10000 -> 0.175 | E163: =$E$3+F163 -> 0.30889117 | F163: =IF($E$5="Yes",D163*$E$6,D163) -> 0.26659117 | G163: =VLOOKUP(A163,'10-year CDS Spreads'!$A$2:$D$158,4,FALSE()) -> 0.0915 | H163: =IF(I163="NA","NA",$E$3+I163) -> 0.1816891 | I163: =IF(G163="NA","NA",G163*$E$6) -> 0.1393891
A164: ='Sovereign Ratings (Moody''s,S&P)'!A157 -> Vietnam | B164: =VLOOKUP(A164,'Regional lookup table'!$A$2:$B$162,2,FALSE()) -> Asia | C164: =VLOOKUP(A164,'Sovereign Ratings (Moody''s,S&P)'!$A$2:$D$158,4,FALSE()) -> Ba2 | D164: =VLOOKUP(C164,$J$10:$K$32,2,FALSE())/10000 -> 0.025569819 | E164: =$E$3+F164 -> 0.081252504 | F164: =IF($E$5="Yes",D164*$E$6,D164) -> 0.038952504 | G164: =VLOOKUP(A164,'10-year CDS Spreads'!$A$2:$D$158,4,FALSE()) -> 0.0137 | H164: =IF(I164="NA","NA",$E$3+I164) -> 0.06317028 | I164: =IF(G164="NA","NA",G164*$E$6) -> 0.02087028
A165: ='Sovereign Ratings (Moody''s,S&P)'!A158 -> Zambia | B165: =VLOOKUP(A165,'Regional lookup table'!$A$2:$B$162,2,FALSE()) -> Africa | C165: =VLOOKUP(A165,'Sovereign Ratings (Moody''s,S&P)'!$A$2:$D$158,4,FALSE()) -> Caa2 | D165: =VLOOKUP(C165,$J$10:$K$32,2,FALSE())/10000 -> 0.076509694 | E165: =$E$3+F165 -> 0.1588532 | F165: =IF($E$5="Yes",D165*$E$6,D165) -> 0.1165532 | G165: =VLOOKUP(A165,'10-year CDS Spreads'!$A$2:$D$158,4,FALSE()) -> 0.0394 | H165: =IF(I165="NA","NA",$E$3+I165) -> 0.1023211 | I165: =IF(G165="NA","NA",G165*$E$6) -> 0.060021098
A166: Frontier Markets (no sovereign ratings)
A167: Country | B167: PRS Composite Risk Score | C167: ERP | D167: CRP | E167: Default Spread
A168: ='PRS Worksheet'!A162 -> Algeria | B168: ='PRS Worksheet'!B162 -> 67 | C168: ='PRS Worksheet'!E162 -> 0.1005766 | D168: ='PRS Worksheet'!G162 -> 0.058276598 | E168: ='PRS Worksheet'!D162 -> 0.038254847
A169: ='PRS Worksheet'!A163 -> Brunei | B169: ='PRS Worksheet'!B163 -> 80.75 | C169: ='PRS Worksheet'!E163 -> 0.050060069 | D169: ='PRS Worksheet'!G163 -> 0.0077600691 | E169: ='PRS Worksheet'!D163 -> 0.0050939875
A170: ='PRS Worksheet'!A164 -> Gambia | B170: ='PRS Worksheet'!B164 -> 65.5 | C170: ='PRS Worksheet'!E164 -> 0.11351005 | D170: ='PRS Worksheet'!G164 -> 0.071210046 | E170: ='PRS Worksheet'!D164 -> 0.046744826
A171: ='PRS Worksheet'!A165 -> Guinea | B171: ='PRS Worksheet'!B165 -> 59.5 | C171: ='PRS Worksheet'!E165 -> 0.1588532 | D171: ='PRS Worksheet'!G165 -> 0.1165532 | E171: ='PRS Worksheet'!D165 -> 0.076509694
A172: ='PRS Worksheet'!A166 -> Guinea-Bissau | B172: ='PRS Worksheet'!B166 -> 60.75 | C172: ='PRS Worksheet'!E166 -> 0.13937694 | D172: ='PRS Worksheet'!G166 -> 0.097076943 | E172: ='PRS Worksheet'!D166 -> 0.063724785
A173: ='PRS Worksheet'!A167 -> Guyana | B173: ='PRS Worksheet'!B167 -> 75.5 | C173: ='PRS Worksheet'!E167 -> 0.062993518 | D173: ='PRS Worksheet'!G167 -> 0.020693518 | E173: ='PRS Worksheet'!D167 -> 0.013583967
A174: ='PRS Worksheet'!A168 -> Haiti | B174: ='PRS Worksheet'!B168 -> 56.75 | C174: ='PRS Worksheet'!E168 -> 0.17178664 | D174: ='PRS Worksheet'!G168 -> 0.12948664 | E174: ='PRS Worksheet'!D168 -> 0.084999673
A175: ='PRS Worksheet'!A169 -> Iran | B175: ='PRS Worksheet'!B169 -> 61.25 | C175: ='PRS Worksheet'!E169 -> 0.13937694 | D175: ='PRS Worksheet'!G169 -> 0.097076943 | E175: ='PRS Worksheet'!D169 -> 0.063724785
A176: ='PRS Worksheet'!A170 -> Korea, D.P.R. | B176: ='PRS Worksheet'!B170 -> 51 | C176: ='PRS Worksheet'!E170 -> 0.19765354 | D176: ='PRS Worksheet'!G170 -> 0.15535354 | E176: ='PRS Worksheet'!D170 -> 0.10197963
A177: ='PRS Worksheet'!A171 -> Liberia | B177: ='PRS Worksheet'!B171 -> 57.75 | C177: ='PRS Worksheet'!E171 -> 0.1588532 | D177: ='PRS Worksheet'!G171 -> 0.1165532 | E177: ='PRS Worksheet'!D171 -> 0.076509694
A178: ='PRS Worksheet'!A172 -> Libya | B178: ='PRS Worksheet'!B172 -> 71.5 | C178: ='PRS Worksheet'!E172 -> 0.081252504 | D178: ='PRS Worksheet'!G172 -> 0.038952504 | E178: ='PRS Worksheet'!D172 -> 0.025569819
A179: ='PRS Worksheet'!A173 -> Madagascar | B179: ='PRS Worksheet'!B173 -> 62.5 | C179: ='PRS Worksheet'!E173 -> 0.12644349 | D179: ='PRS Worksheet'!G173 -> 0.084143495 | E179: ='PRS Worksheet'!D173 -> 0.055234805
... A188: ='PRS Worksheet'!A182 -> Zimbabwe | B188: ='PRS Worksheet'!B182 -> 58.5 | C188: ='PRS Worksheet'!E182 -> 0.1588532 | D188: ='PRS Worksheet'!G182 -> 0.1165532 | E188: ='PRS Worksheet'!D182 -> 0.076509694
B190: Rating | C190: Default spread in basis points
B191: A1 | C191: ='Default Spreads for Ratings'!C2 -> 59.929264
B192: A2 | C192: ='Default Spreads for Ratings'!C3 -> 71.915117
B193: A3 | C193: ='Default Spreads for Ratings'!C4 -> 101.87975
B194: Aa1 | C194: ='Default Spreads for Ratings'!C5 -> 23.336792
B195: Aa2 | C195: ='Default Spreads for Ratings'!C6 -> 41.950485
B196: Aa3 | C196: ='Default Spreads for Ratings'!C7 -> 50.939875
B197: Aaa | C197: ='Default Spreads for Ratings'!C8 -> 0
B198: B1 | C198: ='Default Spreads for Ratings'!C9 -> 382.54847
B199: B2 | C199: ='Default Spreads for Ratings'!C10 -> 467.44826
B200: B3 | C200: ='Default Spreads for Ratings'!C11 -> 552.34805
B201: Ba1 | C201: ='Default Spreads for Ratings'!C12 -> 212.74889
B202: Ba2 | C202: ='Default Spreads for Ratings'!C13 -> 255.69819
... B206: Baa3 | C206: ='Default Spreads for Ratings'!C17 -> 186.77954
B207: C | C207: 1750
B208: Ca | C208: ='Default Spreads for Ratings'!C18 -> 1019.7963
B209: Caa1 | C209: ='Default Spreads for Ratings'!C19 -> 637.24785
B210: Caa2 | C210: ='Default Spreads for Ratings'!C20 -> 765.09694
B211: Caa3 | C211: ='Default Spreads for Ratings'!C21 -> 849.99673
B212: NR | C212: NA

Sheet Relative Equity Volatility
A1: Year | B1: Std Dev (BMI) | C1: Std Dev (JPM Sov Bond) | D1: REL VOL | J1: Estimation note: Those of you who have followed my attempts to estimate the relative equity market volatility know that I have struggled with getting a proxy for returns on emerging market sovereign bonds, and have used the coefficient of varation in yields to make that estimate. I have finally replaced that estimate with a return on an emerging market government bond ETF from iShares. The standard deviations are now computed consistently for emerigng equities and emerigng government bonds. (Using the old yield coefficient of variation approach would have yielded a ratio of 1.49 in this computation.)
A2: 2021 | B2: =STDEV(I15:I276)*(261^0.5) -> 0.14315335 | C2: =STDEV(C15:C267)*(252^0.5) -> 0.068728637 | D2: =B2/C2 -> 2.0828778
A3: 2022 | B3: =STDEV(I277:I536)*(259^0.5) -> 0.18634568 | C3: =STDEV(C268:C518)*(250^0.5) -> 0.15379759 | D3: =B3/C3 -> 1.2116294
A4: 2023 | B4: =STDEV(I537:I796)*(259^0.5) -> 0.11141327 | C4: =STDEV(C519:C768)*(249^0.5) -> 0.098673761 | D4: =B4/C4 -> 1.1291074
A5: 2024 | B5: =STDEV(I797:I1058)*(261^0.5) -> 0.11865915 | C5: =STDEV(C769:C1020)*(251^0.5) -> 0.074136944 | D5: =B5/C5 -> 1.60054
A6: 2025 | B6: =STDEV(I1059:I1319)*(260^0.5) -> 0.14611177 | C6: =STDEV(C1021:C1270)*(249^0.5) -> 0.067898827 | D6: =B6/C6 -> 2.1519042
A7: Average Relative Volatility | B7: =AVERAGE(B2:B6) -> 0.14113664 | C7: =AVERAGE(C2:C6) -> 0.092647151 | D7: =B7/C7 -> 1.5233781
A9: Index: | B9: iShares JP Morgan USD Emerging Markets Bond ETF | G9: Index: | H9: S&P Emerging BMI Index
A10: Source: | B10: Yahoo! | G10: Source: | H10: S&P
B11: https://finance.yahoo.com/quote/EMB/ | H11: https://www.spglobal.com/spdji/en/indices/equity/sp-emerging-bmi/#overview
A12: Period | B12: Five years | C12: (Dec 31, 2020 - Dec 31, 2025) | G12: Period | H12: Five years | I12: (Dec 31, 2020 - Dec 31, 2025)
A13: Interval | B13: Daily | G13: Interval | H13: Daily
A14: Date | B14: Close | C14: Return | G14: Effective date | H14: S&P Emerging BMI (USD) | I14: Return
A15: 42734 | B15: 115.91 | G15: 42734 | H15: 331.34
A16: 42738 | B16: 115.27 | C16: =B16/B15-1 -> -0.0055215253 | G16: 42735 | H16: 331.57 | I16: =H16/H15-1 -> 0.00069415102
A17: 42739 | B17: 115.35 | C17: =B17/B16-1 -> 0.00069402273 | G17: 42738 | H17: 334.34 | I17: =H17/H16-1 -> 0.0083541937
A18: 42740 | B18: 114.52 | C18: =B18/B17-1 -> -0.007195492 | G18: 42739 | H18: 337.8 | I18: =H18/H17-1 -> 0.010348747
A19: 42741 | B19: 114.48 | C19: =B19/B18-1 -> -0.00034928397 | G19: 42740 | H19: 336.87 | I19: =H19/H18-1 -> -0.0027531083
A20: 42742 | B20: 114.54 | C20: =B20/B19-1 -> 0.00052410901 | G20: 42741 | H20: 337.98 | I20: =H20/H19-1 -> 0.0032950396
A21: 42745 | B21: 113.64 | C21: =B21/B20-1 -> -0.007857517 | G21: 42742 | H21: 343.78 | I21: =H21/H20-1 -> 0.017160779
A22: 42746 | B22: 113.1 | C22: =B22/B21-1 -> -0.0047518479 | G22: 42745 | H22: 342.48 | I22: =H22/H21-1 -> -0.0037814882
A23: 42747 | B23: 113.63 | C23: =B23/B22-1 -> 0.0046861185 | G23: 42746 | H23: 344.33 | I23: =H23/H22-1 -> 0.0054017753
A24: 42748 | B24: 113.3 | C24: =B24/B23-1 -> -0.0029041626 | G24: 42747 | H24: 346.61 | I24: =H24/H23-1 -> 0.0066215549
A25: 42749 | B25: 113.43 | C25: =B25/B24-1 -> 0.0011473963 | G25: 42748 | H25: 348.89 | I25: =H25/H24-1 -> 0.0065779983
A26: 42753 | B26: 113.59 | C26: =B26/B25-1 -> 0.0014105616 | G26: 42749 | H26: 346.19 | I26: =H26/H25-1 -> -0.0077388289
A27: 42754 | B27: 113.72 | C27: =B27/B26-1 -> 0.0011444669 | G27: 42752 | H27: 347.78 | I27: =H27/H26-1 -> 0.0045928536
... A1270: 44560 | B1270: 96.28 | C1270: =B1270/B1269-1 -> -0.0019695242 | G1270: 44491 | H1270: 368.92 | I1270: =H1270/H1269-1 -> 0.0026634777
G1271: 44492 | H1271: 370.04 | I1271: =H1271/H1270-1 -> 0.0030358885
G1272: 44495 | H1272: 373.91 | I1272: =H1272/H1271-1 -> 0.010458329
G1273: 44496 | H1273: 373.25 | I1273: =H1273/H1272-1 -> -0.0017651306
G1274: 44497 | H1274: 375.51 | I1274: =H1274/H1273-1 -> 0.006054923
G1275: 44498 | H1275: 373.69 | I1275: =H1275/H1274-1 -> -0.0048467418
G1276: 44499 | H1276: 370.73 | I1276: =H1276/H1275-1 -> -0.007921004
G1277: 44502 | H1277: 371.77 | I1277: =H1277/H1276-1 -> 0.0028052761
G1278: 44503 | H1278: 368.33 | I1278: =H1278/H1277-1 -> -0.0092530328
G1279: 44504 | H1279: 367.59 | I1279: =H1279/H1278-1 -> -0.002009068
G1280: 44505 | H1280: 370.25 | I1280: =H1280/H1279-1 -> 0.0072363231
G1281: 44506 | H1281: 367.93 | I1281: =H1281/H1280-1 -> -0.0062660365
G1282: 44509 | H1282: 371.25 | I1282: =H1282/H1281-1 -> 0.0090234555
... G1319: 44560 | H1319: 369.16 | I1319: =H1319/H1318-1 -> 0.0018182312

Sheet Regional Simple Averages
B3: Data
A4: Region | B4: Average of Adj. Default Spread | C4: Average of Country Risk Premium | D4: Average of Equity Risk Premium | E4: Average of Corporate Tax Rate
A5: Africa | B5: 0.054199361 | C5: 0.082566121 | D5: 0.12486612 | E5: 0.27590667
A6: Asia | B6: 0.031733378 | C6: 0.048341934 | D6: 0.090641934 | E6: 0.240475
A7: Australia & New Zealand | B7: 0.012751616 | C7: 0.019425533 | D7: 0.061725533 | E7: 0.26
A8: Caribbean | B8: 0.03081363 | C8: 0.04694081 | D8: 0.08924081 | E8: 0.17714286
A9: Central and South America | B9: 0.045688523 | C9: 0.069600897 | D9: 0.1119009 | E9: 0.27131579
A10: Eastern Europe & Russia | B10: 0.032942139 | C10: 0.050183334 | D10: 0.092483334 | E10: 0.16423077
A11: Middle East | B11: 0.031033106 | C11: 0.047275155 | D11: 0.089575155 | E11: 0.14683077
A12: North America | B12: 0.0011668396 | C12: 0.0011668396 | D12: 0.04345 | E12: 0.2557
A13: Western Europe | B13: 0.0063068969 | C13: 0.0096077888 | D13: 0.051907789 | E13: 0.19943077
A14: Total Result | B14: 0.032812411 | C14: 0.04997793 | D14: 0.092277715 | E14: 0.21871975

Sheet Regional Weighted Averages
A1: Country | B1: GDP (in millions) in 2024 | C1: Moody's rating | D1: Adj. Default Spread | E1: Equity Risk Premium | F1: Country Risk Premium | G1: Corporate Tax Rate | H1: Region | I1: GDP Weight | J1: Weight*Default Spread | K1: Weight*ERP | L1: Weight*CRP | M1: Weight * Tax Rate
A2: Angola | B2: 100998.92 | C2: B3 | D2: 0.055234805 | E2: =F2+4.23% -> 0.12644349 | F2: 0.084143495 | G2: 0.25 | H2: Africa | I2: =B2/$B$32 -> 0.043145792 | J2: =I2*D2 -> 0.0023831494 | K2: =I2*E2 -> 0.0054555048 | L2: =I2*F2 -> 0.0036304378 | M2: =I2*G2 -> 0.010786448
A3: Benin | B3: 21482.644 | C3: B1 | D3: 0.038254847 | E3: =F3+4.23% -> 0.1005766 | F3: 0.058276598 | G3: 0.3 | H3: Africa | I3: =B3/$B$32 -> 0.0091771844 | J3: =I3*D3 -> 0.00035107179 | K3: =I3*E3 -> 0.00092300999 | L3: =I3*F3 -> 0.00053481508 | M3: =I3*G3 -> 0.0027531553
A4: Botswana | B4: 19402.064 | C4: Baa1 | D4: 0.013583967 | E4: =F4+4.23% -> 0.062993518 | F4: 0.020693518 | G4: 0.22 | H4: Africa | I4: =B4/$B$32 -> 0.00828838 | J4: =I4*D4 -> 0.00011258908 | K4: =I4*E4 -> 0.00052211421 | L4: =I4*F4 -> 0.00017151574 | M4: =I4*G4 -> 0.0018234436
A5: Burkina Faso | B5: 23124.73 | C5: Caa1 | D5: 0.063724785 | E5: =F5+4.23% -> 0.13937694 | F5: 0.097076943 | G5: 0.275 | H5: Africa | I5: =B5/$B$32 -> 0.0098786683 | J5: =I5*D5 -> 0.00062951601 | K5: =I5*E5 -> 0.0013768586 | L5: =I5*F5 -> 0.00095899092 | M5: =I5*G5 -> 0.0027166338
A6: Cameroon | B6: 53296.694 | C6: Caa1 | D6: 0.063724785 | E6: =F6+4.23% -> 0.13937694 | F6: 0.097076943 | G6: 0.33 | H6: Africa | I6: =B6/$B$32 -> 0.022767849 | J6: =I6*D6 -> 0.0014508763 | K6: =I6*E6 -> 0.0031733132 | L6: =I6*F6 -> 0.0022102332 | M6: =I6*G6 -> 0.0075133903
A7: Cape Verde | B7: 2725.4142 | C7: B2 | D7: 0.046744826 | E7: =F7+4.23% -> 0.11351005 | F7: 0.071210046 | G7: 0.2686 | H7: Africa | I7: =B7/$B$32 -> 0.0011642714 | J7: =I7*D7 -> 5.4423666e-05 | K7: =I7*E7 -> 0.0001321565 | L7: =I7*F7 -> 8.2907822e-05 | M7: =I7*G7 -> 0.00031272331
A8: Congo (Democratic Republic of) | B8: 70962.186 | C8: B3 | D8: 0.055234805 | E8: =F8+4.23% -> 0.12644349 | F8: 0.084143495 | G8: 0.3 | H8: Africa | I8: =B8/$B$32 -> 0.030314382 | J8: =I8*D8 -> 0.001674409 | K8: =I8*E8 -> 0.0038330564 | L8: =I8*F8 -> 0.002550758 | M8: =I8*G8 -> 0.0090943146
A9: Congo (Republic of) | B9: 15719.986 | C9: Caa2 | D9: 0.076509694 | E9: =F9+4.23% -> 0.1588532 | F9: 0.1165532 | G9: 0.2686 | H9: Africa | I9: =B9/$B$32 -> 0.006715431 | J9: =I9*D9 -> 0.00051379557 | K9: =I9*E9 -> 0.0010667677 | L9: =I9*F9 -> 0.00078270494 | M9: =I9*G9 -> 0.0018037648
A10: Côte d'Ivoire | B10: 87113.179 | C10: Ba2 | D10: 0.025569819 | E10: =F10+4.23% -> 0.081252504 | F10: 0.038952504 | G10: 0.25 | H10: Africa | I10: =B10/$B$32 -> 0.037213935 | J10: =I10*D10 -> 0.00095155361 | K10: =I10*E10 -> 0.0030237254 | L10: =I10*F10 -> 0.001449576 | M10: =I10*G10 -> 0.0093034838
A11: Egypt | B11: 389059.91 | C11: Caa1 | D11: 0.063724785 | E11: =F11+4.23% -> 0.13937694 | F11: 0.097076943 | G11: 0.225 | H11: Africa | I11: =B11/$B$32 -> 0.16620275 | J11: =I11*D11 -> 0.010591235 | K11: =I11*E11 -> 0.023164832 | L11: =I11*F11 -> 0.016134455 | M11: =I11*G11 -> 0.03739562
A12: Ethiopia | B12: 149740.3 | C12: Caa2 | D12: 0.076509694 | E12: =F12+4.23% -> 0.1588532 | F12: 0.1165532 | G12: 0.3 | H12: Africa | I12: =B12/$B$32 -> 0.063967655 | J12: =I12*D12 -> 0.0048941457 | K12: =I12*E12 -> 0.010161466 | L12: =I12*F12 -> 0.0074556345 | M12: =I12*G12 -> 0.019190296
A13: Gabon | B13: 20895.684 | C13: Caa2 | D13: 0.076509694 | E13: =F13+4.23% -> 0.1588532 | F13: 0.1165532 | G13: 0.3 | H13: Africa | I13: =B13/$B$32 -> 0.0089264409 | J13: =I13*D13 -> 0.00068295927 | K13: =I13*E13 -> 0.0014179937 | L13: =I13*F13 -> 0.0010404052 | M13: =I13*G13 -> 0.0026779323
... A31: Zambia | B31: 25303.185 | C31: Caa2 | D31: 0.076509694 | E31: =F31+4.23% -> 0.1588532 | F31: 0.1165532 | G31: 0.3 | H31: Africa | I31: =B31/$B$32 -> 0.010809284 | J31: =I31*D31 -> 0.00082701502 | K31: =I31*E31 -> 0.0017170893 | L31: =I31*F31 -> 0.0012598566 | M31: =I31*G31 -> 0.0032427852
A32: Africa | B32: =SUM(B2:B31) -> 2340875.2 | D32: =SUM(J2:J31) -> 0.050672304 | E32: =F32+4.23% -> 0.11949308 | F32: =SUM(L2:L31) -> 0.077193081 | G32: =SUM(M2:M31) -> 0.27390174 | I32: =SUM(I2:I31) -> 1
A33: Bangladesh | B33: 450119.43 | C33: B2 | D33: 0.046744826 | E33: =F33+4.23% -> 0.11351005 | F33: 0.071210046 | G33: 0.275 | H33: Asia | I33: =B33/$B$57 -> 0.012959906 | J33: =I33*D33 -> 0.00060580856 | K33: =I33*E33 -> 0.0014710795 | L33: =I33*F33 -> 0.00092287551 | M33: =I33*G33 -> 0.0035639742
A34: Cambodia | B34: 46352.647 | C34: B2 | D34: 0.046744826 | E34: =F34+4.23% -> 0.11351005 | F34: 0.071210046 | G34: 0.2 | H34: Asia | I34: =B34/$B$57 -> 0.0013345924 | J34: =I34*D34 -> 6.2385288e-05 | K34: =I34*E34 -> 0.00015148964 | L34: =I34*F34 -> 9.5036383e-05 | M34: =I34*G34 -> 0.00026691847
A35: China | B35: 18743803 | C35: A1 | D35: 0.0059929264 | E35: =F35+4.23% -> 0.051429493 | F35: 0.0091294931 | G35: 0.25 | H35: Asia | I35: =B35/$B$57 -> 0.53967439 | J35: =I35*D35 -> 0.0032342289 | K35: =I35*E35 -> 0.02775518 | L35: =I35*F35 -> 0.0049269536 | M35: =I35*G35 -> 0.1349186
A36: Fiji | B36: 5968.1259 | C36: B1 | D36: 0.038254847 | E36: =F36+4.23% -> 0.1005766 | F36: 0.058276598 | G36: 0.25 | H36: Asia | I36: =B36/$B$57 -> 0.00017183517 | J36: =I36*D36 -> 6.5735283e-06 | K36: =I36*E36 -> 1.7282597e-05 | L36: =I36*F36 -> 1.0013969e-05 | M36: =I36*G36 -> 4.2958794e-05
A37: Hong Kong | B37: 406863.4 | C37: Aa3 | D37: 0.0050939875 | E37: =F37+4.23% -> 0.050060069 | F37: 0.0077600691 | G37: 0.165 | H37: Asia | I37: =B37/$B$57 -> 0.011714472 | J37: =I37*D37 -> 5.9673373e-05 | K37: =I37*E37 -> 0.00058642727 | L37: =I37*F37 -> 9.0905111e-05 | M37: =I37*G37 -> 0.0019328879
A38: India | B38: 3909891.5 | C38: Baa3 | D38: 0.018677954 | E38: =F38+4.23% -> 0.070753587 | F38: 0.028453587 | G38: 0.3 | H38: Asia | I38: =B38/$B$57 -> 0.11257418 | J38: =I38*D38 -> 0.0021026554 | K38: =I38*E38 -> 0.0079650272 | L38: =I38*F38 -> 0.0032031393 | M38: =I38*G38 -> 0.033772255
A39: Indonesia | B39: 1396300.1 | C39: Baa2 | D39: 0.016180901 | E39: =F39+4.23% -> 0.066949631 | F39: 0.024649631 | G39: 0.22 | H39: Asia | I39: =B39/$B$57 -> 0.040202481 | J39: =I39*D39 -> 0.00065051239 | K39: =I39*E39 -> 0.0026915413 | L39: =I39*F39 -> 0.00099097635 | M39: =I39*G39 -> 0.0088445459
A40: Japan | B40: 4027597.5 | C40: A1 | D40: 0.0059929264 | E40: =F40+4.23% -> 0.051429493 | F40: 0.0091294931 | G40: 0.2974 | H40: Asia | I40: =B40/$B$57 -> 0.11596319 | J40: =I40*D40 -> 0.00069495887 | K40: =I40*E40 -> 0.0059639281 | L40: =I40*F40 -> 0.0010586851 | M40: =I40*G40 -> 0.034487453
A41: Korea | B41: 1875388.2 | C41: Aa2 | D41: 0.0041950485 | E41: =F41+4.23% -> 0.048690645 | F41: 0.0063906452 | G41: 0.264 | H41: Asia | I41: =B41/$B$57 -> 0.053996458 | J41: =I41*D41 -> 0.00022651776 | K41: =I41*E41 -> 0.0026291224 | L41: =I41*F41 -> 0.0003450722 | M41: =I41*G41 -> 0.014255065
A42: Laos | B42: 16502.933 | C42: Caa2 | D42: 0.076509694 | E42: =F42+4.23% -> 0.1588532 | F42: 0.1165532 | G42: 0.2 | H42: Asia | I42: =B42/$B$57 -> 0.00047515492 | J42: =I42*D42 -> 3.6353958e-05 | K42: =I42*E42 -> 7.5479877e-05 | L42: =I42*F42 -> 5.5380824e-05 | M42: =I42*G42 -> 9.5030984e-05
A43: Macao | B43: 49467.259 | C43: Aa3 | D43: 0.0050939875 | E43: =F43+4.23% -> 0.050060069 | F43: 0.0077600691 | G43: 0.25 | H43: Asia | I43: =B43/$B$57 -> 0.0014242687 | J43: =I43*D43 -> 7.255207e-06 | K43: =I43*E43 -> 7.1298991e-05 | L43: =I43*F43 -> 1.1052424e-05 | M43: =I43*G43 -> 0.00035606718
A44: Malaysia | B44: 422227.01 | C44: A3 | D44: 0.010187975 | E44: =F44+4.23% -> 0.057820138 | F44: 0.015520138 | G44: 0.24 | H44: Asia | I44: =B44/$B$57 -> 0.012156823 | J44: =I44*D44 -> 0.00012385341 | K44: =I44*E44 -> 0.0007029092 | L44: =I44*F44 -> 0.00018867558 | M44: =I44*G44 -> 0.0029176376
... A56: Vietnam | B56: 476388.23 | C56: Ba2 | D56: 0.025569819 | E56: =F56+4.23% -> 0.081252504 | F56: 0.038952504 | G56: 0.2 | H56: Asia | I56: =B56/$B$57 -> 0.013716241 | J56: =I56*D56 -> 0.00035072181 | K56: =I56*E56 -> 0.0011144789 | L56: =I56*F56 -> 0.00053428194 | M56: =I56*G56 -> 0.0027432482
A57: Asia | B57: =SUM(B33:B56) -> 34731689 | D57: =SUM(J33:J56) -> 0.0097961467 | E57: =F57+4.23% -> 0.057223236 | F57: =SUM(L33:L56) -> 0.014923236 | G57: =SUM(M33:M56) -> 0.25654535 | I57: =SUM(I33:I56) -> 1
A58: Australia | B58: 1757022.5 | C58: Aaa | D58: 0 | E58: =F58+4.23% -> 0.0423 | F58: 0 | G58: 0.3 | H58: Australia & New Zealand | I58: =B58/$B$61 -> 0.87041254 | J58: =I58*D58 -> 0 | K58: =I58*E58 -> 0.036818451 | L58: =I58*F58 -> 0 | M58: =I58*G58 -> 0.26112376
A59: Cook Islands | B59: 1414 | C59: B1 | D59: 0.038254847 | E59: =F59+4.23% -> 0.1005766 | F59: 0.058276598 | G59: 0.2 | H59: Australia & New Zealand | I59: =B59/$B$61 -> 0.00070048242 | J59: =I59*D59 -> 2.6796848e-05 | K59: =I59*E59 -> 7.0452138e-05 | L59: =I59*F59 -> 4.0821732e-05 | M59: =I59*G59 -> 0.00014009648
A60: New Zealand | B60: 260172.39 | C60: Aaa | D60: 0 | E60: =F60+4.23% -> 0.0423 | F60: 0 | G60: 0.28 | H60: Australia & New Zealand | I60: =B60/$B$61 -> 0.12888697 | J60: =I60*D60 -> 0 | K60: =I60*E60 -> 0.005451919 | L60: =I60*F60 -> 0 | M60: =I60*G60 -> 0.036088353
A61: Australia & New Zealand | B61: =SUM(B58:B60) -> 2018608.8 | D61: =SUM(J58:J60) -> 2.6796848e-05 | E61: =F61+4.23% -> 0.042340822 | F61: =SUM(L58:L60) -> 4.0821732e-05 | G61: =SUM(M58:M60) -> 0.29735221 | I61: =SUM(I58:I60) -> 1
A62: Aruba | B62: 4265.6507 | C62: Baa3 | D62: 0.018677954 | E62: =F62+4.23% -> 0.070753587 | F62: 0.028453587 | G62: 0.22 | H62: Caribbean | I62: =B62/$B$76 -> 0.012264167 | J62: =I62*D62 -> 0.00022906955 | K62: =I62*E62 -> 0.00086773382 | L62: =I62*F62 -> 0.00034895955 | M62: =I62*G62 -> 0.0026981168
A63: Bahamas | B63: 15832.8 | C63: B1 | D63: 0.038254847 | E63: =F63+4.23% -> 0.1005766 | F63: 0.058276598 | G63: 0 | H63: Caribbean | I63: =B63/$B$76 -> 0.045520865 | J63: =I63*D63 -> 0.0017413937 | K63: =I63*E63 -> 0.0045783337 | L63: =I63*F63 -> 0.0026528011 | M63: =I63*G63 -> 0
A64: Barbados | B64: 7498.05 | C64: B2 | D64: 0.046744826 | E64: =F64+4.23% -> 0.11351005 | F64: 0.071210046 | G64: 0.09 | H64: Caribbean | I64: =B64/$B$76 -> 0.021557635 | J64: =I64*D64 -> 0.0010077079 | K64: =I64*E64 -> 0.0024470081 | L64: =I64*F64 -> 0.0015351202 | M64: =I64*G64 -> 0.0019401871
A65: Bermuda | B65: 9233.6 | C65: A2 | D65: 0.0071915117 | E65: =F65+4.23% -> 0.053255392 | F65: 0.010955392 | G65: 0 | H65: Caribbean | I65: =B65/$B$76 -> 0.026547512 | J65: =I65*D65 -> 0.00019091675 | K65: =I65*E65 -> 0.0014137982 | L65: =I65*F65 -> 0.0002908384 | M65: =I65*G65 -> 0
A66: Cayman Islands | B66: 7241.2443 | C66: Aa3 | D66: 0.0050939875 | E66: =F66+4.23% -> 0.050060069 | F66: 0.0077600691 | G66: 0 | H66: Caribbean | I66: =B66/$B$76 -> 0.020819293 | J66: =I66*D66 -> 0.00010605322 | K66: =I66*E66 -> 0.0010422152 | L66: =I66*F66 -> 0.00016155915 | M66: =I66*G66 -> 0
A67: Cuba | B67: 107352 | C67: Ca | D67: 0.10197963 | E67: =F67+4.23% -> 0.19765354 | F67: 0.15535354 | G67: 0.35 | H67: Caribbean | I67: =B67/$B$76 -> 0.30864761 | J67: =I67*D67 -> 0.031475769 | K67: =I67*E67 -> 0.061005293 | L67: =I67*F67 -> 0.047949499 | M67: =I67*G67 -> 0.10802666
A68: Curacao | B68: 3561.1782 | C68: Baa3 | D68: 0.018677954 | E68: =F68+4.23% -> 0.070753587 | F68: 0.028453587 | G68: 0.22 | H68: Caribbean | I68: =B68/$B$76 -> 0.010238739 | J68: =I68*D68 -> 0.0001912387 | K68: =I68*E68 -> 0.00072442752 | L68: =I68*F68 -> 0.00029132885 | M68: =I68*G68 -> 0.0022525226
A69: Dominican Republic | B69: 124282.25 | C69: Ba2 | D69: 0.025569819 | E69: =F69+4.23% -> 0.081252504 | F69: 0.038952504 | G69: 0.27 | H69: Caribbean | I69: =B69/$B$76 -> 0.35732374 | J69: =I69*D69 -> 0.0091367035 | K69: =I69*E69 -> 0.029033448 | L69: =I69*F69 -> 0.013918654 | M69: =I69*G69 -> 0.096477409
A70: Jamaica | B70: 22014.397 | C70: Ba3 | D70: 0.030563925 | E70: =F70+4.23% -> 0.088860415 | F70: 0.046560415 | G70: 0.25 | H70: Caribbean | I70: =B70/$B$76 -> 0.063293567 | J70: =I70*D70 -> 0.0019344998 | K70: =I70*E70 -> 0.0056242926 | L70: =I70*F70 -> 0.0029469747 | M70: =I70*G70 -> 0.015823392
A71: Montserrat | B71: 16199 | C71: Baa3 | D71: 0.018677954 | E71: =F71+4.23% -> 0.070753587 | F71: 0.028453587 | G71: 0.3 | H71: Caribbean | I71: =B71/$B$76 -> 0.046573726 | J71: =I71*D71 -> 0.00086990191 | K71: =I71*E71 -> 0.0032952581 | L71: =I71*F71 -> 0.0013251895 | M71: =I71*G71 -> 0.013972118
A72: St. Maarten | B72: 1797.8367 | C72: Ba2 | D72: 0.025569819 | E72: =F72+4.23% -> 0.081252504 | F72: 0.038952504 | G72: 0.2 | H72: Caribbean | I72: =B72/$B$76 -> 0.0051689581 | J72: =I72*D72 -> 0.00013216932 | K72: =I72*E72 -> 0.00041999079 | L72: =I72*F72 -> 0.00020134386 | M72: =I72*G72 -> 0.0010337916
A73: St. Vincent & the Grenadines | B73: 1157.2074 | C73: B3 | D73: 0.055234805 | E73: =F73+4.23% -> 0.12644349 | F73: 0.084143495 | G73: 0.28 | H73: Caribbean | I73: =B73/$B$76 -> 0.0033270856 | J73: =I73*D73 -> 0.00018377093 | K73: =I73*E73 -> 0.00042068834 | L73: =I73*F73 -> 0.00027995261 | M73: =I73*G73 -> 0.00093158398
... A75: Turks and Caicos Islands | B75: 1745.378 | C75: Baa1 | D75: 0.013583967 | E75: =F75+4.23% -> 0.062993518 | F75: 0.020693518 | G75: 0 | H75: Caribbean | I75: =B75/$B$76 -> 0.0050181342 | J75: =I75*D75 -> 6.8166168e-05 | K75: =I75*E75 -> 0.00031610993 | L75: =I75*F75 -> 0.00010384285 | M75: =I75*G75 -> 0
A76: Caribbean | B76: =SUM(B62:B75) -> 347814.13 | D76: =SUM(J62:J75) -> 0.04915183 | E76: =F76+4.23% -> 0.11717682 | F76: =SUM(L62:L75) -> 0.074876823 | G76: =SUM(M62:M75) -> 0.26526548 | I76: =SUM(I62:I75) -> 1 | L76: =SUM(L62:L75) -> 0.074876823
A77: Argentina | B77: 638365.46 | C77: Caa1 | D77: 0.063724785 | E77: =F77+4.23% -> 0.13937694 | F77: 0.097076943 | G77: 0.35 | H77: Central and South America | I77: =B77/$B$96 -> 0.097631986 | J77: =I77*D77 -> 0.0062215773 | K77: =I77*E77 -> 0.013607648 | L77: =I77*F77 -> 0.0094778147 | M77: =I77*G77 -> 0.034171195
A78: Belize | B78: 3203.6318 | C78: Caa1 | D78: 0.063724785 | E78: =F78+4.23% -> 0.13937694 | F78: 0.097076943 | G78: 0 | H78: Central and South America | I78: =B78/$B$96 -> 0.00048996532 | J78: =I78*D78 -> 3.1222934e-05 | K78: =I78*E78 -> 6.8289868e-05 | L78: =I78*F78 -> 4.7564335e-05 | M78: =I78*G78 -> 0
A79: Bolivia | B79: 54881.327 | C79: Ca | D79: 0.10197963 | E79: =F79+4.23% -> 0.19765354 | F79: 0.15535354 | G79: 0.25 | H79: Central and South America | I79: =B79/$B$96 -> 0.0083935823 | J79: =I79*D79 -> 0.00085597443 | K79: =I79*E79 -> 0.0016590213 | L79: =I79*F79 -> 0.0013039727 | M79: =I79*G79 -> 0.0020983956
A80: Brazil | B80: 2185821.6 | C80: Ba1 | D80: 0.021274889 | E80: =F80+4.23% -> 0.0747097 | F80: 0.0324097 | G80: 0.34 | H80: Central and South America | I80: =B80/$B$96 -> 0.33430084 | J80: =I80*D80 -> 0.0071122132 | K80: =I80*E80 -> 0.024975516 | L80: =I80*F80 -> 0.01083459 | M80: =I80*G80 -> 0.11366229
A81: Chile | B81: 330267.14 | C81: A2 | D81: 0.0071915117 | E81: =F81+4.23% -> 0.053255392 | F81: 0.010955392 | G81: 0.27 | H81: Central and South America | I81: =B81/$B$96 -> 0.050511249 | J81: =I81*D81 -> 0.00036325224 | K81: =I81*E81 -> 0.0026899963 | L81: =I81*F81 -> 0.00055337052 | M81: =I81*G81 -> 0.013638037
A82: Colombia | B82: 418818.15 | C82: Baa3 | D82: 0.018677954 | E82: =F82+4.23% -> 0.070753587 | F82: 0.028453587 | G82: 0.35 | H82: Central and South America | I82: =B82/$B$96 -> 0.064054293 | J82: =I82*D82 -> 0.0011964031 | K82: =I82*E82 -> 0.004532071 | L82: =I82*F82 -> 0.0018225744 | M82: =I82*G82 -> 0.022419003
A83: Costa Rica | B83: 95350.423 | C83: Ba2 | D83: 0.025569819 | E83: =F83+4.23% -> 0.081252504 | F83: 0.038952504 | G83: 0.3 | H83: Central and South America | I83: =B83/$B$96 -> 0.014582949 | J83: =I83*D83 -> 0.00037288338 | K83: =I83*E83 -> 0.0011849012 | L83: =I83*F83 -> 0.00056804239 | M83: =I83*G83 -> 0.0043748848
A84: Ecuador | B84: 124676.07 | C84: Caa3 | D84: 0.084999673 | E84: =F84+4.23% -> 0.17178664 | F84: 0.12948664 | G84: 0.25 | H84: Central and South America | I84: =B84/$B$96 -> 0.019068032 | J84: =I84*D84 -> 0.0016207765 | K84: =I84*E84 -> 0.0032756332 | L84: =I84*F84 -> 0.0024690554 | M84: =I84*G84 -> 0.0047670079
A85: El Salvador | B85: 35364.96 | C85: B3 | D85: 0.055234805 | E85: =F85+4.23% -> 0.12644349 | F85: 0.084143495 | G85: 0.3 | H85: Central and South America | I85: =B85/$B$96 -> 0.0054087376 | J85: =I85*D85 -> 0.00029875057 | K85: =I85*E85 -> 0.00068389969 | L85: =I85*F85 -> 0.00045511009 | M85: =I85*G85 -> 0.0016226213
A86: Guatemala | B86: 113199.58 | C86: Ba1 | D86: 0.021274889 | E86: =F86+4.23% -> 0.0747097 | F86: 0.0324097 | G86: 0.25 | H86: Central and South America | I86: =B86/$B$96 -> 0.01731281 | J86: =I86*D86 -> 0.00036832811 | K86: =I86*E86 -> 0.0012934349 | L86: =I86*F86 -> 0.00056110299 | M86: =I86*G86 -> 0.0043282025
A87: Honduras | B87: 37093.566 | C87: B1 | D87: 0.038254847 | E87: =F87+4.23% -> 0.1005766 | F87: 0.058276598 | G87: 0.3 | H87: Central and South America | I87: =B87/$B$96 -> 0.0056731116 | J87: =I87*D87 -> 0.00021702402 | K87: =I87*E87 -> 0.00057058227 | L87: =I87*F87 -> 0.00033060964 | M87: =I87*G87 -> 0.0017019335
A88: Mexico | B88: 1856365.6 | C88: Baa2 | D88: 0.016180901 | E88: =F88+4.23% -> 0.066949631 | F88: 0.024649631 | G88: 0.3 | H88: Central and South America | I88: =B88/$B$96 -> 0.28391364 | J88: =I88*D88 -> 0.0045939786 | K88: =I88*E88 -> 0.019007914 | L88: =I88*F88 -> 0.0069983666 | M88: =I88*G88 -> 0.085174093
... A95: Venezuela | B95: 119802.96 | C95: C | D95: 0.175 | E95: =F95+4.23% -> 0.30889117 | F95: 0.26659117 | G95: 0.34 | H95: Central and South America | I95: =B95/$B$96 -> 0.018322735 | J95: =I95*D95 -> 0.0032064787 | K95: =I95*E95 -> 0.0056597312 | L95: =I95*F95 -> 0.0048846795 | M95: =I95*G95 -> 0.00622973
A96: Central and South America | B96: =SUM(B77:B95) -> 6538486.9 | D96: =SUM(J77:J95) -> 0.027785942 | E96: =F96+4.23% -> 0.084628496 | F96: =SUM(L77:L95) -> 0.042328496 | G96: =SUM(M77:M95) -> 0.31546691 | I96: =SUM(I77:I95) -> 1
A97: Albania | B97: 27046.429 | C97: Ba3 | D97: 0.030563925 | E97: =F97+4.23% -> 0.088860415 | F97: 0.046560415 | G97: 0.15 | H97: Eastern Europe & Russia | I97: =B97/$B$123 -> 0.0077464144 | J97: =I97*D97 -> 0.00023676083 | K97: =I97*E97 -> 0.0006883496 | L97: =I97*F97 -> 0.00036067627 | M97: =I97*G97 -> 0.0011619622
A98: Armenia | B98: 25955.275 | C98: Ba3 | D98: 0.030563925 | E98: =F98+4.23% -> 0.088860415 | F98: 0.046560415 | G98: 0.18 | H98: Eastern Europe & Russia | I98: =B98/$B$123 -> 0.0074338952 | J98: =I98*D98 -> 0.00022720901 | K98: =I98*E98 -> 0.00066057901 | L98: =I98*F98 -> 0.00034612524 | M98: =I98*G98 -> 0.0013381011
A99: Azerbaijan | B99: 74315.882 | C99: Baa3 | D99: 0.018677954 | E99: =F99+4.23% -> 0.070753587 | F99: 0.028453587 | G99: 0.2 | H99: Eastern Europe & Russia | I99: =B99/$B$123 -> 0.02128494 | J99: =I99*D99 -> 0.00039755913 | K99: =I99*E99 -> 0.0015059858 | L99: =I99*F99 -> 0.00060563289 | M99: =I99*G99 -> 0.004256988
A100: Belarus | B100: 75961.865 | C100: C | D100: 0.175 | E100: =F100+4.23% -> 0.30889117 | F100: 0.26659117 | G100: 0.25 | H100: Eastern Europe & Russia | I100: =B100/$B$123 -> 0.021756369 | J100: =I100*D100 -> 0.0038073645 | K100: =I100*E100 -> 0.0067203503 | L100: =I100*F100 -> 0.0058000559 | M100: =I100*G100 -> 0.0054390922
A101: Bosnia and Herzegovina | B101: 29613.572 | C101: B3 | D101: 0.055234805 | E101: =F101+4.23% -> 0.12644349 | F101: 0.084143495 | G101: 0.1 | H101: Eastern Europe & Russia | I101: =B101/$B$123 -> 0.0084816742 | J101: =I101*D101 -> 0.00046848362 | K101: =I101*E101 -> 0.0010724525 | L101: =I101*F101 -> 0.00071367771 | M101: =I101*G101 -> 0.00084816742
A102: Bulgaria | B102: 113343.36 | C102: Baa1 | D102: 0.013583967 | E102: =F102+4.23% -> 0.062993518 | F102: 0.020693518 | G102: 0.1 | H102: Eastern Europe & Russia | I102: =B102/$B$123 -> 0.032462866 | J102: =I102*D102 -> 0.00044097449 | K102: =I102*E102 -> 0.0020449501 | L102: =I102*F102 -> 0.00067177089 | M102: =I102*G102 -> 0.0032462866
A103: Croatia | B103: 92983.81 | C103: A3 | D103: 0.010187975 | E103: =F103+4.23% -> 0.057820138 | F103: 0.015520138 | G103: 0.18 | H103: Eastern Europe & Russia | I103: =B103/$B$123 -> 0.026631653 | J103: =I103*D103 -> 0.00027132262 | K103: =I103*E103 -> 0.0015398459 | L103: =I103*F103 -> 0.00041332694 | M103: =I103*G103 -> 0.0047936976
A104: Czech Republic | B104: 347034.06 | C104: Aa3 | D104: 0.0050939875 | E104: =F104+4.23% -> 0.050060069 | F104: 0.0077600691 | G104: 0.21 | H104: Eastern Europe & Russia | I104: =B104/$B$123 -> 0.099394624 | J104: =I104*D104 -> 0.00050631497 | K104: =I104*E104 -> 0.0049757017 | L104: =I104*F104 -> 0.00077130915 | M104: =I104*G104 -> 0.020872871
A105: Estonia | B105: 43130.42 | C105: A1 | D105: 0.0059929264 | E105: =F105+4.23% -> 0.051429493 | F105: 0.0091294931 | G105: 0.2 | H105: Eastern Europe & Russia | I105: =B105/$B$123 -> 0.012353058 | J105: =I105*D105 -> 7.4030967e-05 | K105: =I105*E105 -> 0.0006353115 | L105: =I105*F105 -> 0.00011277716 | M105: =I105*G105 -> 0.0024706116
A106: Georgia | B106: 34189.424 | C106: Ba2 | D106: 0.025569819 | E106: =F106+4.23% -> 0.081252504 | F106: 0.038952504 | G106: 0.15 | H106: Eastern Europe & Russia | I106: =B106/$B$123 -> 0.0097922517 | J106: =I106*D106 -> 0.00025038611 | K106: =I106*E106 -> 0.00079564497 | L106: =I106*F106 -> 0.00038143272 | M106: =I106*G106 -> 0.0014688378
A107: Hungary | B107: 222722.74 | C107: Baa2 | D107: 0.016180901 | E107: =F107+4.23% -> 0.066949631 | F107: 0.024649631 | G107: 0.09 | H107: Eastern Europe & Russia | I107: =B107/$B$123 -> 0.063790403 | J107: =I107*D107 -> 0.0010321862 | K107: =I107*E107 -> 0.004270744 | L107: =I107*F107 -> 0.0015724099 | M107: =I107*G107 -> 0.0057411363
A108: Kazakhstan | B108: 291480.27 | C108: Baa1 | D108: 0.013583967 | E108: =F108+4.23% -> 0.062993518 | F108: 0.020693518 | G108: 0.2 | H108: Eastern Europe & Russia | I108: =B108/$B$123 -> 0.083483368 | J108: =I108*D108 -> 0.0011340353 | K108: =I108*E108 -> 0.005258911 | L108: =I108*F108 -> 0.0017275645 | M108: =I108*G108 -> 0.016696674
... A122: Uzbekistan | B122: 114965.29 | C122: Ba3 | D122: 0.030563925 | E122: =F122+4.23% -> 0.088860415 | F122: 0.046560415 | G122: 0.15 | H122: Eastern Europe & Russia | I122: =B122/$B$123 -> 0.032927408 | J122: =I122*D122 -> 0.0010063908 | K122: =I122*E122 -> 0.0029259431 | L122: =I122*F122 -> 0.0015331138 | M122: =I122*G122 -> 0.0049391112
A123: Eastern Europe | B123: =SUM(B97:B122) -> 3491477.2 | D123: =SUM(J97:J122) -> 0.021975562 | E123: =F123+4.23% -> 0.075777091 | F123: =SUM(L97:L122) -> 0.033477091 | G123: =SUM(M97:M122) -> 0.1763748 | I123: =SUM(I97:I122) -> 1
A124: Abu Dhabi | B124: 310000 | C124: Aa2 | D124: 0.0041950485 | E124: =F124+4.23% -> 0.048690645 | F124: 0.0063906452 | G124: 0.09 | H124: Middle East | I124: =B124/$B$137 -> 0.086956075 | J124: =I124*D124 -> 0.00036478495 | K124: =I124*E124 -> 0.0042339474 | L124: =I124*F124 -> 0.00055570542 | M124: =I124*G124 -> 0.0078260468
A125: Bahrain | B125: 47109.734 | C125: B2 | D125: 0.046744826 | E125: =F125+4.23% -> 0.11351005 | F125: 0.071210046 | G125: 0 | H125: Middle East | I125: =B125/$B$137 -> 0.013214444 | J125: =I125*D125 -> 0.00061770688 | K125: =I125*E125 -> 0.0014999721 | L125: =I125*F125 -> 0.00094100116 | M125: =I125*G125 -> 0
A126: Iraq | B126: 279641.26 | C126: Caa1 | D126: 0.063724785 | E126: =F126+4.23% -> 0.13937694 | F126: 0.097076943 | G126: 0.15 | H126: Middle East | I126: =B126/$B$137 -> 0.078440343 | J126: =I126*D126 -> 0.0049985939 | K126: =I126*E126 -> 0.010932775 | L126: =I126*F126 -> 0.0076147487 | M126: =I126*G126 -> 0.011766051
A127: Israel | B127: 540379.92 | C127: Baa1 | D127: 0.013583967 | E127: =F127+4.23% -> 0.062993518 | F127: 0.020693518 | G127: 0.23 | H127: Middle East | I127: =B127/$B$137 -> 0.15157844 | J127: =I127*D127 -> 0.0020590365 | K127: =I127*E127 -> 0.0095484593 | L127: =I127*F127 -> 0.0031366912 | M127: =I127*G127 -> 0.034863042
A128: Jordan | B128: 53352.29 | C128: Ba3 | D128: 0.030563925 | E128: =F128+4.23% -> 0.088860415 | F128: 0.046560415 | G128: 0.2 | H128: Middle East | I128: =B128/$B$137 -> 0.014965502 | J128: =I128*D128 -> 0.00045740449 | K128: =I128*E128 -> 0.0013298407 | L128: =I128*F128 -> 0.00069679999 | M128: =I128*G128 -> 0.0029931005
A129: Kuwait | B129: 160227.27 | C129: A1 | D129: 0.0059929264 | E129: =F129+4.23% -> 0.051429493 | F129: 0.0091294931 | G129: 0.15 | H129: Middle East | I129: =B129/$B$137 -> 0.044944306 | J129: =I129*D129 -> 0.00026934792 | K129: =I129*E129 -> 0.0023114629 | L129: =I129*F129 -> 0.00041031873 | M129: =I129*G129 -> 0.0067416459
A130: Lebanon | B130: 20078.62 | C130: C | D130: 0.175 | E130: =F130+4.23% -> 0.30889117 | F130: 0.26659117 | G130: 0.17 | H130: Middle East | I130: =B130/$B$137 -> 0.0056321226 | J130: =I130*D130 -> 0.00098562146 | K130: =I130*E130 -> 0.001739713 | L130: =I130*F130 -> 0.0015014742 | M130: =I130*G130 -> 0.00095746085
A131: Oman | B131: 107137.2 | C131: Baa3 | D131: 0.018677954 | E131: =F131+4.23% -> 0.070753587 | F131: 0.028453587 | G131: 0.15 | H131: Middle East | I131: =B131/$B$137 -> 0.030052356 | J131: =I131*D131 -> 0.00056131652 | K131: =I131*E131 -> 0.002126312 | L131: =I131*F131 -> 0.00085509731 | M131: =I131*G131 -> 0.0045078534
A132: Qatar | B132: 219162.64 | C132: Aa2 | D132: 0.0041950485 | E132: =F132+4.23% -> 0.048690645 | F132: 0.0063906452 | G132: 0.1 | H132: Middle East | I132: =B132/$B$137 -> 0.06147588 | J132: =I132*D132 -> 0.0002578943 | K132: =I132*E132 -> 0.0029933003 | L132: =I132*F132 -> 0.00039287053 | M132: =I132*G132 -> 0.006147588
A133: Ras Al Khaimah (Emirate of) | B133: 11000 | C133: A3 | D133: 0.010187975 | E133: =F133+4.23% -> 0.057820138 | F133: 0.015520138 | G133: 0.1894 | H133: Middle East | I133: =B133/$B$137 -> 0.0030855381 | J133: =I133*D133 -> 3.1435385e-05 | K133: =I133*E133 -> 0.00017840624 | L133: =I133*F133 -> 4.7887979e-05 | M133: =I133*G133 -> 0.00058440093
A134: Saudi Arabia | B134: 1239804.5 | C134: Aa3 | D134: 0.0050939875 | E134: =F134+4.23% -> 0.050060069 | F134: 0.0077600691 | G134: 0.2 | H134: Middle East | I134: =B134/$B$137 -> 0.34776947 | J134: =I134*D134 -> 0.0017715333 | K134: =I134*E134 -> 0.017409364 | L134: =I134*F134 -> 0.0026987151 | M134: =I134*G134 -> 0.069553894
A135: Sharjah | B135: 24800 | C135: Ba1 | D135: 0.021274889 | E135: =F135+4.23% -> 0.0747097 | F135: 0.0324097 | G135: 0.1894 | H135: Middle East | I135: =B135/$B$137 -> 0.006956486 | J135: =I135*D135 -> 0.00014799847 | K135: =I135*E135 -> 0.00051971699 | L135: =I135*F135 -> 0.00022545763 | M135: =I135*G135 -> 0.0013175584
A136: United Arab Emirates | B136: 552324.85 | C136: Aa2 | D136: 0.0041950485 | E136: =F136+4.23% -> 0.048690645 | F136: 0.0063906452 | G136: 0.09 | H136: Middle East | I136: =B136/$B$137 -> 0.15492903 | J136: =I136*D136 -> 0.00064993482 | K136: =I136*E136 -> 0.0075435947 | L136: =I136*F136 -> 0.00099009649 | M136: =I136*G136 -> 0.013943613
A137: Middle East | B137: =SUM(B124:B136) -> 3565018.3 | D137: =SUM(J124:J136) -> 0.013172609 | E137: =F137+4.23% -> 0.062366864 | F137: =SUM(L124:L136) -> 0.020066864 | G137: =SUM(M124:M136) -> 0.16120226 | I137: =SUM(I124:I136) -> 1
A138: Canada | B138: 2243636.8 | C138: Aaa | D138: 0 | E138: =F138+4.23% -> 0.0423 | F138: 0 | G138: 0.2614 | H138: North America | I138: =B138/B140 -> 0.072388007 | J138: =I138*D138 -> 0 | K138: =I138*E138 -> 0.0030620127 | L138: =I138*F138 -> 0 | M138: =I138*G138 -> 0.018922225
A139: United States | B139: 28750956 | C139: Aa1 | D139: 0.0023336792 | E139: =F139+4.23% -> 0.044633679 | F139: 0.0023336792 | G139: 0.25 | H139: North America | I139: =B139/B140 -> 0.92761199 | J139: =I139*D139 -> 0.0021647488 | K139: =I139*E139 -> 0.041402736 | L139: =I139*F139 -> 0.0021647488 | M139: =I139*G139 -> 0.231903
A140: North America | B140: =SUM(B138:B139) -> 30994593 | D140: =SUM(J138:J139) -> 0.0021647488 | E140: =F140+4.23% -> 0.044464749 | F140: =SUM(L138:L139) -> 0.0021647488 | G140: =SUM(M138:M139) -> 0.25082522 | I140: =SUM(I138:I139) -> 1
A141: Andorra (Principality of) | B141: 4039.8424 | C141: Baa1 | D141: 0.013583967 | E141: =F141+4.23% -> 0.062993518 | F141: 0.020693518 | G141: 0.1 | H141: Western Europe | I141: =B141/$B$167 -> 0.00017145783 | J141: =I141*D141 -> 2.3290775e-06 | K141: =I141*E141 -> 1.0800732e-05 | L141: =I141*F141 -> 3.5480657e-06 | M141: =I141*G141 -> 1.7145783e-05
A142: Austria | B142: 534790.72 | C142: Aa1 | D142: 0.0023336792 | E142: =F142+4.23% -> 0.045855076 | F142: 0.0035550758 | G142: 0.23 | H142: Western Europe | I142: =B142/$B$167 -> 0.022697434 | J142: =I142*D142 -> 5.296853e-05 | K142: =I142*E142 -> 0.0010407926 | L142: =I142*F142 -> 8.06911e-05 | M142: =I142*G142 -> 0.0052204099
A143: Belgium | B143: 671370.08 | C143: Aa3 | D143: 0.0050939875 | E143: =F143+4.23% -> 0.050060069 | F143: 0.0077600691 | G143: 0.25 | H143: Western Europe | I143: =B143/$B$167 -> 0.028494096 | J143: =I143*D143 -> 0.00014514857 | K143: =I143*E143 -> 0.0014264164 | L143: =I143*F143 -> 0.00022111616 | M143: =I143*G143 -> 0.0071235241
A144: Cyprus | B144: 37634.533 | C144: A3 | D144: 0.010187975 | E144: =F144+4.23% -> 0.057820138 | F144: 0.015520138 | G144: 0.125 | H144: Western Europe | I144: =B144/$B$167 -> 0.0015972741 | J144: =I144*D144 -> 1.6272988e-05 | K144: =I144*E144 -> 9.2354607e-05 | L144: =I144*F144 -> 2.4789914e-05 | M144: =I144*G144 -> 0.00019965926
A145: Denmark | B145: 424524.72 | C145: Aaa | D145: 0 | E145: =F145+4.23% -> 0.0423 | F145: 0 | G145: 0.22 | H145: Western Europe | I145: =B145/$B$167 -> 0.018017556 | J145: =I145*D145 -> 0 | K145: =I145*E145 -> 0.00076214264 | L145: =I145*F145 -> 0 | M145: =I145*G145 -> 0.0039638624
A146: Finland | B146: 298696.96 | C146: Aa1 | D146: 0.0023336792 | E146: =F146+4.23% -> 0.045855076 | F146: 0.0035550758 | G146: 0.2 | H146: Western Europe | I146: =B146/$B$167 -> 0.012677211 | J146: =I146*D146 -> 2.9584543e-05 | K146: =I146*E146 -> 0.00058131446 | L146: =I146*F146 -> 4.5068445e-05 | M146: =I146*G146 -> 0.0025354421
A147: France | B147: 3160442.6 | C147: Aa3 | D147: 0.0050939875 | E147: =F147+4.23% -> 0.050060069 | F147: 0.0077600691 | G147: 0.2583 | H147: Western Europe | I147: =B147/$B$167 -> 0.1341346 | J147: =I147*D147 -> 0.00068327997 | K147: =I147*E147 -> 0.0067147873 | L147: =I147*F147 -> 0.0010408938 | M147: =I147*G147 -> 0.034646967
A148: Germany | B148: 4685592.6 | C148: Aaa | D148: 0 | E148: =F148+4.23% -> 0.0423 | F148: 0 | G148: 0.2993 | H148: Western Europe | I148: =B148/$B$167 -> 0.19886458 | J148: =I148*D148 -> 0 | K148: =I148*E148 -> 0.0084119716 | L148: =I148*F148 -> 0 | M148: =I148*G148 -> 0.059520168
...

Sheet Regional breakdown
A1: Country | B1: ='Country GDP'!B1 -> GDP (in millions) in 2024 | C1: ='Sovereign Ratings (Moody''s,S&P)'!D1 -> Moody's rating | D1: Sovereign CDS | E1: Adj. Default Spread | F1: Equity Risk Premium | G1: Country Risk Premium | H1: Corporate Tax Rate | I1: Region
A2: ='Sovereign Ratings (Moody''s,S&P)'!A2 -> Abu Dhabi | B2: =VLOOKUP(A2,'Country GDP'!$A$2:$B$181,2,FALSE()) -> 310000 | C2: =VLOOKUP(A2,'Sovereign Ratings (Moody''s,S&P)'!$A$2:$D$158,4,FALSE()) -> Aa2 | D2: =VLOOKUP(A2,'10-year CDS Spreads'!$A$2:$C$158,3,FALSE()) -> 0.006 | E2: =VLOOKUP(A2,'ERPs by country'!$A$9:$F$165,4,FALSE()) -> 0.0041950485 | F2: =VLOOKUP(A2,'ERPs by country'!$A$9:$F$165,5,FALSE()) -> 0.048690645 | G2: =VLOOKUP(A2,'ERPs by country'!$A$9:$F$165,6,FALSE()) -> 0.0063906452 | H2: =VLOOKUP(A2,'Country Tax Rates'!$A$2:$B$159,2,FALSE()) -> 0.09 | I2: =VLOOKUP(A2,'Regional lookup table'!$A$2:$B$162,2,FALSE()) -> Middle East
A3: ='Sovereign Ratings (Moody''s,S&P)'!A3 -> Albania | B3: =VLOOKUP(A3,'Country GDP'!$A$2:$B$181,2,FALSE()) -> 27046.429 | C3: =VLOOKUP(A3,'Sovereign Ratings (Moody''s,S&P)'!$A$2:$D$158,4,FALSE()) -> Ba3 | D3: =VLOOKUP(A3,'10-year CDS Spreads'!$A$2:$C$158,3,FALSE()) -> NA | E3: =VLOOKUP(A3,'ERPs by country'!$A$9:$F$165,4,FALSE()) -> 0.030563925 | F3: =VLOOKUP(A3,'ERPs by country'!$A$9:$F$165,5,FALSE()) -> 0.088860415 | G3: =VLOOKUP(A3,'ERPs by country'!$A$9:$F$165,6,FALSE()) -> 0.046560415 | H3: =VLOOKUP(A3,'Country Tax Rates'!$A$2:$B$159,2,FALSE()) -> 0.15 | I3: =VLOOKUP(A3,'Regional lookup table'!$A$2:$B$162,2,FALSE()) -> Eastern Europe & Russia
A4: ='Sovereign Ratings (Moody''s,S&P)'!A4 -> Andorra (Principality of) | B4: =VLOOKUP(A4,'Country GDP'!$A$2:$B$181,2,FALSE()) -> 4039.8424 | C4: =VLOOKUP(A4,'Sovereign Ratings (Moody''s,S&P)'!$A$2:$D$158,4,FALSE()) -> Baa1 | D4: =VLOOKUP(A4,'10-year CDS Spreads'!$A$2:$C$158,3,FALSE()) -> NA | E4: =VLOOKUP(A4,'ERPs by country'!$A$9:$F$165,4,FALSE()) -> 0.013583967 | F4: =VLOOKUP(A4,'ERPs by country'!$A$9:$F$165,5,FALSE()) -> 0.062993518 | G4: =VLOOKUP(A4,'ERPs by country'!$A$9:$F$165,6,FALSE()) -> 0.020693518 | H4: =VLOOKUP(A4,'Country Tax Rates'!$A$2:$B$159,2,FALSE()) -> 0.1 | I4: =VLOOKUP(A4,'Regional lookup table'!$A$2:$B$162,2,FALSE()) -> Western Europe
A5: ='Sovereign Ratings (Moody''s,S&P)'!A5 -> Angola | B5: =VLOOKUP(A5,'Country GDP'!$A$2:$B$181,2,FALSE()) -> 100998.92 | C5: =VLOOKUP(A5,'Sovereign Ratings (Moody''s,S&P)'!$A$2:$D$158,4,FALSE()) -> B3 | D5: =VLOOKUP(A5,'10-year CDS Spreads'!$A$2:$C$158,3,FALSE()) -> 0.0624 | E5: =VLOOKUP(A5,'ERPs by country'!$A$9:$F$165,4,FALSE()) -> 0.055234805 | F5: =VLOOKUP(A5,'ERPs by country'!$A$9:$F$165,5,FALSE()) -> 0.12644349 | G5: =VLOOKUP(A5,'ERPs by country'!$A$9:$F$165,6,FALSE()) -> 0.084143495 | H5: =VLOOKUP(A5,'Country Tax Rates'!$A$2:$B$159,2,FALSE()) -> 0.25 | I5: =VLOOKUP(A5,'Regional lookup table'!$A$2:$B$162,2,FALSE()) -> Africa
A6: ='Sovereign Ratings (Moody''s,S&P)'!A6 -> Argentina | B6: =VLOOKUP(A6,'Country GDP'!$A$2:$B$181,2,FALSE()) -> 638365.46 | C6: =VLOOKUP(A6,'Sovereign Ratings (Moody''s,S&P)'!$A$2:$D$158,4,FALSE()) -> Caa1 | D6: =VLOOKUP(A6,'10-year CDS Spreads'!$A$2:$C$158,3,FALSE()) -> NA | E6: =VLOOKUP(A6,'ERPs by country'!$A$9:$F$165,4,FALSE()) -> 0.063724785 | F6: =VLOOKUP(A6,'ERPs by country'!$A$9:$F$165,5,FALSE()) -> 0.13937694 | G6: =VLOOKUP(A6,'ERPs by country'!$A$9:$F$165,6,FALSE()) -> 0.097076943 | H6: =VLOOKUP(A6,'Country Tax Rates'!$A$2:$B$159,2,FALSE()) -> 0.35 | I6: =VLOOKUP(A6,'Regional lookup table'!$A$2:$B$162,2,FALSE()) -> Central and South America
A7: ='Sovereign Ratings (Moody''s,S&P)'!A7 -> Armenia | B7: =VLOOKUP(A7,'Country GDP'!$A$2:$B$181,2,FALSE()) -> 25955.275 | C7: =VLOOKUP(A7,'Sovereign Ratings (Moody''s,S&P)'!$A$2:$D$158,4,FALSE()) -> Ba3 | D7: =VLOOKUP(A7,'10-year CDS Spreads'!$A$2:$C$158,3,FALSE()) -> NA | E7: =VLOOKUP(A7,'ERPs by country'!$A$9:$F$165,4,FALSE()) -> 0.030563925 | F7: =VLOOKUP(A7,'ERPs by country'!$A$9:$F$165,5,FALSE()) -> 0.088860415 | G7: =VLOOKUP(A7,'ERPs by country'!$A$9:$F$165,6,FALSE()) -> 0.046560415 | H7: =VLOOKUP(A7,'Country Tax Rates'!$A$2:$B$159,2,FALSE()) -> 0.18 | I7: =VLOOKUP(A7,'Regional lookup table'!$A$2:$B$162,2,FALSE()) -> Eastern Europe & Russia
A8: ='Sovereign Ratings (Moody''s,S&P)'!A8 -> Aruba | B8: =VLOOKUP(A8,'Country GDP'!$A$2:$B$181,2,FALSE()) -> 4265.6507 | C8: =VLOOKUP(A8,'Sovereign Ratings (Moody''s,S&P)'!$A$2:$D$158,4,FALSE()) -> Baa3 | D8: =VLOOKUP(A8,'10-year CDS Spreads'!$A$2:$C$158,3,FALSE()) -> NA | E8: =VLOOKUP(A8,'ERPs by country'!$A$9:$F$165,4,FALSE()) -> 0.018677954 | F8: =VLOOKUP(A8,'ERPs by country'!$A$9:$F$165,5,FALSE()) -> 0.070753587 | G8: =VLOOKUP(A8,'ERPs by country'!$A$9:$F$165,6,FALSE()) -> 0.028453587 | H8: =VLOOKUP(A8,'Country Tax Rates'!$A$2:$B$159,2,FALSE()) -> 0.22 | I8: =VLOOKUP(A8,'Regional lookup table'!$A$2:$B$162,2,FALSE()) -> Caribbean
A9: ='Sovereign Ratings (Moody''s,S&P)'!A9 -> Australia | B9: =VLOOKUP(A9,'Country GDP'!$A$2:$B$181,2,FALSE()) -> 1757022.5 | C9: =VLOOKUP(A9,'Sovereign Ratings (Moody''s,S&P)'!$A$2:$D$158,4,FALSE()) -> Aaa | D9: =VLOOKUP(A9,'10-year CDS Spreads'!$A$2:$C$158,3,FALSE()) -> 0.0019 | E9: =VLOOKUP(A9,'ERPs by country'!$A$9:$F$165,4,FALSE()) -> 0 | F9: =VLOOKUP(A9,'ERPs by country'!$A$9:$F$165,5,FALSE()) -> 0.0423 | G9: =VLOOKUP(A9,'ERPs by country'!$A$9:$F$165,6,FALSE()) -> 0 | H9: =VLOOKUP(A9,'Country Tax Rates'!$A$2:$B$159,2,FALSE()) -> 0.3 | I9: =VLOOKUP(A9,'Regional lookup table'!$A$2:$B$162,2,FALSE()) -> Australia & New Zealand
A10: ='Sovereign Ratings (Moody''s,S&P)'!A10 -> Austria | B10: =VLOOKUP(A10,'Country GDP'!$A$2:$B$181,2,FALSE()) -> 534790.72 | C10: =VLOOKUP(A10,'Sovereign Ratings (Moody''s,S&P)'!$A$2:$D$158,4,FALSE()) -> Aa1 | D10: =VLOOKUP(A10,'10-year CDS Spreads'!$A$2:$C$158,3,FALSE()) -> 0.0028 | E10: =VLOOKUP(A10,'ERPs by country'!$A$9:$F$165,4,FALSE()) -> 0.0023336792 | F10: =VLOOKUP(A10,'ERPs by country'!$A$9:$F$165,5,FALSE()) -> 0.045855076 | G10: =VLOOKUP(A10,'ERPs by country'!$A$9:$F$165,6,FALSE()) -> 0.0035550758 | H10: =VLOOKUP(A10,'Country Tax Rates'!$A$2:$B$159,2,FALSE()) -> 0.23 | I10: =VLOOKUP(A10,'Regional lookup table'!$A$2:$B$162,2,FALSE()) -> Western Europe
A11: ='Sovereign Ratings (Moody''s,S&P)'!A11 -> Azerbaijan | B11: =VLOOKUP(A11,'Country GDP'!$A$2:$B$181,2,FALSE()) -> 74315.882 | C11: =VLOOKUP(A11,'Sovereign Ratings (Moody''s,S&P)'!$A$2:$D$158,4,FALSE()) -> Baa3 | D11: =VLOOKUP(A11,'10-year CDS Spreads'!$A$2:$C$158,3,FALSE()) -> NA | E11: =VLOOKUP(A11,'ERPs by country'!$A$9:$F$165,4,FALSE()) -> 0.018677954 | F11: =VLOOKUP(A11,'ERPs by country'!$A$9:$F$165,5,FALSE()) -> 0.070753587 | G11: =VLOOKUP(A11,'ERPs by country'!$A$9:$F$165,6,FALSE()) -> 0.028453587 | H11: =VLOOKUP(A11,'Country Tax Rates'!$A$2:$B$159,2,FALSE()) -> 0.2 | I11: =VLOOKUP(A11,'Regional lookup table'!$A$2:$B$162,2,FALSE()) -> Eastern Europe & Russia
A12: ='Sovereign Ratings (Moody''s,S&P)'!A12 -> Bahamas | B12: =VLOOKUP(A12,'Country GDP'!$A$2:$B$181,2,FALSE()) -> 15832.8 | C12: =VLOOKUP(A12,'Sovereign Ratings (Moody''s,S&P)'!$A$2:$D$158,4,FALSE()) -> B1 | D12: =VLOOKUP(A12,'10-year CDS Spreads'!$A$2:$C$158,3,FALSE()) -> NA | E12: =VLOOKUP(A12,'ERPs by country'!$A$9:$F$165,4,FALSE()) -> 0.038254847 | F12: =VLOOKUP(A12,'ERPs by country'!$A$9:$F$165,5,FALSE()) -> 0.1005766 | G12: =VLOOKUP(A12,'ERPs by country'!$A$9:$F$165,6,FALSE()) -> 0.058276598 | H12: =VLOOKUP(A12,'Country Tax Rates'!$A$2:$B$159,2,FALSE()) -> 0 | I12: =VLOOKUP(A12,'Regional lookup table'!$A$2:$B$162,2,FALSE()) -> Caribbean
A13: ='Sovereign Ratings (Moody''s,S&P)'!A13 -> Bahrain | B13: =VLOOKUP(A13,'Country GDP'!$A$2:$B$181,2,FALSE()) -> 47109.734 | C13: =VLOOKUP(A13,'Sovereign Ratings (Moody''s,S&P)'!$A$2:$D$158,4,FALSE()) -> B2 | D13: =VLOOKUP(A13,'10-year CDS Spreads'!$A$2:$C$158,3,FALSE()) -> 0.0247 | E13: =VLOOKUP(A13,'ERPs by country'!$A$9:$F$165,4,FALSE()) -> 0.046744826 | F13: =VLOOKUP(A13,'ERPs by country'!$A$9:$F$165,5,FALSE()) -> 0.11351005 | G13: =VLOOKUP(A13,'ERPs by country'!$A$9:$F$165,6,FALSE()) -> 0.071210046 | H13: =VLOOKUP(A13,'Country Tax Rates'!$A$2:$B$159,2,FALSE()) -> 0 | I13: =VLOOKUP(A13,'Regional lookup table'!$A$2:$B$162,2,FALSE()) -> Middle East
... A158: ='Sovereign Ratings (Moody''s,S&P)'!A158 -> Zambia | B158: =VLOOKUP(A158,'Country GDP'!$A$2:$B$181,2,FALSE()) -> 25303.185 | C158: =VLOOKUP(A158,'Sovereign Ratings (Moody''s,S&P)'!$A$2:$D$158,4,FALSE()) -> Caa2 | D158: =VLOOKUP(A158,'10-year CDS Spreads'!$A$2:$C$158,3,FALSE()) -> 0.0408 | E158: =VLOOKUP(A158,'ERPs by country'!$A$9:$F$165,4,FALSE()) -> 0.076509694 | F158: =VLOOKUP(A158,'ERPs by country'!$A$9:$F$165,5,FALSE()) -> 0.1588532 | G158: =VLOOKUP(A158,'ERPs by country'!$A$9:$F$165,6,FALSE()) -> 0.1165532 | H158: =VLOOKUP(A158,'Country Tax Rates'!$A$2:$B$159,2,FALSE()) -> 0.3 | I158: =VLOOKUP(A158,'Regional lookup table'!$A$2:$B$162,2,FALSE()) -> Africa

Sheet Sovereign Ratings (Moody's,S&P)
A1: Country | B1: S&P Rating | C1: Fitch rating | D1: Moody's rating | E1: Moody's Rating (unadj)
A2: ='Ratings worksheet'!A2 -> Abu Dhabi | B2: =VLOOKUP(A2,'Ratings worksheet'!$A$2:$C$159,2,FALSE()) -> #N/A | C2: =VLOOKUP(A2,'Ratings worksheet'!$E$2:$H$159,4,FALSE()) -> #N/A | D2: =IF(E2="NR",VLOOKUP(B2,'Sovereign Ratings (Moody''s,S&P)'!$G$9:$H$34,2,FALSE()),E2) -> Aa2 | E2: =VLOOKUP(A2,'Ratings worksheet'!$A$2:$C$159,3,FALSE()) -> Aa2 | G2: GOVERNMENT BOND RATINGS
A3: ='Ratings worksheet'!A3 -> Albania | B3: =VLOOKUP(A3,'Ratings worksheet'!$A$2:$C$159,2,FALSE()) -> BB | C3: =VLOOKUP(A3,'Ratings worksheet'!$E$2:$H$159,4,FALSE()) -> NR | D3: =IF(E3="NR",VLOOKUP(B3,'Sovereign Ratings (Moody''s,S&P)'!$G$9:$H$34,2,FALSE()),E3) -> Ba3 | E3: =VLOOKUP(A3,'Ratings worksheet'!$A$2:$C$159,3,FALSE()) -> Ba3 | G3: In local currency
A4: ='Ratings worksheet'!A4 -> Andorra (Principality of) | B4: =VLOOKUP(A4,'Ratings worksheet'!$A$2:$C$159,2,FALSE()) -> A- | C4: =VLOOKUP(A4,'Ratings worksheet'!$E$2:$H$159,4,FALSE()) -> #N/A | D4: =IF(E4="NR",VLOOKUP(B4,'Sovereign Ratings (Moody''s,S&P)'!$G$9:$H$34,2,FALSE()),E4) -> Baa1 | E4: =VLOOKUP(A4,'Ratings worksheet'!$A$2:$C$159,3,FALSE()) -> Baa1 | G4: S&P: These are the S&P sovereign local currency ratings
A5: ='Ratings worksheet'!A5 -> Angola | B5: =VLOOKUP(A5,'Ratings worksheet'!$A$2:$C$159,2,FALSE()) -> B- | C5: =VLOOKUP(A5,'Ratings worksheet'!$E$2:$H$159,4,FALSE()) -> B- | D5: =IF(E5="NR",VLOOKUP(B5,'Sovereign Ratings (Moody''s,S&P)'!$G$9:$H$34,2,FALSE()),E5) -> B3 | E5: =VLOOKUP(A5,'Ratings worksheet'!$A$2:$C$159,3,FALSE()) -> B3 | G5: Moody's: These are the Moody's local currency rating
A6: ='Ratings worksheet'!A6 -> Argentina | B6: =VLOOKUP(A6,'Ratings worksheet'!$A$2:$C$159,2,FALSE()) -> CCC+ | C6: =VLOOKUP(A6,'Ratings worksheet'!$E$2:$H$159,4,FALSE()) -> CCC+ | D6: =IF(E6="NR",VLOOKUP(B6,'Sovereign Ratings (Moody''s,S&P)'!$G$9:$H$34,2,FALSE()),E6) -> Caa1 | E6: =VLOOKUP(A6,'Ratings worksheet'!$A$2:$C$159,3,FALSE()) -> Caa1 | G6: In red: These are countries where S&P has a rating and Moody's does not. The following lookup table is used to estimate the
A7: ='Ratings worksheet'!A7 -> Armenia | B7: =VLOOKUP(A7,'Ratings worksheet'!$A$2:$C$159,2,FALSE()) -> BB- | C7: =VLOOKUP(A7,'Ratings worksheet'!$E$2:$H$159,4,FALSE()) -> BB- | D7: =IF(E7="NR",VLOOKUP(B7,'Sovereign Ratings (Moody''s,S&P)'!$G$9:$H$34,2,FALSE()),E7) -> Ba3 | E7: =VLOOKUP(A7,'Ratings worksheet'!$A$2:$C$159,3,FALSE()) -> Ba3 | G7: Moody's equivalent rating for these countries.
A8: ='Ratings worksheet'!A8 -> Aruba | B8: =VLOOKUP(A8,'Ratings worksheet'!$A$2:$C$159,2,FALSE()) -> BBB+ | C8: =VLOOKUP(A8,'Ratings worksheet'!$E$2:$H$159,4,FALSE()) -> BBB- | D8: =IF(E8="NR",VLOOKUP(B8,'Sovereign Ratings (Moody''s,S&P)'!$G$9:$H$34,2,FALSE()),E8) -> Baa3 | E8: =VLOOKUP(A8,'Ratings worksheet'!$A$2:$C$159,3,FALSE()) -> Baa3 | G8: S&P/Fitch | H8: Moody's
A9: ='Ratings worksheet'!A9 -> Australia | B9: =VLOOKUP(A9,'Ratings worksheet'!$A$2:$C$159,2,FALSE()) -> AAA | C9: =VLOOKUP(A9,'Ratings worksheet'!$E$2:$H$159,4,FALSE()) -> AAA | D9: =IF(E9="NR",VLOOKUP(B9,'Sovereign Ratings (Moody''s,S&P)'!$G$9:$H$34,2,FALSE()),E9) -> Aaa | E9: =VLOOKUP(A9,'Ratings worksheet'!$A$2:$C$159,3,FALSE()) -> Aaa | G9: A | H9: A2
A10: ='Ratings worksheet'!A10 -> Austria | B10: =VLOOKUP(A10,'Ratings worksheet'!$A$2:$C$159,2,FALSE()) -> AA+ | C10: =VLOOKUP(A10,'Ratings worksheet'!$E$2:$H$159,4,FALSE()) -> AA | D10: =IF(E10="NR",VLOOKUP(B10,'Sovereign Ratings (Moody''s,S&P)'!$G$9:$H$34,2,FALSE()),E10) -> Aa1 | E10: =VLOOKUP(A10,'Ratings worksheet'!$A$2:$C$159,3,FALSE()) -> Aa1 | G10: A- | H10: A3
A11: ='Ratings worksheet'!A11 -> Azerbaijan | B11: =VLOOKUP(A11,'Ratings worksheet'!$A$2:$C$159,2,FALSE()) -> NR | C11: =VLOOKUP(A11,'Ratings worksheet'!$E$2:$H$159,4,FALSE()) -> BBB- | D11: =IF(E11="NR",VLOOKUP(B11,'Sovereign Ratings (Moody''s,S&P)'!$G$9:$H$34,2,FALSE()),E11) -> Baa3 | E11: =VLOOKUP(A11,'Ratings worksheet'!$A$2:$C$159,3,FALSE()) -> Baa3 | G11: A+ | H11: A1
A12: ='Ratings worksheet'!A12 -> Bahamas | B12: =VLOOKUP(A12,'Ratings worksheet'!$A$2:$C$159,2,FALSE()) -> BB- | C12: =VLOOKUP(A12,'Ratings worksheet'!$E$2:$H$159,4,FALSE()) -> BB- | D12: =IF(E12="NR",VLOOKUP(B12,'Sovereign Ratings (Moody''s,S&P)'!$G$9:$H$34,2,FALSE()),E12) -> B1 | E12: =VLOOKUP(A12,'Ratings worksheet'!$A$2:$C$159,3,FALSE()) -> B1 | G12: AA | H12: Aa2
A13: ='Ratings worksheet'!A13 -> Bahrain | B13: =VLOOKUP(A13,'Ratings worksheet'!$A$2:$C$159,2,FALSE()) -> B | C13: =VLOOKUP(A13,'Ratings worksheet'!$E$2:$H$159,4,FALSE()) -> B+ | D13: =IF(E13="NR",VLOOKUP(B13,'Sovereign Ratings (Moody''s,S&P)'!$G$9:$H$34,2,FALSE()),E13) -> B2 | E13: =VLOOKUP(A13,'Ratings worksheet'!$A$2:$C$159,3,FALSE()) -> B2 | G13: AA- | H13: Aa3
A14: ='Ratings worksheet'!A14 -> Bangladesh | B14: =VLOOKUP(A14,'Ratings worksheet'!$A$2:$C$159,2,FALSE()) -> B+ | C14: =VLOOKUP(A14,'Ratings worksheet'!$E$2:$H$159,4,FALSE()) -> B+ | D14: =IF(E14="NR",VLOOKUP(B14,'Sovereign Ratings (Moody''s,S&P)'!$G$9:$H$34,2,FALSE()),E14) -> B2 | E14: =VLOOKUP(A14,'Ratings worksheet'!$A$2:$C$159,3,FALSE()) -> B2 | G14: AA+ | H14: Aa1
A15: ='Ratings worksheet'!A15 -> Barbados | B15: =VLOOKUP(A15,'Ratings worksheet'!$A$2:$C$159,2,FALSE()) -> B+ | C15: =VLOOKUP(A15,'Ratings worksheet'!$E$2:$H$159,4,FALSE()) -> B+ | D15: =IF(E15="NR",VLOOKUP(B15,'Sovereign Ratings (Moody''s,S&P)'!$G$9:$H$34,2,FALSE()),E15) -> B2 | E15: =VLOOKUP(A15,'Ratings worksheet'!$A$2:$C$159,3,FALSE()) -> B2 | G15: AAA | H15: Aaa
A16: ='Ratings worksheet'!A16 -> Belarus | B16: =VLOOKUP(A16,'Ratings worksheet'!$A$2:$C$159,2,FALSE()) -> NR | C16: =VLOOKUP(A16,'Ratings worksheet'!$E$2:$H$159,4,FALSE()) -> CCC | D16: =IF(E16="NR",VLOOKUP(B16,'Sovereign Ratings (Moody''s,S&P)'!$G$9:$H$34,2,FALSE()),E16) -> C | E16: =VLOOKUP(A16,'Ratings worksheet'!$A$2:$C$159,3,FALSE()) -> C | G16: B | H16: B2
A17: ='Ratings worksheet'!A17 -> Belgium | B17: =VLOOKUP(A17,'Ratings worksheet'!$A$2:$C$159,2,FALSE()) -> AA | C17: =VLOOKUP(A17,'Ratings worksheet'!$E$2:$H$159,4,FALSE()) -> A+ | D17: =IF(E17="NR",VLOOKUP(B17,'Sovereign Ratings (Moody''s,S&P)'!$G$9:$H$34,2,FALSE()),E17) -> Aa3 | E17: =VLOOKUP(A17,'Ratings worksheet'!$A$2:$C$159,3,FALSE()) -> Aa3 | G17: B- | H17: B3
A18: ='Ratings worksheet'!A18 -> Belize | B18: =VLOOKUP(A18,'Ratings worksheet'!$A$2:$C$159,2,FALSE()) -> B- | C18: =VLOOKUP(A18,'Ratings worksheet'!$E$2:$H$159,4,FALSE()) -> NR | D18: =IF(E18="NR",VLOOKUP(B18,'Sovereign Ratings (Moody''s,S&P)'!$G$9:$H$34,2,FALSE()),E18) -> Caa1 | E18: =VLOOKUP(A18,'Ratings worksheet'!$A$2:$C$159,3,FALSE()) -> Caa1 | G18: B+ | H18: B1
A19: ='Ratings worksheet'!A19 -> Benin | B19: =VLOOKUP(A19,'Ratings worksheet'!$A$2:$C$159,2,FALSE()) -> BB- | C19: =VLOOKUP(A19,'Ratings worksheet'!$E$2:$H$159,4,FALSE()) -> B+ | D19: =IF(E19="NR",VLOOKUP(B19,'Sovereign Ratings (Moody''s,S&P)'!$G$9:$H$34,2,FALSE()),E19) -> B1 | E19: =VLOOKUP(A19,'Ratings worksheet'!$A$2:$C$159,3,FALSE()) -> B1 | G19: BB | H19: Ba2
... A34: ='Ratings worksheet'!A34 -> Colombia | B34: =VLOOKUP(A34,'Ratings worksheet'!$A$2:$C$159,2,FALSE()) -> BB | C34: =VLOOKUP(A34,'Ratings worksheet'!$E$2:$H$159,4,FALSE()) -> BB | D34: =IF(E34="NR",VLOOKUP(B34,'Sovereign Ratings (Moody''s,S&P)'!$G$9:$H$34,2,FALSE()),E34) -> Baa3 | E34: =VLOOKUP(A34,'Ratings worksheet'!$A$2:$C$159,3,FALSE()) -> Baa3 | G34: NR | H34: NA
A35: ='Ratings worksheet'!A35 -> Congo (Democratic Republic of) | B35: =VLOOKUP(A35,'Ratings worksheet'!$A$2:$C$159,2,FALSE()) -> #N/A | C35: =VLOOKUP(A35,'Ratings worksheet'!$E$2:$H$159,4,FALSE()) -> #N/A | D35: =IF(E35="NR",VLOOKUP(B35,'Sovereign Ratings (Moody''s,S&P)'!$G$9:$H$34,2,FALSE()),E35) -> B3 | E35: =VLOOKUP(A35,'Ratings worksheet'!$A$2:$C$159,3,FALSE()) -> B3
A36: ='Ratings worksheet'!A36 -> Congo (Republic of) | B36: =VLOOKUP(A36,'Ratings worksheet'!$A$2:$C$159,2,FALSE()) -> CCC+ | C36: =VLOOKUP(A36,'Ratings worksheet'!$E$2:$H$159,4,FALSE()) -> #N/A | D36: =IF(E36="NR",VLOOKUP(B36,'Sovereign Ratings (Moody''s,S&P)'!$G$9:$H$34,2,FALSE()),E36) -> Caa2 | E36: =VLOOKUP(A36,'Ratings worksheet'!$A$2:$C$159,3,FALSE()) -> Caa2
A37: ='Ratings worksheet'!A37 -> Cook Islands | B37: =VLOOKUP(A37,'Ratings worksheet'!$A$2:$C$159,2,FALSE()) -> #N/A | C37: =VLOOKUP(A37,'Ratings worksheet'!$E$2:$H$159,4,FALSE()) -> #N/A | D37: =IF(E37="NR",VLOOKUP(B37,'Sovereign Ratings (Moody''s,S&P)'!$G$9:$H$34,2,FALSE()),E37) -> B1 | E37: =VLOOKUP(A37,'Ratings worksheet'!$A$2:$C$159,3,FALSE()) -> B1
A38: ='Ratings worksheet'!A38 -> Costa Rica | B38: =VLOOKUP(A38,'Ratings worksheet'!$A$2:$C$159,2,FALSE()) -> BB | C38: =VLOOKUP(A38,'Ratings worksheet'!$E$2:$H$159,4,FALSE()) -> BB | D38: =IF(E38="NR",VLOOKUP(B38,'Sovereign Ratings (Moody''s,S&P)'!$G$9:$H$34,2,FALSE()),E38) -> Ba2 | E38: =VLOOKUP(A38,'Ratings worksheet'!$A$2:$C$159,3,FALSE()) -> Ba2
A39: ='Ratings worksheet'!A39 -> Côte d'Ivoire | B39: =VLOOKUP(A39,'Ratings worksheet'!$A$2:$C$159,2,FALSE()) -> #N/A | C39: =VLOOKUP(A39,'Ratings worksheet'!$E$2:$H$159,4,FALSE()) -> #N/A | D39: =IF(E39="NR",VLOOKUP(B39,'Sovereign Ratings (Moody''s,S&P)'!$G$9:$H$34,2,FALSE()),E39) -> Ba2 | E39: =VLOOKUP(A39,'Ratings worksheet'!$A$2:$C$159,3,FALSE()) -> Ba2
A40: ='Ratings worksheet'!A40 -> Croatia | B40: =VLOOKUP(A40,'Ratings worksheet'!$A$2:$C$159,2,FALSE()) -> A- | C40: =VLOOKUP(A40,'Ratings worksheet'!$E$2:$H$159,4,FALSE()) -> A- | D40: =IF(E40="NR",VLOOKUP(B40,'Sovereign Ratings (Moody''s,S&P)'!$G$9:$H$34,2,FALSE()),E40) -> A3 | E40: =VLOOKUP(A40,'Ratings worksheet'!$A$2:$C$159,3,FALSE()) -> A3
A41: ='Ratings worksheet'!A41 -> Cuba | B41: =VLOOKUP(A41,'Ratings worksheet'!$A$2:$C$159,2,FALSE()) -> #N/A | C41: =VLOOKUP(A41,'Ratings worksheet'!$E$2:$H$159,4,FALSE()) -> NR | D41: =IF(E41="NR",VLOOKUP(B41,'Sovereign Ratings (Moody''s,S&P)'!$G$9:$H$34,2,FALSE()),E41) -> Ca | E41: =VLOOKUP(A41,'Ratings worksheet'!$A$2:$C$159,3,FALSE()) -> Ca
A42: ='Ratings worksheet'!A42 -> Curacao | B42: =VLOOKUP(A42,'Ratings worksheet'!$A$2:$C$159,2,FALSE()) -> BBB- | C42: =VLOOKUP(A42,'Ratings worksheet'!$E$2:$H$159,4,FALSE()) -> #N/A | D42: =IF(E42="NR",VLOOKUP(B42,'Sovereign Ratings (Moody''s,S&P)'!$G$9:$H$34,2,FALSE()),E42) -> Baa3 | E42: =VLOOKUP(A42,'Ratings worksheet'!$A$2:$C$159,3,FALSE()) -> NR
A43: ='Ratings worksheet'!A43 -> Cyprus | B43: =VLOOKUP(A43,'Ratings worksheet'!$A$2:$C$159,2,FALSE()) -> A- | C43: =VLOOKUP(A43,'Ratings worksheet'!$E$2:$H$159,4,FALSE()) -> A- | D43: =IF(E43="NR",VLOOKUP(B43,'Sovereign Ratings (Moody''s,S&P)'!$G$9:$H$34,2,FALSE()),E43) -> A3 | E43: =VLOOKUP(A43,'Ratings worksheet'!$A$2:$C$159,3,FALSE()) -> A3
A44: ='Ratings worksheet'!A44 -> Czech Republic | B44: =VLOOKUP(A44,'Ratings worksheet'!$A$2:$C$159,2,FALSE()) -> AA- | C44: =VLOOKUP(A44,'Ratings worksheet'!$E$2:$H$159,4,FALSE()) -> #N/A | D44: =IF(E44="NR",VLOOKUP(B44,'Sovereign Ratings (Moody''s,S&P)'!$G$9:$H$34,2,FALSE()),E44) -> Aa3 | E44: =VLOOKUP(A44,'Ratings worksheet'!$A$2:$C$159,3,FALSE()) -> Aa3
A45: ='Ratings worksheet'!A45 -> Denmark | B45: =VLOOKUP(A45,'Ratings worksheet'!$A$2:$C$159,2,FALSE()) -> AAA | C45: =VLOOKUP(A45,'Ratings worksheet'!$E$2:$H$159,4,FALSE()) -> AAA | D45: =IF(E45="NR",VLOOKUP(B45,'Sovereign Ratings (Moody''s,S&P)'!$G$9:$H$34,2,FALSE()),E45) -> Aaa | E45: =VLOOKUP(A45,'Ratings worksheet'!$A$2:$C$159,3,FALSE()) -> Aaa
A46: ='Ratings worksheet'!A46 -> Dominican Republic | B46: =VLOOKUP(A46,'Ratings worksheet'!$A$2:$C$159,2,FALSE()) -> BB | C46: =VLOOKUP(A46,'Ratings worksheet'!$E$2:$H$159,4,FALSE()) -> BB- | D46: =IF(E46="NR",VLOOKUP(B46,'Sovereign Ratings (Moody''s,S&P)'!$G$9:$H$34,2,FALSE()),E46) -> Ba2 | E46: =VLOOKUP(A46,'Ratings worksheet'!$A$2:$C$159,3,FALSE()) -> Ba2
... A60: ='Ratings worksheet'!A60 -> Guatemala | B60: =VLOOKUP(A60,'Ratings worksheet'!$A$2:$C$159,2,FALSE()) -> BB+ | C60: =VLOOKUP(A60,'Ratings worksheet'!$E$2:$H$159,4,FALSE()) -> BB+ | D60: =IF(E60="NR",VLOOKUP(B60,'Sovereign Ratings (Moody''s,S&P)'!$G$9:$H$34,2,FALSE()),E60) -> Ba1 | E60: =VLOOKUP(A60,'Ratings worksheet'!$A$2:$C$159,3,FALSE()) -> Ba1
A61: ='Ratings worksheet'!A61 -> Guernsey (States of) | B61: =VLOOKUP(A61,'Ratings worksheet'!$A$2:$C$159,2,FALSE()) -> A+ | C61: =VLOOKUP(A61,'Ratings worksheet'!$E$2:$H$159,4,FALSE()) -> #N/A | D61: =IF(E61="NR",VLOOKUP(B61,'Sovereign Ratings (Moody''s,S&P)'!$G$9:$H$34,2,FALSE()),E61) -> A1 | E61: NR
A62: ='Ratings worksheet'!A62 -> Honduras | B62: =VLOOKUP(A62,'Ratings worksheet'!$A$2:$C$159,2,FALSE()) -> BB- | C62: =VLOOKUP(A62,'Ratings worksheet'!$E$2:$H$159,4,FALSE()) -> B | D62: =IF(E62="NR",VLOOKUP(B62,'Sovereign Ratings (Moody''s,S&P)'!$G$9:$H$34,2,FALSE()),E62) -> B1 | E62: =VLOOKUP(A62,'Ratings worksheet'!$A$2:$C$159,3,FALSE()) -> B1
A63: ='Ratings worksheet'!A63 -> Hong Kong | B63: =VLOOKUP(A63,'Ratings worksheet'!$A$2:$C$159,2,FALSE()) -> AA+ | C63: =VLOOKUP(A63,'Ratings worksheet'!$E$2:$H$159,4,FALSE()) -> AA- | D63: =IF(E63="NR",VLOOKUP(B63,'Sovereign Ratings (Moody''s,S&P)'!$G$9:$H$34,2,FALSE()),E63) -> Aa3 | E63: =VLOOKUP(A63,'Ratings worksheet'!$A$2:$C$159,3,FALSE()) -> Aa3
A64: ='Ratings worksheet'!A64 -> Hungary | B64: =VLOOKUP(A64,'Ratings worksheet'!$A$2:$C$159,2,FALSE()) -> BBB- | C64: =VLOOKUP(A64,'Ratings worksheet'!$E$2:$H$159,4,FALSE()) -> BBB | D64: =IF(E64="NR",VLOOKUP(B64,'Sovereign Ratings (Moody''s,S&P)'!$G$9:$H$34,2,FALSE()),E64) -> Baa2 | E64: =VLOOKUP(A64,'Ratings worksheet'!$A$2:$C$159,3,FALSE()) -> Baa2
A65: ='Ratings worksheet'!A65 -> Iceland | B65: =VLOOKUP(A65,'Ratings worksheet'!$A$2:$C$159,2,FALSE()) -> A+ | C65: =VLOOKUP(A65,'Ratings worksheet'!$E$2:$H$159,4,FALSE()) -> A | D65: =IF(E65="NR",VLOOKUP(B65,'Sovereign Ratings (Moody''s,S&P)'!$G$9:$H$34,2,FALSE()),E65) -> A1 | E65: =VLOOKUP(A65,'Ratings worksheet'!$A$2:$C$159,3,FALSE()) -> A1
A66: ='Ratings worksheet'!A66 -> India | B66: =VLOOKUP(A66,'Ratings worksheet'!$A$2:$C$159,2,FALSE()) -> BBB | C66: =VLOOKUP(A66,'Ratings worksheet'!$E$2:$H$159,4,FALSE()) -> BBB- | D66: =IF(E66="NR",VLOOKUP(B66,'Sovereign Ratings (Moody''s,S&P)'!$G$9:$H$34,2,FALSE()),E66) -> Baa3 | E66: =VLOOKUP(A66,'Ratings worksheet'!$A$2:$C$159,3,FALSE()) -> Baa3
A67: ='Ratings worksheet'!A67 -> Indonesia | B67: =VLOOKUP(A67,'Ratings worksheet'!$A$2:$C$159,2,FALSE()) -> BBB | C67: =VLOOKUP(A67,'Ratings worksheet'!$E$2:$H$159,4,FALSE()) -> BBB | D67: =IF(E67="NR",VLOOKUP(B67,'Sovereign Ratings (Moody''s,S&P)'!$G$9:$H$34,2,FALSE()),E67) -> Baa2 | E67: =VLOOKUP(A67,'Ratings worksheet'!$A$2:$C$159,3,FALSE()) -> Baa2
A68: ='Ratings worksheet'!A68 -> Iraq | B68: =VLOOKUP(A68,'Ratings worksheet'!$A$2:$C$159,2,FALSE()) -> B- | C68: =VLOOKUP(A68,'Ratings worksheet'!$E$2:$H$159,4,FALSE()) -> B- | D68: =IF(E68="NR",VLOOKUP(B68,'Sovereign Ratings (Moody''s,S&P)'!$G$9:$H$34,2,FALSE()),E68) -> Caa1 | E68: =VLOOKUP(A68,'Ratings worksheet'!$A$2:$C$159,3,FALSE()) -> Caa1
A69: ='Ratings worksheet'!A69 -> Ireland | B69: =VLOOKUP(A69,'Ratings worksheet'!$A$2:$C$159,2,FALSE()) -> AA | C69: =VLOOKUP(A69,'Ratings worksheet'!$E$2:$H$159,4,FALSE()) -> AA | D69: =IF(E69="NR",VLOOKUP(B69,'Sovereign Ratings (Moody''s,S&P)'!$G$9:$H$34,2,FALSE()),E69) -> Aa3 | E69: =VLOOKUP(A69,'Ratings worksheet'!$A$2:$C$159,3,FALSE()) -> Aa3
A70: ='Ratings worksheet'!A70 -> Isle of Man | B70: =VLOOKUP(A70,'Ratings worksheet'!$A$2:$C$159,2,FALSE()) -> NR | C70: =VLOOKUP(A70,'Ratings worksheet'!$E$2:$H$159,4,FALSE()) -> #N/A | D70: =IF(E70="NR",VLOOKUP(B70,'Sovereign Ratings (Moody''s,S&P)'!$G$9:$H$34,2,FALSE()),E70) -> Aa3 | E70: =VLOOKUP(A70,'Ratings worksheet'!$A$2:$C$159,3,FALSE()) -> Aa3
A71: ='Ratings worksheet'!A71 -> Israel | B71: =VLOOKUP(A71,'Ratings worksheet'!$A$2:$C$159,2,FALSE()) -> A | C71: =VLOOKUP(A71,'Ratings worksheet'!$E$2:$H$159,4,FALSE()) -> A | D71: =IF(E71="NR",VLOOKUP(B71,'Sovereign Ratings (Moody''s,S&P)'!$G$9:$H$34,2,FALSE()),E71) -> Baa1 | E71: =VLOOKUP(A71,'Ratings worksheet'!$A$2:$C$159,3,FALSE()) -> Baa1
A72: ='Ratings worksheet'!A72 -> Italy | B72: =VLOOKUP(A72,'Ratings worksheet'!$A$2:$C$159,2,FALSE()) -> BBB+ | C72: =VLOOKUP(A72,'Ratings worksheet'!$E$2:$H$159,4,FALSE()) -> BBB+ | D72: =IF(E72="NR",VLOOKUP(B72,'Sovereign Ratings (Moody''s,S&P)'!$G$9:$H$34,2,FALSE()),E72) -> Baa2 | E72: =VLOOKUP(A72,'Ratings worksheet'!$A$2:$C$159,3,FALSE()) -> Baa2
A73: ='Ratings worksheet'!A73 -> Jamaica | B73: =VLOOKUP(A73,'Ratings worksheet'!$A$2:$C$159,2,FALSE()) -> BB | C73: =VLOOKUP(A73,'Ratings worksheet'!$E$2:$H$159,4,FALSE()) -> BB- | D73: =IF(E73="NR",VLOOKUP(B73,'Sovereign Ratings (Moody''s,S&P)'!$G$9:$H$34,2,FALSE()),E73) -> Ba3 | E73: =VLOOKUP(A73,'Ratings worksheet'!$A$2:$C$159,3,FALSE()) -> Ba3
A74: ='Ratings worksheet'!A74 -> Japan | B74: =VLOOKUP(A74,'Ratings worksheet'!$A$2:$C$159,2,FALSE()) -> A+ | C74: =VLOOKUP(A74,'Ratings worksheet'!$E$2:$H$159,4,FALSE()) -> A | D74: =IF(E74="NR",VLOOKUP(B74,'Sovereign Ratings (Moody''s,S&P)'!$G$9:$H$34,2,FALSE()),E74) -> A1 | E74: =VLOOKUP(A74,'Ratings worksheet'!$A$2:$C$159,3,FALSE()) -> A1
A75: ='Ratings worksheet'!A75 -> Jersey (States of) | B75: =VLOOKUP(A75,'Ratings worksheet'!$A$2:$C$159,2,FALSE()) -> AA- | C75: =VLOOKUP(A75,'Ratings worksheet'!$E$2:$H$159,4,FALSE()) -> #N/A | D75: =IF(E75="NR",VLOOKUP(B75,'Sovereign Ratings (Moody''s,S&P)'!$G$9:$H$34,2,FALSE()),E75) -> Aa3 | E75: NR
A76: ='Ratings worksheet'!A76 -> Jordan | B76: =VLOOKUP(A76,'Ratings worksheet'!$A$2:$C$159,2,FALSE()) -> BB- | C76: =VLOOKUP(A76,'Ratings worksheet'!$E$2:$H$159,4,FALSE()) -> BB- | D76: =IF(E76="NR",VLOOKUP(B76,'Sovereign Ratings (Moody''s,S&P)'!$G$9:$H$34,2,FALSE()),E76) -> Ba3 | E76: =VLOOKUP(A76,'Ratings worksheet'!$A$2:$C$159,3,FALSE()) -> Ba3
A77: ='Ratings worksheet'!A77 -> Kazakhstan | B77: =VLOOKUP(A77,'Ratings worksheet'!$A$2:$C$159,2,FALSE()) -> BBB- | C77: =VLOOKUP(A77,'Ratings worksheet'!$E$2:$H$159,4,FALSE()) -> BBB | D77: =IF(E77="NR",VLOOKUP(B77,'Sovereign Ratings (Moody''s,S&P)'!$G$9:$H$34,2,FALSE()),E77) -> Baa1 | E77: =VLOOKUP(A77,'Ratings worksheet'!$A$2:$C$159,3,FALSE()) -> Baa1
A78: ='Ratings worksheet'!A78 -> Kenya | B78: =VLOOKUP(A78,'Ratings worksheet'!$A$2:$C$159,2,FALSE()) -> B | C78: =VLOOKUP(A78,'Ratings worksheet'!$E$2:$H$159,4,FALSE()) -> B- | D78: =IF(E78="NR",VLOOKUP(B78,'Sovereign Ratings (Moody''s,S&P)'!$G$9:$H$34,2,FALSE()),E78) -> B3 | E78: =VLOOKUP(A78,'Ratings worksheet'!$A$2:$C$159,3,FALSE()) -> B3
A79: ='Ratings worksheet'!A79 -> Korea | B79: =VLOOKUP(A79,'Ratings worksheet'!$A$2:$C$159,2,FALSE()) -> AA | C79: =VLOOKUP(A79,'Ratings worksheet'!$E$2:$H$159,4,FALSE()) -> #N/A | D79: =IF(E79="NR",VLOOKUP(B79,'Sovereign Ratings (Moody''s,S&P)'!$G$9:$H$34,2,FALSE()),E79) -> Aa2 | E79: =VLOOKUP(A79,'Ratings worksheet'!$A$2:$C$159,3,FALSE()) -> Aa2
A80: ='Ratings worksheet'!A80 -> Kuwait | B80: =VLOOKUP(A80,'Ratings worksheet'!$A$2:$C$159,2,FALSE()) -> AA- | C80: =VLOOKUP(A80,'Ratings worksheet'!$E$2:$H$159,4,FALSE()) -> AA- | D80: =IF(E80="NR",VLOOKUP(B80,'Sovereign Ratings (Moody''s,S&P)'!$G$9:$H$34,2,FALSE()),E80) -> A1 | E80: =VLOOKUP(A80,'Ratings worksheet'!$A$2:$C$159,3,FALSE()) -> A1
A81: ='Ratings worksheet'!A81 -> Kyrgyzstan | B81: =VLOOKUP(A81,'Ratings worksheet'!$A$2:$C$159,2,FALSE()) -> #N/A | C81: =VLOOKUP(A81,'Ratings worksheet'!$E$2:$H$159,4,FALSE()) -> #N/A | D81: =IF(E81="NR",VLOOKUP(B81,'Sovereign Ratings (Moody''s,S&P)'!$G$9:$H$34,2,FALSE()),E81) -> B3 | E81: =VLOOKUP(A81,'Ratings worksheet'!$A$2:$C$159,3,FALSE()) -> B3
A82: ='Ratings worksheet'!A82 -> Laos | B82: =VLOOKUP(A82,'Ratings worksheet'!$A$2:$C$159,2,FALSE()) -> CCC+ | C82: =VLOOKUP(A82,'Ratings worksheet'!$E$2:$H$159,4,FALSE()) -> CCC+ | D82: =IF(E82="NR",VLOOKUP(B82,'Sovereign Ratings (Moody''s,S&P)'!$G$9:$H$34,2,FALSE()),E82) -> Caa2 | E82: =VLOOKUP(A82,'Ratings worksheet'!$A$2:$C$159,3,FALSE()) -> Caa2
A83: ='Ratings worksheet'!A83 -> Latvia | B83: =VLOOKUP(A83,'Ratings worksheet'!$A$2:$C$159,2,FALSE()) -> A | C83: =VLOOKUP(A83,'Ratings worksheet'!$E$2:$H$159,4,FALSE()) -> A- | D83: =IF(E83="NR",VLOOKUP(B83,'Sovereign Ratings (Moody''s,S&P)'!$G$9:$H$34,2,FALSE()),E83) -> A3 | E83: =VLOOKUP(A83,'Ratings worksheet'!$A$2:$C$159,3,FALSE()) -> A3
A84: ='Ratings worksheet'!A84 -> Lebanon | B84: =VLOOKUP(A84,'Ratings worksheet'!$A$2:$C$159,2,FALSE()) -> SD | C84: =VLOOKUP(A84,'Ratings worksheet'!$E$2:$H$159,4,FALSE()) -> NR | D84: =IF(E84="NR",VLOOKUP(B84,'Sovereign Ratings (Moody''s,S&P)'!$G$9:$H$34,2,FALSE()),E84) -> C | E84: =VLOOKUP(A84,'Ratings worksheet'!$A$2:$C$159,3,FALSE()) -> C
A85: ='Ratings worksheet'!A85 -> Liechtenstein | B85: =VLOOKUP(A85,'Ratings worksheet'!$A$2:$C$159,2,FALSE()) -> AAA | C85: =VLOOKUP(A85,'Ratings worksheet'!$E$2:$H$159,4,FALSE()) -> NR | D85: =IF(E85="NR",VLOOKUP(B85,'Sovereign Ratings (Moody''s,S&P)'!$G$9:$H$34,2,FALSE()),E85) -> Aaa | E85: =VLOOKUP(A85,'Ratings worksheet'!$A$2:$C$159,3,FALSE()) -> NR
A86: ='Ratings worksheet'!A86 -> Lithuania | B86: =VLOOKUP(A86,'Ratings worksheet'!$A$2:$C$159,2,FALSE()) -> A | C86: =VLOOKUP(A86,'Ratings worksheet'!$E$2:$H$159,4,FALSE()) -> A | D86: =IF(E86="NR",VLOOKUP(B86,'Sovereign Ratings (Moody''s,S&P)'!$G$9:$H$34,2,FALSE()),E86) -> A2 | E86: =VLOOKUP(A86,'Ratings worksheet'!$A$2:$C$159,3,FALSE()) -> A2
A87: ='Ratings worksheet'!A87 -> Luxembourg | B87: =VLOOKUP(A87,'Ratings worksheet'!$A$2:$C$159,2,FALSE()) -> AAA | C87: =VLOOKUP(A87,'Ratings worksheet'!$E$2:$H$159,4,FALSE()) -> AAA | D87: =IF(E87="NR",VLOOKUP(B87,'Sovereign Ratings (Moody''s,S&P)'!$G$9:$H$34,2,FALSE()),E87) -> Aaa | E87: =VLOOKUP(A87,'Ratings worksheet'!$A$2:$C$159,3,FALSE()) -> Aaa
... A102: ='Ratings worksheet'!A102 -> Namibia | B102: =VLOOKUP(A102,'Ratings worksheet'!$A$2:$C$159,2,FALSE()) -> 0 | C102: =VLOOKUP(A102,'Ratings worksheet'!$E$2:$H$159,4,FALSE()) -> BB- | D102: =IF(E102="NR",VLOOKUP(B102,'Sovereign Ratings (Moody''s,S&P)'!$G$9:$H$34,2,FALSE()),E102) -> B1 | E102: =VLOOKUP(A102,'Ratings worksheet'!$A$2:$C$159,3,FALSE()) -> B1
A103: ='Ratings worksheet'!E103 -> Nepal | B103: =VLOOKUP(A103,'Ratings worksheet'!$A$2:$C$159,2,FALSE()) -> NR | C103: =VLOOKUP(A103,'Ratings worksheet'!$E$2:$H$159,4,FALSE()) -> BB- | D103: =IF(E103="NR",VLOOKUP(C103,'Sovereign Ratings (Moody''s,S&P)'!$G$9:$H$34,2,FALSE()),E103) -> Ba3 | E103: =VLOOKUP(A103,'Ratings worksheet'!$A$2:$C$159,3,FALSE()) -> NR
A104: ='Ratings worksheet'!A104 -> Netherlands | B104: =VLOOKUP(A104,'Ratings worksheet'!$A$2:$C$159,2,FALSE()) -> AAA | C104: =VLOOKUP(A104,'Ratings worksheet'!$E$2:$H$159,4,FALSE()) -> AAA | D104: =IF(E104="NR",VLOOKUP(B104,'Sovereign Ratings (Moody''s,S&P)'!$G$9:$H$34,2,FALSE()),E104) -> Aaa | E104: =VLOOKUP(A104,'Ratings worksheet'!$A$2:$C$159,3,FALSE()) -> Aaa
A105: ='Ratings worksheet'!A105 -> New Zealand | B105: =VLOOKUP(A105,'Ratings worksheet'!$A$2:$C$159,2,FALSE()) -> AA+ | C105: =VLOOKUP(A105,'Ratings worksheet'!$E$2:$H$159,4,FALSE()) -> AA+ | D105: =IF(E105="NR",VLOOKUP(B105,'Sovereign Ratings (Moody''s,S&P)'!$G$9:$H$34,2,FALSE()),E105) -> Aaa | E105: =VLOOKUP(A105,'Ratings worksheet'!$A$2:$C$159,3,FALSE()) -> Aaa
A106: ='Ratings worksheet'!A106 -> Nicaragua | B106: =VLOOKUP(A106,'Ratings worksheet'!$A$2:$C$159,2,FALSE()) -> B+ | C106: =VLOOKUP(A106,'Ratings worksheet'!$E$2:$H$159,4,FALSE()) -> B | D106: =IF(E106="NR",VLOOKUP(B106,'Sovereign Ratings (Moody''s,S&P)'!$G$9:$H$34,2,FALSE()),E106) -> B2 | E106: =VLOOKUP(A106,'Ratings worksheet'!$A$2:$C$159,3,FALSE()) -> B2
A107: ='Ratings worksheet'!A107 -> Niger | B107: =VLOOKUP(A107,'Ratings worksheet'!$A$2:$C$159,2,FALSE()) -> 0 | C107: =VLOOKUP(A107,'Ratings worksheet'!$E$2:$H$159,4,FALSE()) -> NR | D107: =IF(E107="NR",VLOOKUP(B107,'Sovereign Ratings (Moody''s,S&P)'!$G$9:$H$34,2,FALSE()),E107) -> Caa3 | E107: =VLOOKUP(A107,'Ratings worksheet'!$A$2:$C$159,3,FALSE()) -> Caa3
A108: ='Ratings worksheet'!A108 -> Nigeria | B108: =VLOOKUP(A108,'Ratings worksheet'!$A$2:$C$159,2,FALSE()) -> B- | C108: =VLOOKUP(A108,'Ratings worksheet'!$E$2:$H$159,4,FALSE()) -> B | D108: =IF(E108="NR",VLOOKUP(B108,'Sovereign Ratings (Moody''s,S&P)'!$G$9:$H$34,2,FALSE()),E108) -> B3 | E108: =VLOOKUP(A108,'Ratings worksheet'!$A$2:$C$159,3,FALSE()) -> B3
A109: ='Ratings worksheet'!A109 -> Norway | B109: =VLOOKUP(A109,'Ratings worksheet'!$A$2:$C$159,2,FALSE()) -> AAA | C109: =VLOOKUP(A109,'Ratings worksheet'!$E$2:$H$159,4,FALSE()) -> AAA | D109: =IF(E109="NR",VLOOKUP(B109,'Sovereign Ratings (Moody''s,S&P)'!$G$9:$H$34,2,FALSE()),E109) -> Aaa | E109: =VLOOKUP(A109,'Ratings worksheet'!$A$2:$C$159,3,FALSE()) -> Aaa
A110: ='Ratings worksheet'!A110 -> Oman | B110: =VLOOKUP(A110,'Ratings worksheet'!$A$2:$C$159,2,FALSE()) -> BBB- | C110: =VLOOKUP(A110,'Ratings worksheet'!$E$2:$H$159,4,FALSE()) -> BBB- | D110: =IF(E110="NR",VLOOKUP(B110,'Sovereign Ratings (Moody''s,S&P)'!$G$9:$H$34,2,FALSE()),E110) -> Baa3 | E110: =VLOOKUP(A110,'Ratings worksheet'!$A$2:$C$159,3,FALSE()) -> Baa3
A111: ='Ratings worksheet'!A111 -> Pakistan | B111: =VLOOKUP(A111,'Ratings worksheet'!$A$2:$C$159,2,FALSE()) -> B- | C111: =VLOOKUP(A111,'Ratings worksheet'!$E$2:$H$159,4,FALSE()) -> B- | D111: =IF(E111="NR",VLOOKUP(B111,'Sovereign Ratings (Moody''s,S&P)'!$G$9:$H$34,2,FALSE()),E111) -> Caa1 | E111: =VLOOKUP(A111,'Ratings worksheet'!$A$2:$C$159,3,FALSE()) -> Caa1
A112: ='Ratings worksheet'!A112 -> Panama | B112: =VLOOKUP(A112,'Ratings worksheet'!$A$2:$C$159,2,FALSE()) -> BBB- | C112: =VLOOKUP(A112,'Ratings worksheet'!$E$2:$H$159,4,FALSE()) -> BB+ | D112: =IF(E112="NR",VLOOKUP(B112,'Sovereign Ratings (Moody''s,S&P)'!$G$9:$H$34,2,FALSE()),E112) -> Baa3 | E112: =VLOOKUP(A112,'Ratings worksheet'!$A$2:$C$159,3,FALSE()) -> Baa3
A113: ='Ratings worksheet'!A113 -> Papua New Guinea | B113: =VLOOKUP(A113,'Ratings worksheet'!$A$2:$C$159,2,FALSE()) -> B- | C113: =VLOOKUP(A113,'Ratings worksheet'!$E$2:$H$159,4,FALSE()) -> B+ | D113: =IF(E113="NR",VLOOKUP(B113,'Sovereign Ratings (Moody''s,S&P)'!$G$9:$H$34,2,FALSE()),E113) -> B2 | E113: =VLOOKUP(A113,'Ratings worksheet'!$A$2:$C$159,3,FALSE()) -> B2
A114: ='Ratings worksheet'!A114 -> Paraguay | B114: =VLOOKUP(A114,'Ratings worksheet'!$A$2:$C$159,2,FALSE()) -> BBB- | C114: =VLOOKUP(A114,'Ratings worksheet'!$E$2:$H$159,4,FALSE()) -> BB+ | D114: =IF(E114="NR",VLOOKUP(B114,'Sovereign Ratings (Moody''s,S&P)'!$G$9:$H$34,2,FALSE()),E114) -> Baa3 | E114: =VLOOKUP(A114,'Ratings worksheet'!$A$2:$C$159,3,FALSE()) -> Baa3
A115: ='Ratings worksheet'!A115 -> Peru | B115: =VLOOKUP(A115,'Ratings worksheet'!$A$2:$C$159,2,FALSE()) -> BBB- | C115: =VLOOKUP(A115,'Ratings worksheet'!$E$2:$H$159,4,FALSE()) -> BBB | D115: =IF(E115="NR",VLOOKUP(B115,'Sovereign Ratings (Moody''s,S&P)'!$G$9:$H$34,2,FALSE()),E115) -> Baa1 | E115: =VLOOKUP(A115,'Ratings worksheet'!$A$2:$C$159,3,FALSE()) -> Baa1
... A121: ='Ratings worksheet'!A121 -> Romania | B121: =VLOOKUP(A121,'Ratings worksheet'!$A$2:$C$159,2,FALSE()) -> BBB- | C121: =VLOOKUP(A121,'Ratings worksheet'!$E$2:$H$159,4,FALSE()) -> BBB- | D121: =IF(E121="NR",VLOOKUP(B121,'Sovereign Ratings (Moody''s,S&P)'!$G$9:$H$34,2,FALSE()),E121) -> Baa3 | E121: =VLOOKUP(A121,'Ratings worksheet'!$A$2:$C$159,3,FALSE()) -> Baa3
A122: ='Ratings worksheet'!A123 -> Rwanda | B122: =VLOOKUP(A122,'Ratings worksheet'!$A$2:$C$159,2,FALSE()) -> B+ | C122: =VLOOKUP(A122,'Ratings worksheet'!$E$2:$H$159,4,FALSE()) -> B+ | D122: =IF(E122="NR",VLOOKUP(B122,'Sovereign Ratings (Moody''s,S&P)'!$G$9:$H$34,2,FALSE()),E122) -> B2 | E122: =VLOOKUP(A122,'Ratings worksheet'!$A$2:$C$159,3,FALSE()) -> B2
A123: ='Ratings worksheet'!A124 -> Saudi Arabia | B123: =VLOOKUP(A123,'Ratings worksheet'!$A$2:$C$159,2,FALSE()) -> A+ | C123: =VLOOKUP(A123,'Ratings worksheet'!$E$2:$H$159,4,FALSE()) -> A+ | D123: =IF(E123="NR",VLOOKUP(B123,'Sovereign Ratings (Moody''s,S&P)'!$G$9:$H$34,2,FALSE()),E123) -> Aa3 | E123: =VLOOKUP(A123,'Ratings worksheet'!$A$2:$C$159,3,FALSE()) -> Aa3
A124: ='Ratings worksheet'!A125 -> Senegal | B124: =VLOOKUP(A124,'Ratings worksheet'!$A$2:$C$159,2,FALSE()) -> CCC+ | C124: =VLOOKUP(A124,'Ratings worksheet'!$E$2:$H$159,4,FALSE()) -> NR | D124: =IF(E124="NR",VLOOKUP(B124,'Sovereign Ratings (Moody''s,S&P)'!$G$9:$H$34,2,FALSE()),E124) -> Caa1 | E124: =VLOOKUP(A124,'Ratings worksheet'!$A$2:$C$159,3,FALSE()) -> Caa1
A125: ='Ratings worksheet'!A126 -> Serbia | B125: =VLOOKUP(A125,'Ratings worksheet'!$A$2:$C$159,2,FALSE()) -> BBB- | C125: =VLOOKUP(A125,'Ratings worksheet'!$E$2:$H$159,4,FALSE()) -> BB+ | D125: =IF(E125="NR",VLOOKUP(B125,'Sovereign Ratings (Moody''s,S&P)'!$G$9:$H$34,2,FALSE()),E125) -> Ba2 | E125: =VLOOKUP(A125,'Ratings worksheet'!$A$2:$C$159,3,FALSE()) -> Ba2
A126: ='Ratings worksheet'!A127 -> Sharjah | B126: =VLOOKUP(A126,'Ratings worksheet'!$A$2:$C$159,2,FALSE()) -> NR | C126: =VLOOKUP(A126,'Ratings worksheet'!$E$2:$H$159,4,FALSE()) -> #N/A | D126: =IF(E126="NR",VLOOKUP(B126,'Sovereign Ratings (Moody''s,S&P)'!$G$9:$H$34,2,FALSE()),E126) -> Ba1 | E126: =VLOOKUP(A126,'Ratings worksheet'!$A$2:$C$159,3,FALSE()) -> Ba1
A127: ='Ratings worksheet'!A128 -> Singapore | B127: =VLOOKUP(A127,'Ratings worksheet'!$A$2:$C$159,2,FALSE()) -> AAA | C127: =VLOOKUP(A127,'Ratings worksheet'!$E$2:$H$159,4,FALSE()) -> AAA | D127: =IF(E127="NR",VLOOKUP(B127,'Sovereign Ratings (Moody''s,S&P)'!$G$9:$H$34,2,FALSE()),E127) -> Aaa | E127: =VLOOKUP(A127,'Ratings worksheet'!$A$2:$C$159,3,FALSE()) -> Aaa
A128: ='Ratings worksheet'!A129 -> Slovakia | B128: =VLOOKUP(A128,'Ratings worksheet'!$A$2:$C$159,2,FALSE()) -> A+ | C128: =VLOOKUP(A128,'Ratings worksheet'!$E$2:$H$159,4,FALSE()) -> A- | D128: =IF(E128="NR",VLOOKUP(B128,'Sovereign Ratings (Moody''s,S&P)'!$G$9:$H$34,2,FALSE()),E128) -> A3 | E128: =VLOOKUP(A128,'Ratings worksheet'!$A$2:$C$159,3,FALSE()) -> A3
A129: ='Ratings worksheet'!A130 -> Slovenia | B129: =VLOOKUP(A129,'Ratings worksheet'!$A$2:$C$159,2,FALSE()) -> AA | C129: =VLOOKUP(A129,'Ratings worksheet'!$E$2:$H$159,4,FALSE()) -> A+ | D129: =IF(E129="NR",VLOOKUP(B129,'Sovereign Ratings (Moody''s,S&P)'!$G$9:$H$34,2,FALSE()),E129) -> A3 | E129: =VLOOKUP(A129,'Ratings worksheet'!$A$2:$C$159,3,FALSE()) -> A3
A130: ='Ratings worksheet'!A131 -> Solomon Islands | B130: =VLOOKUP(A130,'Ratings worksheet'!$A$2:$C$159,2,FALSE()) -> 0 | C130: =VLOOKUP(A130,'Ratings worksheet'!$E$2:$H$159,4,FALSE()) -> NR | D130: =IF(E130="NR",VLOOKUP(B130,'Sovereign Ratings (Moody''s,S&P)'!$G$9:$H$34,2,FALSE()),E130) -> Caa1 | E130: =VLOOKUP(A130,'Ratings worksheet'!$A$2:$C$159,3,FALSE()) -> Caa1
A131: ='Ratings worksheet'!A132 -> South Africa | B131: =VLOOKUP(A131,'Ratings worksheet'!$A$2:$C$159,2,FALSE()) -> BB | C131: =VLOOKUP(A131,'Ratings worksheet'!$E$2:$H$159,4,FALSE()) -> BB- | D131: =IF(E131="NR",VLOOKUP(B131,'Sovereign Ratings (Moody''s,S&P)'!$G$9:$H$34,2,FALSE()),E131) -> Ba2 | E131: =VLOOKUP(A131,'Ratings worksheet'!$A$2:$C$159,3,FALSE()) -> Ba2
A132: ='Ratings worksheet'!A133 -> Spain | B132: =VLOOKUP(A132,'Ratings worksheet'!$A$2:$C$159,2,FALSE()) -> A+ | C132: =VLOOKUP(A132,'Ratings worksheet'!$E$2:$H$159,4,FALSE()) -> A | D132: =IF(E132="NR",VLOOKUP(B132,'Sovereign Ratings (Moody''s,S&P)'!$G$9:$H$34,2,FALSE()),E132) -> A3 | E132: =VLOOKUP(A132,'Ratings worksheet'!$A$2:$C$159,3,FALSE()) -> A3
A133: ='Ratings worksheet'!A134 -> Sri Lanka | B133: =VLOOKUP(A133,'Ratings worksheet'!$A$2:$C$159,2,FALSE()) -> CCC+ | C133: =VLOOKUP(A133,'Ratings worksheet'!$E$2:$H$159,4,FALSE()) -> CCC+ | D133: =IF(E133="NR",VLOOKUP(B133,'Sovereign Ratings (Moody''s,S&P)'!$G$9:$H$34,2,FALSE()),E133) -> Ca | E133: =VLOOKUP(A133,'Ratings worksheet'!$A$2:$C$159,3,FALSE()) -> Ca
... A158: ='Ratings worksheet'!A159 -> Zambia | B158: =VLOOKUP(A158,'Ratings worksheet'!$A$2:$C$159,2,FALSE()) -> CCC+ | C158: =VLOOKUP(A158,'Ratings worksheet'!$E$2:$H$159,4,FALSE()) -> B- | D158: =IF(E158="NR",VLOOKUP(B158,'Sovereign Ratings (Moody''s,S&P)'!$G$9:$H$34,2,FALSE()),E158) -> Caa2 | E158: =VLOOKUP(A158,'Ratings worksheet'!$A$2:$C$159,3,FALSE()) -> Caa2

Sheet Regional lookup table
A1: Country | B1: Region
A2: Abu Dhabi | B2: Middle East
A3: Albania | B3: Eastern Europe & Russia
A4: ='Sovereign Ratings (Moody''s,S&P)'!A4 -> Andorra (Principality of) | B4: Western Europe
A5: Angola | B5: Africa
A6: Argentina | B6: Central and South America
A7: Armenia | B7: Eastern Europe & Russia
A8: Aruba | B8: Caribbean
A9: Australia | B9: Australia & New Zealand
A10: Austria | B10: Western Europe
A11: Azerbaijan | B11: Eastern Europe & Russia
A12: Bahamas | B12: Caribbean
A13: Bahrain | B13: Middle East
A14: Bangladesh | B14: Asia
A15: Barbados | B15: Caribbean
A16: Belarus | B16: Eastern Europe & Russia
... A162: Zambia | B162: Africa

Sheet Default Spreads for Ratings
A1: Rating | B1: Default Spread (7/1/25) | C1: Updated Default Spread (12/31/25) | E1: Country | F1: Moody's rating | G1: 44377 | H1: 44560 | I1: CDS % Change | K1: Country | L1: 44560
A2: A1 | B2: 69.336444 | C2: =B2*(1+$I$84) -> 59.929264 | E2: Abu Dhabi | F2: =VLOOKUP(E2,'Sovereign Ratings (Moody''s,S&P)'!A2:D158,4,FALSE()) -> Aa2 | G2: 0.0068 | H2: =VLOOKUP(E2,$K$2:$L$91,2,FALSE()) -> 0.006 | I2: =IF(H2="NA","NA",IF(G2="NA","NA",H2/G2-1)) -> -0.11764706 | K2: Abu Dhabi | L2: 0.006
A3: A2 | B3: 83.203732 | C3: =B3*(1+$I$84) -> 71.915117 | E3: Algeria | F3: =VLOOKUP(E3,'Sovereign Ratings (Moody''s,S&P)'!A3:D159,4,FALSE()) -> #N/A | G3: 0.014 | H3: =VLOOKUP(E3,$K$2:$L$91,2,FALSE()) -> 0.0134 | I3: =IF(H3="NA","NA",IF(G3="NA","NA",H3/G3-1)) -> -0.042857143 | K3: Algeria | L3: 0.0134
A4: A3 | B4: 117.87195 | C4: =B4*(1+$I$84) -> 101.87975 | E4: Angola | F4: =VLOOKUP(E4,'Sovereign Ratings (Moody''s,S&P)'!A4:D160,4,FALSE()) -> B3 | G4: 0.0716 | H4: =VLOOKUP(E4,$K$2:$L$91,2,FALSE()) -> 0.0624 | I4: =IF(H4="NA","NA",IF(G4="NA","NA",H4/G4-1)) -> -0.12849162 | K4: Angola | L4: 0.0624
A5: Aa1 | B5: 27 | C5: =B5*(1+$I$84) -> 23.336792 | D5: * Adjusted to reflect US addition to Aa1 countries | E5: Australia | F5: =VLOOKUP(E5,'Sovereign Ratings (Moody''s,S&P)'!A5:D161,4,FALSE()) -> Aaa | G5: 0.0018 | H5: =VLOOKUP(E5,$K$2:$L$91,2,FALSE()) -> 0.0019 | I5: =IF(H5="NA","NA",IF(G5="NA","NA",H5/G5-1)) -> 0.055555556 | K5: Argentina | L5: 0.0694
A6: Aa2 | B6: 48.53551 | C6: =B6*(1+$I$84) -> 41.950485 | E6: Austria | F6: =VLOOKUP(E6,'Sovereign Ratings (Moody''s,S&P)'!A6:D162,4,FALSE()) -> Aa1 | G6: 0.0032 | H6: =VLOOKUP(E6,$K$2:$L$91,2,FALSE()) -> 0.0028 | I6: =IF(H6="NA","NA",IF(G6="NA","NA",H6/G6-1)) -> -0.125 | K6: Australia | L6: 0.0019
A7: Aa3 | B7: 58.935977 | C7: =B7*(1+$I$84) -> 50.939875 | E7: Bahrain | F7: =VLOOKUP(E7,'Sovereign Ratings (Moody''s,S&P)'!A7:D163,4,FALSE()) -> B2 | G7: 0.0279 | H7: =VLOOKUP(E7,$K$2:$L$91,2,FALSE()) -> 0.0247 | I7: =IF(H7="NA","NA",IF(G7="NA","NA",H7/G7-1)) -> -0.11469534 | K7: Austria | L7: 0.0028
A8: Aaa | B8: 0 | C8: =B8*(1+$I$84) -> 0 | E8: Belgium | F8: =VLOOKUP(E8,'Sovereign Ratings (Moody''s,S&P)'!A8:D164,4,FALSE()) -> Aa3 | G8: 0.005 | H8: =VLOOKUP(E8,$K$2:$L$91,2,FALSE()) -> 0.004 | I8: =IF(H8="NA","NA",IF(G8="NA","NA",H8/G8-1)) -> -0.2 | K8: Bahrain | L8: 0.0247
A9: B1 | B9: 442.59763 | C9: =B9*(1+$I$84) -> 382.54847 | E9: Brazil | F9: =VLOOKUP(E9,'Sovereign Ratings (Moody''s,S&P)'!A9:D165,4,FALSE()) -> Ba1 | G9: 0.0255 | H9: =VLOOKUP(E9,$K$2:$L$91,2,FALSE()) -> 0.0235 | I9: =IF(H9="NA","NA",IF(G9="NA","NA",H9/G9-1)) -> -0.078431373 | K9: Belgium | L9: 0.004
A10: B2 | B10: 540.82426 | C10: =B10*(1+$I$84) -> 467.44826 | E10: Bulgaria | F10: =VLOOKUP(E10,'Sovereign Ratings (Moody''s,S&P)'!A10:D166,4,FALSE()) -> Baa1 | G10: 0.0112 | H10: =VLOOKUP(E10,$K$2:$L$91,2,FALSE()) -> 0.0077 | I10: =IF(H10="NA","NA",IF(G10="NA","NA",H10/G10-1)) -> -0.3125 | K10: Brazil | L10: 0.0235
A11: B3 | B11: 639.05089 | C11: =B11*(1+$I$84) -> 552.34805 | E11: Cameroon | F11: =VLOOKUP(E11,'Sovereign Ratings (Moody''s,S&P)'!A11:D167,4,FALSE()) -> Caa1 | G11: 0.0803 | H11: =VLOOKUP(E11,$K$2:$L$91,2,FALSE()) -> 0.0687 | I11: =IF(H11="NA","NA",IF(G11="NA","NA",H11/G11-1)) -> -0.14445828 | K11: Bulgaria | L11: 0.0077
A12: Ba1 | B12: 246.14437 | C12: =B12*(1+$I$84) -> 212.74889 | E12: Canada | F12: =VLOOKUP(E12,'Sovereign Ratings (Moody''s,S&P)'!A12:D168,4,FALSE()) -> Aaa | G12: 0.0037 | H12: =VLOOKUP(E12,$K$2:$L$91,2,FALSE()) -> 0.0033 | I12: =IF(H12="NA","NA",IF(G12="NA","NA",H12/G12-1)) -> -0.10810811 | K12: Cameroon | L12: 0.0687
A13: Ba2 | B13: 295.83549 | C13: =B13*(1+$I$84) -> 255.69819 | E13: Chile | F13: =VLOOKUP(E13,'Sovereign Ratings (Moody''s,S&P)'!A13:D169,4,FALSE()) -> A2 | G13: 0.0104 | H13: =VLOOKUP(E13,$K$2:$L$91,2,FALSE()) -> 0.0087 | I13: =IF(H13="NA","NA",IF(G13="NA","NA",H13/G13-1)) -> -0.16346154 | K13: Canada | L13: 0.0033
A14: Ba3 | B14: 353.61586 | C14: =B14*(1+$I$84) -> 305.63925 | E14: China | F14: =VLOOKUP(E14,'Sovereign Ratings (Moody''s,S&P)'!A14:D170,4,FALSE()) -> A1 | G14: 0.0075 | H14: =VLOOKUP(E14,$K$2:$L$91,2,FALSE()) -> 0.0064 | I14: =IF(H14="NA","NA",IF(G14="NA","NA",H14/G14-1)) -> -0.14666667 | K14: Chile | L14: 0.0087
A15: Baa1 | B15: 157.16261 | C15: =B15*(1+$I$84) -> 135.83967 | E15: Colombia | F15: =VLOOKUP(E15,'Sovereign Ratings (Moody''s,S&P)'!A15:D171,4,FALSE()) -> Baa3 | G15: 0.0348 | H15: =VLOOKUP(E15,$K$2:$L$91,2,FALSE()) -> 0.0334 | I15: =IF(H15="NA","NA",IF(G15="NA","NA",H15/G15-1)) -> -0.040229885 | K15: China | L15: 0.0064
A16: Baa2 | B16: 187.2084 | C16: =B16*(1+$I$84) -> 161.80901 | E16: Costa Rica | F16: =VLOOKUP(E16,'Sovereign Ratings (Moody''s,S&P)'!A16:D172,4,FALSE()) -> Ba2 | G16: 0.025 | H16: =VLOOKUP(E16,$K$2:$L$91,2,FALSE()) -> 0.0175 | I16: =IF(H16="NA","NA",IF(G16="NA","NA",H16/G16-1)) -> -0.3 | K16: Colombia | L16: 0.0334
A17: Baa3 | B17: 216.09858 | C17: =B17*(1+$I$84) -> 186.77954 | E17: Croatia | F17: =VLOOKUP(E17,'Sovereign Ratings (Moody''s,S&P)'!A17:D173,4,FALSE()) -> A3 | G17: 0.0124 | H17: =VLOOKUP(E17,$K$2:$L$91,2,FALSE()) -> 0.0102 | I17: =IF(H17="NA","NA",IF(G17="NA","NA",H17/G17-1)) -> -0.17741935 | K17: Costa Rica | L17: 0.0175
... A21: Caa3 | B21: 983.42189 | C21: =B21*(1+$I$84) -> 849.99673 | E21: Dubai | F21: =VLOOKUP(E21,'Sovereign Ratings (Moody''s,S&P)'!A21:D177,4,FALSE()) -> #N/A | G21: 0.0098 | H21: =VLOOKUP(E21,$K$2:$L$91,2,FALSE()) -> 0.0082 | I21: =IF(H21="NA","NA",IF(G21="NA","NA",H21/G21-1)) -> -0.16326531 | K21: Denmark | L21: 0.0018
A22: NR | B22: NA | C22: NA | E22: Ecuador | F22: =VLOOKUP(E22,'Sovereign Ratings (Moody''s,S&P)'!A22:D178,4,FALSE()) -> Caa3 | G22: 0.1242 | H22: =VLOOKUP(E22,$K$2:$L$91,2,FALSE()) -> 0.0567 | I22: =IF(H22="NA","NA",IF(G22="NA","NA",H22/G22-1)) -> -0.54347826 | K22: Dubai | L22: 0.0082
E23: Egypt | F23: =VLOOKUP(E23,'Sovereign Ratings (Moody''s,S&P)'!A23:D179,4,FALSE()) -> Caa1 | G23: 0.0661 | H23: =VLOOKUP(E23,$K$2:$L$91,2,FALSE()) -> 0.0355 | I23: =IF(H23="NA","NA",IF(G23="NA","NA",H23/G23-1)) -> -0.46293495 | K23: Ecuador | L23: 0.0567
E24: El Salvador | F24: =VLOOKUP(E24,'Sovereign Ratings (Moody''s,S&P)'!A24:D180,4,FALSE()) -> B3 | G24: 0.0447 | H24: =VLOOKUP(E24,$K$2:$L$91,2,FALSE()) -> 0.034 | I24: =IF(H24="NA","NA",IF(G24="NA","NA",H24/G24-1)) -> -0.2393736 | K24: Egypt | L24: 0.0355
E25: Estonia | F25: =VLOOKUP(E25,'Sovereign Ratings (Moody''s,S&P)'!A25:D181,4,FALSE()) -> A1 | G25: 0.0093 | H25: =VLOOKUP(E25,$K$2:$L$91,2,FALSE()) -> 0.01 | I25: =IF(H25="NA","NA",IF(G25="NA","NA",H25/G25-1)) -> 0.075268817 | K25: El Salvador | L25: 0.034
E26: Finland | F26: =VLOOKUP(E26,'Sovereign Ratings (Moody''s,S&P)'!A26:D182,4,FALSE()) -> Aa1 | G26: 0.0032 | H26: =VLOOKUP(E26,$K$2:$L$91,2,FALSE()) -> 0.0026 | I26: =IF(H26="NA","NA",IF(G26="NA","NA",H26/G26-1)) -> -0.1875 | K26: Estonia | L26: 0.01
E27: France | F27: =VLOOKUP(E27,'Sovereign Ratings (Moody''s,S&P)'!A27:D183,4,FALSE()) -> Aa3 | G27: 0.0068 | H27: =VLOOKUP(E27,$K$2:$L$91,2,FALSE()) -> 0.0064 | I27: =IF(H27="NA","NA",IF(G27="NA","NA",H27/G27-1)) -> -0.058823529 | K27: Ethiopia | L27: NA
E28: Germany | F28: =VLOOKUP(E28,'Sovereign Ratings (Moody''s,S&P)'!A28:D184,4,FALSE()) -> Aaa | G28: 0.0024 | H28: =VLOOKUP(E28,$K$2:$L$91,2,FALSE()) -> 0.0021 | I28: =IF(H28="NA","NA",IF(G28="NA","NA",H28/G28-1)) -> -0.125 | K28: Finland | L28: 0.0026
E29: Greece | F29: =VLOOKUP(E29,'Sovereign Ratings (Moody''s,S&P)'!A29:D185,4,FALSE()) -> Baa3 | G29: 0.0104 | H29: =VLOOKUP(E29,$K$2:$L$91,2,FALSE()) -> 0.0075 | I29: =IF(H29="NA","NA",IF(G29="NA","NA",H29/G29-1)) -> -0.27884615 | K29: France | L29: 0.0064
E30: Guatemala | F30: =VLOOKUP(E30,'Sovereign Ratings (Moody''s,S&P)'!A30:D186,4,FALSE()) -> Ba1 | G30: 0.0221 | H30: =VLOOKUP(E30,$K$2:$L$91,2,FALSE()) -> 0.0171 | I30: =IF(H30="NA","NA",IF(G30="NA","NA",H30/G30-1)) -> -0.22624434 | K30: Gabon | L30: 0.0854
E31: Hong Kong | F31: =VLOOKUP(E31,'Sovereign Ratings (Moody''s,S&P)'!A31:D187,4,FALSE()) -> Aa3 | G31: 0.0059 | H31: =VLOOKUP(E31,$K$2:$L$91,2,FALSE()) -> 0.0044 | I31: =IF(H31="NA","NA",IF(G31="NA","NA",H31/G31-1)) -> -0.25423729 | K31: Germany | L31: 0.0021
E32: Hungary | F32: =VLOOKUP(E32,'Sovereign Ratings (Moody''s,S&P)'!A32:D188,4,FALSE()) -> Baa2 | G32: 0.0183 | H32: =VLOOKUP(E32,$K$2:$L$91,2,FALSE()) -> 0.016 | I32: =IF(H32="NA","NA",IF(G32="NA","NA",H32/G32-1)) -> -0.12568306 | K32: Greece | L32: 0.0075
E33: Iceland | F33: =VLOOKUP(E33,'Sovereign Ratings (Moody''s,S&P)'!A33:D189,4,FALSE()) -> A1 | G33: 0.0047 | H33: =VLOOKUP(E33,$K$2:$L$91,2,FALSE()) -> 0.0045 | I33: =IF(H33="NA","NA",IF(G33="NA","NA",H33/G33-1)) -> -0.042553191 | K33: Guatemala | L33: 0.0171
E34: India | F34: =VLOOKUP(E34,'Sovereign Ratings (Moody''s,S&P)'!A34:D190,4,FALSE()) -> Baa3 | G34: 0.0084 | H34: =VLOOKUP(E34,$K$2:$L$91,2,FALSE()) -> 0.008 | I34: =IF(H34="NA","NA",IF(G34="NA","NA",H34/G34-1)) -> -0.047619048 | K34: Hong Kong | L34: 0.0044
E35: Indonesia | F35: =VLOOKUP(E35,'Sovereign Ratings (Moody''s,S&P)'!A35:D191,4,FALSE()) -> Baa2 | G35: 0.0134 | H35: =VLOOKUP(E35,$K$2:$L$91,2,FALSE()) -> 0.0119 | I35: =IF(H35="NA","NA",IF(G35="NA","NA",H35/G35-1)) -> -0.1119403 | K35: Hungary | L35: 0.016
E36: Iraq | F36: =VLOOKUP(E36,'Sovereign Ratings (Moody''s,S&P)'!A36:D192,4,FALSE()) -> Caa1 | G36: 0.0405 | H36: =VLOOKUP(E36,$K$2:$L$91,2,FALSE()) -> 0.0289 | I36: =IF(H36="NA","NA",IF(G36="NA","NA",H36/G36-1)) -> -0.28641975 | K36: Iceland | L36: 0.0045
E37: Ireland | F37: =VLOOKUP(E37,'Sovereign Ratings (Moody''s,S&P)'!A37:D193,4,FALSE()) -> Aa3 | G37: 0.0038 | H37: =VLOOKUP(E37,$K$2:$L$91,2,FALSE()) -> 0.0034 | I37: =IF(H37="NA","NA",IF(G37="NA","NA",H37/G37-1)) -> -0.10526316 | K37: India | L37: 0.008
E38: Israel | F38: =VLOOKUP(E38,'Sovereign Ratings (Moody''s,S&P)'!A38:D194,4,FALSE()) -> Baa1 | G38: 0.0139 | H38: =VLOOKUP(E38,$K$2:$L$91,2,FALSE()) -> 0.0113 | I38: =IF(H38="NA","NA",IF(G38="NA","NA",H38/G38-1)) -> -0.18705036 | K38: Indonesia | L38: 0.0119
E39: Italy | F39: =VLOOKUP(E39,'Sovereign Ratings (Moody''s,S&P)'!A39:D195,4,FALSE()) -> Baa2 | G39: 0.0098 | H39: =VLOOKUP(E39,$K$2:$L$91,2,FALSE()) -> 0.0061 | I39: =IF(H39="NA","NA",IF(G39="NA","NA",H39/G39-1)) -> -0.37755102 | K39: Iraq | L39: 0.0289
... E48: Mexico | F48: =VLOOKUP(E48,'Sovereign Ratings (Moody''s,S&P)'!A48:D204,4,FALSE()) -> Baa2 | G48: 0.0186 | H48: =VLOOKUP(E48,$K$2:$L$91,2,FALSE()) -> 0.0166 | I48: =IF(H48="NA","NA",IF(G48="NA","NA",H48/G48-1)) -> -0.10752688 | K48: Latvia | L48: 0.0082
E49: Morocco | F49: =VLOOKUP(E49,'Sovereign Ratings (Moody''s,S&P)'!A49:D205,4,FALSE()) -> Ba1 | G49: 0.016 | H49: =VLOOKUP(E49,$K$2:$L$91,2,FALSE()) -> 0.013 | I49: =IF(H49="NA","NA",IF(G49="NA","NA",H49/G49-1)) -> -0.1875 | K49: Lebanon | L49: NA
E50: Namibia | F50: =VLOOKUP(E50,'Sovereign Ratings (Moody''s,S&P)'!A50:D206,4,FALSE()) -> B1 | G50: 0.0365 | H50: =VLOOKUP(E50,$K$2:$L$91,2,FALSE()) -> 0.0341 | I50: =IF(H50="NA","NA",IF(G50="NA","NA",H50/G50-1)) -> -0.065753425 | K50: Lithuania | L50: 0.0082
E51: Netherlands | F51: =VLOOKUP(E51,'Sovereign Ratings (Moody''s,S&P)'!A51:D207,4,FALSE()) -> Aaa | G51: 0.0025 | H51: =VLOOKUP(E51,$K$2:$L$91,2,FALSE()) -> 0.002 | I51: =IF(H51="NA","NA",IF(G51="NA","NA",H51/G51-1)) -> -0.2 | K51: Malaysia | L51: 0.0067
E52: New Zealand | F52: =VLOOKUP(E52,'Sovereign Ratings (Moody''s,S&P)'!A52:D208,4,FALSE()) -> Aaa | G52: 0.0023 | H52: =VLOOKUP(E52,$K$2:$L$91,2,FALSE()) -> 0.0023 | I52: =IF(H52="NA","NA",IF(G52="NA","NA",H52/G52-1)) -> 0 | K52: Mexico | L52: 0.0166
E53: Nicaragua | F53: =VLOOKUP(E53,'Sovereign Ratings (Moody''s,S&P)'!A53:D209,4,FALSE()) -> B2 | G53: 0.0637 | H53: =VLOOKUP(E53,$K$2:$L$91,2,FALSE()) -> 0.0529 | I53: =IF(H53="NA","NA",IF(G53="NA","NA",H53/G53-1)) -> -0.16954474 | K53: Mongolia | L53: 0.0326
E54: Nigeria | F54: =VLOOKUP(E54,'Sovereign Ratings (Moody''s,S&P)'!A54:D210,4,FALSE()) -> B3 | G54: 0.0605 | H54: =VLOOKUP(E54,$K$2:$L$91,2,FALSE()) -> 0.0391 | I54: =IF(H54="NA","NA",IF(G54="NA","NA",H54/G54-1)) -> -0.35371901 | K54: Morocco | L54: 0.013
E55: Norway | F55: =VLOOKUP(E55,'Sovereign Ratings (Moody''s,S&P)'!A55:D211,4,FALSE()) -> Aaa | G55: 0.0022 | H55: =VLOOKUP(E55,$K$2:$L$91,2,FALSE()) -> 0.0018 | I55: =IF(H55="NA","NA",IF(G55="NA","NA",H55/G55-1)) -> -0.18181818 | K55: Namibia | L55: 0.0341
E56: Oman | F56: =VLOOKUP(E56,'Sovereign Ratings (Moody''s,S&P)'!A56:D212,4,FALSE()) -> Baa3 | G56: 0.0166 | H56: =VLOOKUP(E56,$K$2:$L$91,2,FALSE()) -> 0.013 | I56: =IF(H56="NA","NA",IF(G56="NA","NA",H56/G56-1)) -> -0.21686747 | K56: Netherlands | L56: 0.002
E57: Pakistan | F57: =VLOOKUP(E57,'Sovereign Ratings (Moody''s,S&P)'!A57:D213,4,FALSE()) -> Caa1 | G57: 0.0764 | H57: =VLOOKUP(E57,$K$2:$L$91,2,FALSE()) -> 0.0523 | I57: =IF(H57="NA","NA",IF(G57="NA","NA",H57/G57-1)) -> -0.31544503 | K57: New Zealand | L57: 0.0023
E58: Panama | F58: =VLOOKUP(E58,'Sovereign Ratings (Moody''s,S&P)'!A58:D214,4,FALSE()) -> Baa3 | G58: 0.0296 | H58: =VLOOKUP(E58,$K$2:$L$91,2,FALSE()) -> 0.0222 | I58: =IF(H58="NA","NA",IF(G58="NA","NA",H58/G58-1)) -> -0.25 | K58: Nicaragua | L58: 0.0529
E59: Peru | F59: =VLOOKUP(E59,'Sovereign Ratings (Moody''s,S&P)'!A59:D215,4,FALSE()) -> Baa1 | G59: 0.0139 | H59: =VLOOKUP(E59,$K$2:$L$91,2,FALSE()) -> 0.0126 | I59: =IF(H59="NA","NA",IF(G59="NA","NA",H59/G59-1)) -> -0.09352518 | K59: Nigeria | L59: 0.0391
E60: Philippines | F60: =VLOOKUP(E60,'Sovereign Ratings (Moody''s,S&P)'!A60:D216,4,FALSE()) -> Baa2 | G60: 0.0115 | H60: =VLOOKUP(E60,$K$2:$L$91,2,FALSE()) -> 0.0102 | I60: =IF(H60="NA","NA",IF(G60="NA","NA",H60/G60-1)) -> -0.11304348 | K60: Norway | L60: 0.0018
E61: Poland | F61: =VLOOKUP(E61,'Sovereign Ratings (Moody''s,S&P)'!A61:D217,4,FALSE()) -> A2 | G61: 0.011 | H61: =VLOOKUP(E61,$K$2:$L$91,2,FALSE()) -> 0.01 | I61: =IF(H61="NA","NA",IF(G61="NA","NA",H61/G61-1)) -> -0.090909091 | K61: Oman | L61: 0.013
... E64: Romania | F64: =VLOOKUP(E64,'Sovereign Ratings (Moody''s,S&P)'!A64:D220,4,FALSE()) -> Baa3 | G64: 0.0267 | H64: =VLOOKUP(E64,$K$2:$L$91,2,FALSE()) -> 0.0211 | I64: =IF(H64="NA","NA",IF(G64="NA","NA",H64/G64-1)) -> -0.20973783 | K64: Peru | L64: 0.0126
E65: Russia | F65: MR | G65: NA | H65: =VLOOKUP(E65,$K$2:$L$91,2,FALSE()) -> NA | I65: =IF(H65="NA","NA",IF(G65="NA","NA",H65/G65-1)) -> NA | K65: Philippines | L65: 0.0102
E66: Rwanda | F66: =VLOOKUP(E66,'Sovereign Ratings (Moody''s,S&P)'!A66:D222,4,FALSE()) -> B2 | G66: 0.0543 | H66: =VLOOKUP(E66,$K$2:$L$91,2,FALSE()) -> 0.0403 | I66: =IF(H66="NA","NA",IF(G66="NA","NA",H66/G66-1)) -> -0.25782689 | K66: Poland | L66: 0.01
E67: Saudi Arabia | F67: =VLOOKUP(E67,'Sovereign Ratings (Moody''s,S&P)'!A67:D223,4,FALSE()) -> Aa3 | G67: 0.0112 | H67: =VLOOKUP(E67,$K$2:$L$91,2,FALSE()) -> 0.0112 | I67: =IF(H67="NA","NA",IF(G67="NA","NA",H67/G67-1)) -> 0 | K67: Portugal | L67: 0.0045
E68: Senegal | F68: =VLOOKUP(E68,'Sovereign Ratings (Moody''s,S&P)'!A68:D224,4,FALSE()) -> Caa1 | G68: 0.0783 | H68: =VLOOKUP(E68,$K$2:$L$91,2,FALSE()) -> 0.0993 | I68: =IF(H68="NA","NA",IF(G68="NA","NA",H68/G68-1)) -> 0.26819923 | K68: Qatar | L68: 0.0061
E69: Serbia | F69: =VLOOKUP(E69,'Sovereign Ratings (Moody''s,S&P)'!A69:D225,4,FALSE()) -> Ba2 | G69: 0.023 | H69: =VLOOKUP(E69,$K$2:$L$91,2,FALSE()) -> 0.0196 | I69: =IF(H69="NA","NA",IF(G69="NA","NA",H69/G69-1)) -> -0.14782609 | K69: Romania | L69: 0.0211
E70: Slovakia | F70: =VLOOKUP(E70,'Sovereign Ratings (Moody''s,S&P)'!A70:D226,4,FALSE()) -> A3 | G70: 0.0061 | H70: =VLOOKUP(E70,$K$2:$L$91,2,FALSE()) -> 0.0057 | I70: =IF(H70="NA","NA",IF(G70="NA","NA",H70/G70-1)) -> -0.06557377 | K70: Russia | L70: NA
E71: Slovenia | F71: =VLOOKUP(E71,'Sovereign Ratings (Moody''s,S&P)'!A71:D227,4,FALSE()) -> A3 | G71: 0.007 | H71: =VLOOKUP(E71,$K$2:$L$91,2,FALSE()) -> 0.0067 | I71: =IF(H71="NA","NA",IF(G71="NA","NA",H71/G71-1)) -> -0.042857143 | K71: Rwanda | L71: 0.0403
E72: South Africa | F72: =VLOOKUP(E72,'Sovereign Ratings (Moody''s,S&P)'!A72:D228,4,FALSE()) -> Ba2 | G72: 0.0301 | H72: =VLOOKUP(E72,$K$2:$L$91,2,FALSE()) -> 0.024 | I72: =IF(H72="NA","NA",IF(G72="NA","NA",H72/G72-1)) -> -0.20265781 | K72: Saudi Arabia | L72: 0.0112
E73: Spain | F73: =VLOOKUP(E73,'Sovereign Ratings (Moody''s,S&P)'!A73:D229,4,FALSE()) -> A3 | G73: 0.0064 | H73: =VLOOKUP(E73,$K$2:$L$91,2,FALSE()) -> 0.0045 | I73: =IF(H73="NA","NA",IF(G73="NA","NA",H73/G73-1)) -> -0.296875 | K73: Senegal | L73: 0.0993
E74: Sweden | F74: =VLOOKUP(E74,'Sovereign Ratings (Moody''s,S&P)'!A74:D230,4,FALSE()) -> Aaa | G74: 0.0025 | H74: =VLOOKUP(E74,$K$2:$L$91,2,FALSE()) -> 0.002 | I74: =IF(H74="NA","NA",IF(G74="NA","NA",H74/G74-1)) -> -0.2 | K74: Serbia | L74: 0.0196
E75: Switzerland | F75: =VLOOKUP(E75,'Sovereign Ratings (Moody''s,S&P)'!A75:D231,4,FALSE()) -> Aaa | G75: 0.0017 | H75: =VLOOKUP(E75,$K$2:$L$91,2,FALSE()) -> 0.0014 | I75: =IF(H75="NA","NA",IF(G75="NA","NA",H75/G75-1)) -> -0.17647059 | K75: Slovakia | L75: 0.0057
E76: Thailand | F76: =VLOOKUP(E76,'Sovereign Ratings (Moody''s,S&P)'!A76:D232,4,FALSE()) -> Baa1 | G76: 0.0072 | H76: =VLOOKUP(E76,$K$2:$L$91,2,FALSE()) -> 0.0066 | I76: =IF(H76="NA","NA",IF(G76="NA","NA",H76/G76-1)) -> -0.083333333 | K76: Slovenia | L76: 0.0067
E77: Tunisia | F77: =VLOOKUP(E77,'Sovereign Ratings (Moody''s,S&P)'!A77:D233,4,FALSE()) -> Caa1 | G77: 0.0742 | H77: =VLOOKUP(E77,$K$2:$L$91,2,FALSE()) -> 0.0701 | I77: =IF(H77="NA","NA",IF(G77="NA","NA",H77/G77-1)) -> -0.055256065 | K77: South Africa | L77: 0.024
E78: Turkey | F78: =VLOOKUP(E78,'Sovereign Ratings (Moody''s,S&P)'!A78:D234,4,FALSE()) -> Ba3 | G78: 0.038 | H78: =VLOOKUP(E78,$K$2:$L$91,2,FALSE()) -> 0.0299 | I78: =IF(H78="NA","NA",IF(G78="NA","NA",H78/G78-1)) -> -0.21315789 | K78: Spain | L78: 0.0045
E79: United Kingdom | F79: =VLOOKUP(E79,'Sovereign Ratings (Moody''s,S&P)'!A79:D235,4,FALSE()) -> Aa3 | G79: 0.0037 | H79: =VLOOKUP(E79,$K$2:$L$91,2,FALSE()) -> 0.0037 | I79: =IF(H79="NA","NA",IF(G79="NA","NA",H79/G79-1)) -> 0 | K79: Sri Lanka | L79: NA
E80: United States | F80: =VLOOKUP(E80,'Sovereign Ratings (Moody''s,S&P)'!A80:D236,4,FALSE()) -> Aa1 | G80: 0.005 | H80: =VLOOKUP(E80,$K$2:$L$91,2,FALSE()) -> 0.0044 | I80: =IF(H80="NA","NA",IF(G80="NA","NA",H80/G80-1)) -> -0.12 | K80: Sweden | L80: 0.002
E81: Uruguay | F81: =VLOOKUP(E81,'Sovereign Ratings (Moody''s,S&P)'!A81:D237,4,FALSE()) -> Baa1 | G81: 0.0119 | H81: =VLOOKUP(E81,$K$2:$L$91,2,FALSE()) -> 0.0077 | I81: =IF(H81="NA","NA",IF(G81="NA","NA",H81/G81-1)) -> -0.35294118 | K81: Switzerland | L81: 0.0014
E82: Vietnam | F82: =VLOOKUP(E82,'Sovereign Ratings (Moody''s,S&P)'!A82:D238,4,FALSE()) -> Ba2 | G82: 0.0157 | H82: =VLOOKUP(E82,$K$2:$L$91,2,FALSE()) -> 0.0151 | I82: =IF(H82="NA","NA",IF(G82="NA","NA",H82/G82-1)) -> -0.038216561 | K82: Thailand | L82: 0.0066
E83: Average | I83: =AVERAGE(I2:I82) -> -0.14665547 | K83: Tunisia | L83: 0.0701
E84: Median | I84: =MEDIAN(I2:I82) -> -0.13567438 | K84: Turkey | L84: 0.0299
K85: Ukraine | L85: NA
K86: United Kingdom | L86: 0.0037
K87: United States | L87: 0.0044
K88: Uruguay | L88: 0.0077
K89: Venezuela | L89: 0.0929
K90: Vietnam | L90: 0.0151
K91: Zambia | L91: 0.0408

Sheet 10-year CDS Spreads
A1: Country | B1: Moody's rating | C1: CDS Spread (12/31/25) | D1: CDS Spread adj for Switzerland
A2: ='Sovereign Ratings (Moody''s,S&P)'!A2 -> Abu Dhabi | B2: ='Sovereign Ratings (Moody''s,S&P)'!D2 -> Aa2 | C2: =VLOOKUP(A2,$H$24:$J$113,2,FALSE()) -> 0.006 | D2: =IF(C2="NA","NA",IF(C2>$C$139,C2-$C$139,0)) -> 0.0046
A3: ='Sovereign Ratings (Moody''s,S&P)'!A3 -> Albania | B3: ='Sovereign Ratings (Moody''s,S&P)'!D3 -> Ba3 | C3: NA | D3: =IF(C3="NA","NA",IF(C3>$C$139,C3-$C$139,0)) -> NA
A4: ='Sovereign Ratings (Moody''s,S&P)'!A4 -> Andorra (Principality of) | B4: ='Sovereign Ratings (Moody''s,S&P)'!D4 -> Baa1 | C4: NA | D4: =IF(C4="NA","NA",IF(C4>$C$139,C4-$C$139,0)) -> NA
A5: ='Sovereign Ratings (Moody''s,S&P)'!A5 -> Angola | B5: ='Sovereign Ratings (Moody''s,S&P)'!D5 -> B3 | C5: =VLOOKUP(A5,$H$24:$J$113,2,FALSE()) -> 0.0624 | D5: =IF(C5="NA","NA",IF(C5>$C$139,C5-$C$139,0)) -> 0.061
A6: ='Sovereign Ratings (Moody''s,S&P)'!A6 -> Argentina | B6: ='Sovereign Ratings (Moody''s,S&P)'!D6 -> Caa1 | C6: NA | D6: =IF(C6="NA","NA",IF(C6>$C$139,C6-$C$139,0)) -> NA
A7: ='Sovereign Ratings (Moody''s,S&P)'!A7 -> Armenia | B7: ='Sovereign Ratings (Moody''s,S&P)'!D7 -> Ba3 | C7: NA | D7: =IF(C7="NA","NA",IF(C7>$C$139,C7-$C$139,0)) -> NA
A8: ='Sovereign Ratings (Moody''s,S&P)'!A8 -> Aruba | B8: ='Sovereign Ratings (Moody''s,S&P)'!D8 -> Baa3 | C8: NA | D8: =IF(C8="NA","NA",IF(C8>$C$139,C8-$C$139,0)) -> NA
A9: ='Sovereign Ratings (Moody''s,S&P)'!A9 -> Australia | B9: ='Sovereign Ratings (Moody''s,S&P)'!D9 -> Aaa | C9: =VLOOKUP(A9,$H$24:$J$113,2,FALSE()) -> 0.0019 | D9: =IF(C9="NA","NA",IF(C9>$C$139,C9-$C$139,0)) -> 0.0005
A10: ='Sovereign Ratings (Moody''s,S&P)'!A10 -> Austria | B10: ='Sovereign Ratings (Moody''s,S&P)'!D10 -> Aa1 | C10: =VLOOKUP(A10,$H$24:$J$113,2,FALSE()) -> 0.0028 | D10: =IF(C10="NA","NA",IF(C10>$C$139,C10-$C$139,0)) -> 0.0014
A11: ='Sovereign Ratings (Moody''s,S&P)'!A11 -> Azerbaijan | B11: ='Sovereign Ratings (Moody''s,S&P)'!D11 -> Baa3 | C11: NA | D11: =IF(C11="NA","NA",IF(C11>$C$139,C11-$C$139,0)) -> NA
A12: ='Sovereign Ratings (Moody''s,S&P)'!A12 -> Bahamas | B12: ='Sovereign Ratings (Moody''s,S&P)'!D12 -> B1 | C12: NA | D12: =IF(C12="NA","NA",IF(C12>$C$139,C12-$C$139,0)) -> NA
A13: ='Sovereign Ratings (Moody''s,S&P)'!A13 -> Bahrain | B13: ='Sovereign Ratings (Moody''s,S&P)'!D13 -> B2 | C13: =VLOOKUP(A13,$H$24:$J$113,2,FALSE()) -> 0.0247 | D13: =IF(C13="NA","NA",IF(C13>$C$139,C13-$C$139,0)) -> 0.0233
A14: ='Sovereign Ratings (Moody''s,S&P)'!A14 -> Bangladesh | B14: ='Sovereign Ratings (Moody''s,S&P)'!D14 -> B2 | C14: NA | D14: =IF(C14="NA","NA",IF(C14>$C$139,C14-$C$139,0)) -> NA
A15: ='Sovereign Ratings (Moody''s,S&P)'!A15 -> Barbados | B15: ='Sovereign Ratings (Moody''s,S&P)'!D15 -> B2 | C15: NA | D15: =IF(C15="NA","NA",IF(C15>$C$139,C15-$C$139,0)) -> NA
A16: ='Sovereign Ratings (Moody''s,S&P)'!A16 -> Belarus | B16: ='Sovereign Ratings (Moody''s,S&P)'!D16 -> C | C16: NA | D16: =IF(C16="NA","NA",IF(C16>$C$139,C16-$C$139,0)) -> NA
A17: ='Sovereign Ratings (Moody''s,S&P)'!A17 -> Belgium | B17: ='Sovereign Ratings (Moody''s,S&P)'!D17 -> Aa3 | C17: =VLOOKUP(A17,$H$24:$J$113,2,FALSE()) -> 0.004 | D17: =IF(C17="NA","NA",IF(C17>$C$139,C17-$C$139,0)) -> 0.0026
A18: ='Sovereign Ratings (Moody''s,S&P)'!A18 -> Belize | B18: ='Sovereign Ratings (Moody''s,S&P)'!D18 -> Caa1 | C18: NA | D18: =IF(C18="NA","NA",IF(C18>$C$139,C18-$C$139,0)) -> NA
A19: ='Sovereign Ratings (Moody''s,S&P)'!A19 -> Benin | B19: ='Sovereign Ratings (Moody''s,S&P)'!D19 -> B1 | C19: NA | D19: =IF(C19="NA","NA",IF(C19>$C$139,C19-$C$139,0)) -> NA
A20: ='Sovereign Ratings (Moody''s,S&P)'!A20 -> Bermuda | B20: ='Sovereign Ratings (Moody''s,S&P)'!D20 -> A2 | C20: NA | D20: =IF(C20="NA","NA",IF(C20>$C$139,C20-$C$139,0)) -> NA
A21: ='Sovereign Ratings (Moody''s,S&P)'!A21 -> Bolivia | B21: ='Sovereign Ratings (Moody''s,S&P)'!D21 -> Ca | C21: NA | D21: =IF(C21="NA","NA",IF(C21>$C$139,C21-$C$139,0)) -> NA
A22: ='Sovereign Ratings (Moody''s,S&P)'!A22 -> Bosnia and Herzegovina | B22: ='Sovereign Ratings (Moody''s,S&P)'!D22 -> B3 | C22: NA | D22: =IF(C22="NA","NA",IF(C22>$C$139,C22-$C$139,0)) -> NA
A23: ='Sovereign Ratings (Moody''s,S&P)'!A23 -> Botswana | B23: ='Sovereign Ratings (Moody''s,S&P)'!D23 -> Baa1 | C23: NA | D23: =IF(C23="NA","NA",IF(C23>$C$139,C23-$C$139,0)) -> NA | H23: Country | I23: 44560 | J23: CDS Spread net of Switzerland
A24: ='Sovereign Ratings (Moody''s,S&P)'!A24 -> Brazil | B24: ='Sovereign Ratings (Moody''s,S&P)'!D24 -> Ba1 | C24: =VLOOKUP(A24,$H$24:$J$113,2,FALSE()) -> 0.0235 | D24: =IF(C24="NA","NA",IF(C24>$C$139,C24-$C$139,0)) -> 0.0221 | H24: Abu Dhabi | I24: 0.006 | J24: =IF(I24="NA","NA",IF(I24<$I$103,0,I24-$I$103)) -> 0.0046
A25: ='Sovereign Ratings (Moody''s,S&P)'!A25 -> Bulgaria | B25: ='Sovereign Ratings (Moody''s,S&P)'!D25 -> Baa1 | C25: =VLOOKUP(A25,$H$24:$J$113,2,FALSE()) -> 0.0077 | D25: =IF(C25="NA","NA",IF(C25>$C$139,C25-$C$139,0)) -> 0.0063 | H25: Algeria | I25: 0.0134 | J25: =IF(I25="NA","NA",IF(I25<$I$103,0,I25-$I$103)) -> 0.012
A26: ='Sovereign Ratings (Moody''s,S&P)'!A26 -> Burkina Faso | B26: ='Sovereign Ratings (Moody''s,S&P)'!D26 -> Caa1 | C26: NA | D26: =IF(C26="NA","NA",IF(C26>$C$139,C26-$C$139,0)) -> NA | H26: Angola | I26: 0.0624 | J26: =IF(I26="NA","NA",IF(I26<$I$103,0,I26-$I$103)) -> 0.061
A27: ='Sovereign Ratings (Moody''s,S&P)'!A27 -> Cambodia | B27: ='Sovereign Ratings (Moody''s,S&P)'!D27 -> B2 | C27: NA | D27: =IF(C27="NA","NA",IF(C27>$C$139,C27-$C$139,0)) -> NA | H27: Argentina | I27: 0.0694 | J27: =IF(I27="NA","NA",IF(I27<$I$103,0,I27-$I$103)) -> 0.068
A28: ='Sovereign Ratings (Moody''s,S&P)'!A28 -> Cameroon | B28: ='Sovereign Ratings (Moody''s,S&P)'!D28 -> Caa1 | C28: =VLOOKUP(A28,$H$24:$J$113,2,FALSE()) -> 0.0687 | D28: =IF(C28="NA","NA",IF(C28>$C$139,C28-$C$139,0)) -> 0.0673 | H28: Australia | I28: 0.0019 | J28: =IF(I28="NA","NA",IF(I28<$I$103,0,I28-$I$103)) -> 0.0005
A29: ='Sovereign Ratings (Moody''s,S&P)'!A29 -> Canada | B29: ='Sovereign Ratings (Moody''s,S&P)'!D29 -> Aaa | C29: =VLOOKUP(A29,$H$24:$J$113,2,FALSE()) -> 0.0033 | D29: =IF(C29="NA","NA",IF(C29>$C$139,C29-$C$139,0)) -> 0.0019 | H29: Austria | I29: 0.0028 | J29: =IF(I29="NA","NA",IF(I29<$I$103,0,I29-$I$103)) -> 0.0014
A30: ='Sovereign Ratings (Moody''s,S&P)'!A30 -> Cape Verde | B30: ='Sovereign Ratings (Moody''s,S&P)'!D30 -> B2 | C30: NA | D30: =IF(C30="NA","NA",IF(C30>$C$139,C30-$C$139,0)) -> NA | H30: Bahrain | I30: 0.0247 | J30: =IF(I30="NA","NA",IF(I30<$I$103,0,I30-$I$103)) -> 0.0233
A31: ='Sovereign Ratings (Moody''s,S&P)'!A31 -> Cayman Islands | B31: ='Sovereign Ratings (Moody''s,S&P)'!D31 -> Aa3 | C31: NA | D31: =IF(C31="NA","NA",IF(C31>$C$139,C31-$C$139,0)) -> NA | H31: Belgium | I31: 0.004 | J31: =IF(I31="NA","NA",IF(I31<$I$103,0,I31-$I$103)) -> 0.0026
A32: ='Sovereign Ratings (Moody''s,S&P)'!A32 -> Chile | B32: ='Sovereign Ratings (Moody''s,S&P)'!D32 -> A2 | C32: =VLOOKUP(A32,$H$24:$J$113,2,FALSE()) -> 0.0087 | D32: =IF(C32="NA","NA",IF(C32>$C$139,C32-$C$139,0)) -> 0.0073 | H32: Brazil | I32: 0.0235 | J32: =IF(I32="NA","NA",IF(I32<$I$103,0,I32-$I$103)) -> 0.0221
A33: ='Sovereign Ratings (Moody''s,S&P)'!A33 -> China | B33: ='Sovereign Ratings (Moody''s,S&P)'!D33 -> A1 | C33: =VLOOKUP(A33,$H$24:$J$113,2,FALSE()) -> 0.0064 | D33: =IF(C33="NA","NA",IF(C33>$C$139,C33-$C$139,0)) -> 0.005 | H33: Bulgaria | I33: 0.0077 | J33: =IF(I33="NA","NA",IF(I33<$I$103,0,I33-$I$103)) -> 0.0063
A34: ='Sovereign Ratings (Moody''s,S&P)'!A34 -> Colombia | B34: ='Sovereign Ratings (Moody''s,S&P)'!D34 -> Baa3 | C34: =VLOOKUP(A34,$H$24:$J$113,2,FALSE()) -> 0.0334 | D34: =IF(C34="NA","NA",IF(C34>$C$139,C34-$C$139,0)) -> 0.032 | H34: Cameroon | I34: 0.0687 | J34: =IF(I34="NA","NA",IF(I34<$I$103,0,I34-$I$103)) -> 0.0673
A35: ='Sovereign Ratings (Moody''s,S&P)'!A35 -> Congo (Democratic Republic of) | B35: ='Sovereign Ratings (Moody''s,S&P)'!D35 -> B3 | C35: NA | D35: =IF(C35="NA","NA",IF(C35>$C$139,C35-$C$139,0)) -> NA | H35: Canada | I35: 0.0033 | J35: =IF(I35="NA","NA",IF(I35<$I$103,0,I35-$I$103)) -> 0.0019
A36: ='Sovereign Ratings (Moody''s,S&P)'!A36 -> Congo (Republic of) | B36: ='Sovereign Ratings (Moody''s,S&P)'!D36 -> Caa2 | C36: NA | D36: =IF(C36="NA","NA",IF(C36>$C$139,C36-$C$139,0)) -> NA | H36: Chile | I36: 0.0087 | J36: =IF(I36="NA","NA",IF(I36<$I$103,0,I36-$I$103)) -> 0.0073
A37: ='Sovereign Ratings (Moody''s,S&P)'!A37 -> Cook Islands | B37: ='Sovereign Ratings (Moody''s,S&P)'!D37 -> B1 | C37: NA | D37: =IF(C37="NA","NA",IF(C37>$C$139,C37-$C$139,0)) -> NA | H37: China | I37: 0.0064 | J37: =IF(I37="NA","NA",IF(I37<$I$103,0,I37-$I$103)) -> 0.005
A38: ='Sovereign Ratings (Moody''s,S&P)'!A38 -> Costa Rica | B38: ='Sovereign Ratings (Moody''s,S&P)'!D38 -> Ba2 | C38: =VLOOKUP(A38,$H$24:$J$113,2,FALSE()) -> 0.0175 | D38: =IF(C38="NA","NA",IF(C38>$C$139,C38-$C$139,0)) -> 0.0161 | H38: Colombia | I38: 0.0334 | J38: =IF(I38="NA","NA",IF(I38<$I$103,0,I38-$I$103)) -> 0.032
A39: ='Sovereign Ratings (Moody''s,S&P)'!A39 -> Côte d'Ivoire | B39: ='Sovereign Ratings (Moody''s,S&P)'!D39 -> Ba2 | C39: NA | D39: =IF(C39="NA","NA",IF(C39>$C$139,C39-$C$139,0)) -> NA | H39: Costa Rica | I39: 0.0175 | J39: =IF(I39="NA","NA",IF(I39<$I$103,0,I39-$I$103)) -> 0.0161
A40: ='Sovereign Ratings (Moody''s,S&P)'!A40 -> Croatia | B40: ='Sovereign Ratings (Moody''s,S&P)'!D40 -> A3 | C40: =VLOOKUP(A40,$H$24:$J$113,2,FALSE()) -> 0.0102 | D40: =IF(C40="NA","NA",IF(C40>$C$139,C40-$C$139,0)) -> 0.0088 | H40: Croatia | I40: 0.0102 | J40: =IF(I40="NA","NA",IF(I40<$I$103,0,I40-$I$103)) -> 0.0088
A41: ='Sovereign Ratings (Moody''s,S&P)'!A41 -> Cuba | B41: ='Sovereign Ratings (Moody''s,S&P)'!D41 -> Ca | C41: NA | D41: =IF(C41="NA","NA",IF(C41>$C$139,C41-$C$139,0)) -> NA | H41: Cyprus | I41: 0.0075 | J41: =IF(I41="NA","NA",IF(I41<$I$103,0,I41-$I$103)) -> 0.0061
A42: ='Sovereign Ratings (Moody''s,S&P)'!A42 -> Curacao | B42: ='Sovereign Ratings (Moody''s,S&P)'!D42 -> Baa3 | C42: NA | D42: =IF(C42="NA","NA",IF(C42>$C$139,C42-$C$139,0)) -> NA | H42: Czech Republic | I42: 0.0048 | J42: =IF(I42="NA","NA",IF(I42<$I$103,0,I42-$I$103)) -> 0.0034
A43: ='Sovereign Ratings (Moody''s,S&P)'!A43 -> Cyprus | B43: ='Sovereign Ratings (Moody''s,S&P)'!D43 -> A3 | C43: =VLOOKUP(A43,$H$24:$J$113,2,FALSE()) -> 0.0075 | D43: =IF(C43="NA","NA",IF(C43>$C$139,C43-$C$139,0)) -> 0.0061 | H43: Denmark | I43: 0.0018 | J43: =IF(I43="NA","NA",IF(I43<$I$103,0,I43-$I$103)) -> 0.0004
A44: ='Sovereign Ratings (Moody''s,S&P)'!A44 -> Czech Republic | B44: ='Sovereign Ratings (Moody''s,S&P)'!D44 -> Aa3 | C44: =VLOOKUP(A44,$H$24:$J$113,2,FALSE()) -> 0.0048 | D44: =IF(C44="NA","NA",IF(C44>$C$139,C44-$C$139,0)) -> 0.0034 | H44: Dubai | I44: 0.0082 | J44: =IF(I44="NA","NA",IF(I44<$I$103,0,I44-$I$103)) -> 0.0068
A45: ='Sovereign Ratings (Moody''s,S&P)'!A45 -> Denmark | B45: ='Sovereign Ratings (Moody''s,S&P)'!D45 -> Aaa | C45: =VLOOKUP(A45,$H$24:$J$113,2,FALSE()) -> 0.0018 | D45: =IF(C45="NA","NA",IF(C45>$C$139,C45-$C$139,0)) -> 0.0004 | H45: Ecuador | I45: 0.0567 | J45: =IF(I45="NA","NA",IF(I45<$I$103,0,I45-$I$103)) -> 0.0553
A46: ='Sovereign Ratings (Moody''s,S&P)'!A46 -> Dominican Republic | B46: ='Sovereign Ratings (Moody''s,S&P)'!D46 -> Ba2 | C46: NA | D46: =IF(C46="NA","NA",IF(C46>$C$139,C46-$C$139,0)) -> NA | H46: Egypt | I46: 0.0355 | J46: =IF(I46="NA","NA",IF(I46<$I$103,0,I46-$I$103)) -> 0.0341
A47: ='Sovereign Ratings (Moody''s,S&P)'!A47 -> Ecuador | B47: ='Sovereign Ratings (Moody''s,S&P)'!D47 -> Caa3 | C47: =VLOOKUP(A47,$H$24:$J$113,2,FALSE()) -> 0.0567 | D47: =IF(C47="NA","NA",IF(C47>$C$139,C47-$C$139,0)) -> 0.0553 | H47: El Salvador | I47: 0.034 | J47: =IF(I47="NA","NA",IF(I47<$I$103,0,I47-$I$103)) -> 0.0326
A48: ='Sovereign Ratings (Moody''s,S&P)'!A48 -> Egypt | B48: ='Sovereign Ratings (Moody''s,S&P)'!D48 -> Caa1 | C48: =VLOOKUP(A48,$H$24:$J$113,2,FALSE()) -> 0.0355 | D48: =IF(C48="NA","NA",IF(C48>$C$139,C48-$C$139,0)) -> 0.0341 | H48: Estonia | I48: 0.01 | J48: =IF(I48="NA","NA",IF(I48<$I$103,0,I48-$I$103)) -> 0.0086
A49: ='Sovereign Ratings (Moody''s,S&P)'!A49 -> El Salvador | B49: ='Sovereign Ratings (Moody''s,S&P)'!D49 -> B3 | C49: =VLOOKUP(A49,$H$24:$J$113,2,FALSE()) -> 0.034 | D49: =IF(C49="NA","NA",IF(C49>$C$139,C49-$C$139,0)) -> 0.0326 | H49: Ethiopia | I49: NA | J49: =IF(I49="NA","NA",IF(I49<$I$103,0,I49-$I$103)) -> NA
A50: ='Sovereign Ratings (Moody''s,S&P)'!A50 -> Estonia | B50: ='Sovereign Ratings (Moody''s,S&P)'!D50 -> A1 | C50: =VLOOKUP(A50,$H$24:$J$113,2,FALSE()) -> 0.01 | D50: =IF(C50="NA","NA",IF(C50>$C$139,C50-$C$139,0)) -> 0.0086 | H50: Finland | I50: 0.0026 | J50: =IF(I50="NA","NA",IF(I50<$I$103,0,I50-$I$103)) -> 0.0012
A51: ='Sovereign Ratings (Moody''s,S&P)'!A51 -> Ethiopia | B51: ='Sovereign Ratings (Moody''s,S&P)'!D51 -> Caa2 | C51: =VLOOKUP(A51,$H$24:$J$113,2,FALSE()) -> NA | D51: =IF(C51="NA","NA",IF(C51>$C$139,C51-$C$139,0)) -> NA | H51: France | I51: 0.0064 | J51: =IF(I51="NA","NA",IF(I51<$I$103,0,I51-$I$103)) -> 0.005
A52: ='Sovereign Ratings (Moody''s,S&P)'!A52 -> Fiji | B52: ='Sovereign Ratings (Moody''s,S&P)'!D52 -> B1 | C52: NA | D52: =IF(C52="NA","NA",IF(C52>$C$139,C52-$C$139,0)) -> NA | H52: Gabon | I52: 0.0854 | J52: =IF(I52="NA","NA",IF(I52<$I$103,0,I52-$I$103)) -> 0.084
A53: ='Sovereign Ratings (Moody''s,S&P)'!A53 -> Finland | B53: ='Sovereign Ratings (Moody''s,S&P)'!D53 -> Aa1 | C53: =VLOOKUP(A53,$H$24:$J$113,2,FALSE()) -> 0.0026 | D53: =IF(C53="NA","NA",IF(C53>$C$139,C53-$C$139,0)) -> 0.0012 | H53: Germany | I53: 0.0021 | J53: =IF(I53="NA","NA",IF(I53<$I$103,0,I53-$I$103)) -> 0.0007
A54: ='Sovereign Ratings (Moody''s,S&P)'!A54 -> France | B54: ='Sovereign Ratings (Moody''s,S&P)'!D54 -> Aa3 | C54: =VLOOKUP(A54,$H$24:$J$113,2,FALSE()) -> 0.0064 | D54: =IF(C54="NA","NA",IF(C54>$C$139,C54-$C$139,0)) -> 0.005 | H54: Greece | I54: 0.0075 | J54: =IF(I54="NA","NA",IF(I54<$I$103,0,I54-$I$103)) -> 0.0061
A55: ='Sovereign Ratings (Moody''s,S&P)'!A55 -> Gabon | B55: ='Sovereign Ratings (Moody''s,S&P)'!D55 -> Caa2 | C55: NA | D55: =IF(C55="NA","NA",IF(C55>$C$139,C55-$C$139,0)) -> NA | H55: Guatemala | I55: 0.0171 | J55: =IF(I55="NA","NA",IF(I55<$I$103,0,I55-$I$103)) -> 0.0157
A56: ='Sovereign Ratings (Moody''s,S&P)'!A56 -> Georgia | B56: ='Sovereign Ratings (Moody''s,S&P)'!D56 -> Ba2 | C56: NA | D56: =IF(C56="NA","NA",IF(C56>$C$139,C56-$C$139,0)) -> NA | H56: Hong Kong | I56: 0.0044 | J56: =IF(I56="NA","NA",IF(I56<$I$103,0,I56-$I$103)) -> 0.003
A57: ='Sovereign Ratings (Moody''s,S&P)'!A57 -> Germany | B57: ='Sovereign Ratings (Moody''s,S&P)'!D57 -> Aaa | C57: =VLOOKUP(A57,$H$24:$J$113,2,FALSE()) -> 0.0021 | D57: =IF(C57="NA","NA",IF(C57>$C$139,C57-$C$139,0)) -> 0.0007 | H57: Hungary | I57: 0.016 | J57: =IF(I57="NA","NA",IF(I57<$I$103,0,I57-$I$103)) -> 0.0146
A58: ='Sovereign Ratings (Moody''s,S&P)'!A58 -> Ghana | B58: ='Sovereign Ratings (Moody''s,S&P)'!D58 -> Caa1 | C58: NA | D58: =IF(C58="NA","NA",IF(C58>$C$139,C58-$C$139,0)) -> NA | H58: Iceland | I58: 0.0045 | J58: =IF(I58="NA","NA",IF(I58<$I$103,0,I58-$I$103)) -> 0.0031
A59: ='Sovereign Ratings (Moody''s,S&P)'!A59 -> Greece | B59: ='Sovereign Ratings (Moody''s,S&P)'!D59 -> Baa3 | C59: =VLOOKUP(A59,$H$24:$J$113,2,FALSE()) -> 0.0075 | D59: =IF(C59="NA","NA",IF(C59>$C$139,C59-$C$139,0)) -> 0.0061 | H59: India | I59: 0.008 | J59: =IF(I59="NA","NA",IF(I59<$I$103,0,I59-$I$103)) -> 0.0066
A60: ='Sovereign Ratings (Moody''s,S&P)'!A60 -> Guatemala | B60: ='Sovereign Ratings (Moody''s,S&P)'!D60 -> Ba1 | C60: NA | D60: =IF(C60="NA","NA",IF(C60>$C$139,C60-$C$139,0)) -> NA | H60: Indonesia | I60: 0.0119 | J60: =IF(I60="NA","NA",IF(I60<$I$103,0,I60-$I$103)) -> 0.0105
A61: ='Sovereign Ratings (Moody''s,S&P)'!A61 -> Guernsey (States of) | B61: ='Sovereign Ratings (Moody''s,S&P)'!D61 -> A1 | C61: NA | D61: =IF(C61="NA","NA",IF(C61>$C$139,C61-$C$139,0)) -> NA | H61: Iraq | I61: 0.0289 | J61: =IF(I61="NA","NA",IF(I61<$I$103,0,I61-$I$103)) -> 0.0275
A62: ='Sovereign Ratings (Moody''s,S&P)'!A62 -> Honduras | B62: ='Sovereign Ratings (Moody''s,S&P)'!D62 -> B1 | C62: NA | D62: =IF(C62="NA","NA",IF(C62>$C$139,C62-$C$139,0)) -> NA | H62: Ireland | I62: 0.0034 | J62: =IF(I62="NA","NA",IF(I62<$I$103,0,I62-$I$103)) -> 0.002
A63: ='Sovereign Ratings (Moody''s,S&P)'!A63 -> Hong Kong | B63: ='Sovereign Ratings (Moody''s,S&P)'!D63 -> Aa3 | C63: =VLOOKUP(A63,$H$24:$J$113,2,FALSE()) -> 0.0044 | D63: =IF(C63="NA","NA",IF(C63>$C$139,C63-$C$139,0)) -> 0.003 | H63: Israel | I63: 0.0113 | J63: =IF(I63="NA","NA",IF(I63<$I$103,0,I63-$I$103)) -> 0.0099
A64: ='Sovereign Ratings (Moody''s,S&P)'!A64 -> Hungary | B64: ='Sovereign Ratings (Moody''s,S&P)'!D64 -> Baa2 | C64: =VLOOKUP(A64,$H$24:$J$113,2,FALSE()) -> 0.016 | D64: =IF(C64="NA","NA",IF(C64>$C$139,C64-$C$139,0)) -> 0.0146 | H64: Italy | I64: 0.0061 | J64: =IF(I64="NA","NA",IF(I64<$I$103,0,I64-$I$103)) -> 0.0047
A65: ='Sovereign Ratings (Moody''s,S&P)'!A65 -> Iceland | B65: ='Sovereign Ratings (Moody''s,S&P)'!D65 -> A1 | C65: =VLOOKUP(A65,$H$24:$J$113,2,FALSE()) -> 0.0045 | D65: =IF(C65="NA","NA",IF(C65>$C$139,C65-$C$139,0)) -> 0.0031 | H65: Japan | I65: 0.0044 | J65: =IF(I65="NA","NA",IF(I65<$I$103,0,I65-$I$103)) -> 0.003
A66: ='Sovereign Ratings (Moody''s,S&P)'!A66 -> India | B66: ='Sovereign Ratings (Moody''s,S&P)'!D66 -> Baa3 | C66: =VLOOKUP(A66,$H$24:$J$113,2,FALSE()) -> 0.008 | D66: =IF(C66="NA","NA",IF(C66>$C$139,C66-$C$139,0)) -> 0.0066 | H66: Kazakhstan | I66: 0.0131 | J66: =IF(I66="NA","NA",IF(I66<$I$103,0,I66-$I$103)) -> 0.0117
A67: ='Sovereign Ratings (Moody''s,S&P)'!A67 -> Indonesia | B67: ='Sovereign Ratings (Moody''s,S&P)'!D67 -> Baa2 | C67: =VLOOKUP(A67,$H$24:$J$113,2,FALSE()) -> 0.0119 | D67: =IF(C67="NA","NA",IF(C67>$C$139,C67-$C$139,0)) -> 0.0105 | H67: Kenya | I67: 0.0451 | J67: =IF(I67="NA","NA",IF(I67<$I$103,0,I67-$I$103)) -> 0.0437
A68: ='Sovereign Ratings (Moody''s,S&P)'!A68 -> Iraq | B68: ='Sovereign Ratings (Moody''s,S&P)'!D68 -> Caa1 | C68: =VLOOKUP(A68,$H$24:$J$113,2,FALSE()) -> 0.0289 | D68: =IF(C68="NA","NA",IF(C68>$C$139,C68-$C$139,0)) -> 0.0275 | H68: Korea | I68: 0.0034 | J68: =IF(I68="NA","NA",IF(I68<$I$103,0,I68-$I$103)) -> 0.002
A69: ='Sovereign Ratings (Moody''s,S&P)'!A69 -> Ireland | B69: ='Sovereign Ratings (Moody''s,S&P)'!D69 -> Aa3 | C69: =VLOOKUP(A69,$H$24:$J$113,2,FALSE()) -> 0.0034 | D69: =IF(C69="NA","NA",IF(C69>$C$139,C69-$C$139,0)) -> 0.002 | H69: Kuwait | I69: 0.0087 | J69: =IF(I69="NA","NA",IF(I69<$I$103,0,I69-$I$103)) -> 0.0073
A70: ='Sovereign Ratings (Moody''s,S&P)'!A70 -> Isle of Man | B70: ='Sovereign Ratings (Moody''s,S&P)'!D70 -> Aa3 | C70: NA | D70: =IF(C70="NA","NA",IF(C70>$C$139,C70-$C$139,0)) -> NA | H70: Latvia | I70: 0.0082 | J70: =IF(I70="NA","NA",IF(I70<$I$103,0,I70-$I$103)) -> 0.0068
A71: ='Sovereign Ratings (Moody''s,S&P)'!A71 -> Israel | B71: ='Sovereign Ratings (Moody''s,S&P)'!D71 -> Baa1 | C71: =VLOOKUP(A71,$H$24:$J$113,2,FALSE()) -> 0.0113 | D71: =IF(C71="NA","NA",IF(C71>$C$139,C71-$C$139,0)) -> 0.0099 | H71: Lebanon | I71: NA | J71: =IF(I71="NA","NA",IF(I71<$I$103,0,I71-$I$103)) -> NA
A72: ='Sovereign Ratings (Moody''s,S&P)'!A72 -> Italy | B72: ='Sovereign Ratings (Moody''s,S&P)'!D72 -> Baa2 | C72: =VLOOKUP(A72,$H$24:$J$113,2,FALSE()) -> 0.0061 | D72: =IF(C72="NA","NA",IF(C72>$C$139,C72-$C$139,0)) -> 0.0047 | H72: Lithuania | I72: 0.0082 | J72: =IF(I72="NA","NA",IF(I72<$I$103,0,I72-$I$103)) -> 0.0068
A73: ='Sovereign Ratings (Moody''s,S&P)'!A73 -> Jamaica | B73: ='Sovereign Ratings (Moody''s,S&P)'!D73 -> Ba3 | C73: NA | D73: =IF(C73="NA","NA",IF(C73>$C$139,C73-$C$139,0)) -> NA | H73: Malaysia | I73: 0.0067 | J73: =IF(I73="NA","NA",IF(I73<$I$103,0,I73-$I$103)) -> 0.0053
A74: ='Sovereign Ratings (Moody''s,S&P)'!A74 -> Japan | B74: ='Sovereign Ratings (Moody''s,S&P)'!D74 -> A1 | C74: =VLOOKUP(A74,$H$24:$J$113,2,FALSE()) -> 0.0044 | D74: =IF(C74="NA","NA",IF(C74>$C$139,C74-$C$139,0)) -> 0.003 | H74: Mexico | I74: 0.0166 | J74: =IF(I74="NA","NA",IF(I74<$I$103,0,I74-$I$103)) -> 0.0152
A75: ='Sovereign Ratings (Moody''s,S&P)'!A75 -> Jersey (States of) | B75: ='Sovereign Ratings (Moody''s,S&P)'!D75 -> Aa3 | C75: NA | D75: =IF(C75="NA","NA",IF(C75>$C$139,C75-$C$139,0)) -> NA | H75: Mongolia | I75: 0.0326 | J75: =IF(I75="NA","NA",IF(I75<$I$103,0,I75-$I$103)) -> 0.0312
A76: ='Sovereign Ratings (Moody''s,S&P)'!A76 -> Jordan | B76: ='Sovereign Ratings (Moody''s,S&P)'!D76 -> Ba3 | C76: NA | D76: =IF(C76="NA","NA",IF(C76>$C$139,C76-$C$139,0)) -> NA | H76: Morocco | I76: 0.013 | J76: =IF(I76="NA","NA",IF(I76<$I$103,0,I76-$I$103)) -> 0.0116
A77: ='Sovereign Ratings (Moody''s,S&P)'!A77 -> Kazakhstan | B77: ='Sovereign Ratings (Moody''s,S&P)'!D77 -> Baa1 | C77: =VLOOKUP(A77,$H$24:$J$113,2,FALSE()) -> 0.0131 | D77: =IF(C77="NA","NA",IF(C77>$C$139,C77-$C$139,0)) -> 0.0117 | H77: Namibia | I77: 0.0341 | J77: =IF(I77="NA","NA",IF(I77<$I$103,0,I77-$I$103)) -> 0.0327
A78: ='Sovereign Ratings (Moody''s,S&P)'!A78 -> Kenya | B78: ='Sovereign Ratings (Moody''s,S&P)'!D78 -> B3 | C78: =VLOOKUP(A78,$H$24:$J$113,2,FALSE()) -> 0.0451 | D78: =IF(C78="NA","NA",IF(C78>$C$139,C78-$C$139,0)) -> 0.0437 | H78: Netherlands | I78: 0.002 | J78: =IF(I78="NA","NA",IF(I78<$I$103,0,I78-$I$103)) -> 0.0006
A79: ='Sovereign Ratings (Moody''s,S&P)'!A79 -> Korea | B79: ='Sovereign Ratings (Moody''s,S&P)'!D79 -> Aa2 | C79: =VLOOKUP(A79,$H$24:$J$113,2,FALSE()) -> 0.0034 | D79: =IF(C79="NA","NA",IF(C79>$C$139,C79-$C$139,0)) -> 0.002 | H79: New Zealand | I79: 0.0023 | J79: =IF(I79="NA","NA",IF(I79<$I$103,0,I79-$I$103)) -> 0.0009
A80: ='Sovereign Ratings (Moody''s,S&P)'!A80 -> Kuwait | B80: ='Sovereign Ratings (Moody''s,S&P)'!D80 -> A1 | C80: =VLOOKUP(A80,$H$24:$J$113,2,FALSE()) -> 0.0087 | D80: =IF(C80="NA","NA",IF(C80>$C$139,C80-$C$139,0)) -> 0.0073 | H80: Nicaragua | I80: 0.0529 | J80: =IF(I80="NA","NA",IF(I80<$I$103,0,I80-$I$103)) -> 0.0515
A81: ='Sovereign Ratings (Moody''s,S&P)'!A81 -> Kyrgyzstan | B81: ='Sovereign Ratings (Moody''s,S&P)'!D81 -> B3 | C81: NA | D81: =IF(C81="NA","NA",IF(C81>$C$139,C81-$C$139,0)) -> NA | H81: Nigeria | I81: 0.0391 | J81: =IF(I81="NA","NA",IF(I81<$I$103,0,I81-$I$103)) -> 0.0377
A82: ='Sovereign Ratings (Moody''s,S&P)'!A82 -> Laos | B82: ='Sovereign Ratings (Moody''s,S&P)'!D82 -> Caa2 | C82: NA | D82: =IF(C82="NA","NA",IF(C82>$C$139,C82-$C$139,0)) -> NA | H82: Norway | I82: 0.0018 | J82: =IF(I82="NA","NA",IF(I82<$I$103,0,I82-$I$103)) -> 0.0004
A83: ='Sovereign Ratings (Moody''s,S&P)'!A83 -> Latvia | B83: ='Sovereign Ratings (Moody''s,S&P)'!D83 -> A3 | C83: =VLOOKUP(A83,$H$24:$J$113,2,FALSE()) -> 0.0082 | D83: =IF(C83="NA","NA",IF(C83>$C$139,C83-$C$139,0)) -> 0.0068 | H83: Oman | I83: 0.013 | J83: =IF(I83="NA","NA",IF(I83<$I$103,0,I83-$I$103)) -> 0.0116
A84: ='Sovereign Ratings (Moody''s,S&P)'!A84 -> Lebanon | B84: ='Sovereign Ratings (Moody''s,S&P)'!D84 -> C | C84: =VLOOKUP(A84,$H$24:$J$113,2,FALSE()) -> NA | D84: =IF(C84="NA","NA",IF(C84>$C$139,C84-$C$139,0)) -> NA | H84: Pakistan | I84: 0.0523 | J84: =IF(I84="NA","NA",IF(I84<$I$103,0,I84-$I$103)) -> 0.0509
A85: ='Sovereign Ratings (Moody''s,S&P)'!A85 -> Liechtenstein | B85: ='Sovereign Ratings (Moody''s,S&P)'!D85 -> Aaa | C85: NA | D85: =IF(C85="NA","NA",IF(C85>$C$139,C85-$C$139,0)) -> NA | H85: Panama | I85: 0.0222 | J85: =IF(I85="NA","NA",IF(I85<$I$103,0,I85-$I$103)) -> 0.0208
A86: ='Sovereign Ratings (Moody''s,S&P)'!A86 -> Lithuania | B86: ='Sovereign Ratings (Moody''s,S&P)'!D86 -> A2 | C86: =VLOOKUP(A86,$H$24:$J$113,2,FALSE()) -> 0.0082 | D86: =IF(C86="NA","NA",IF(C86>$C$139,C86-$C$139,0)) -> 0.0068 | H86: Peru | I86: 0.0126 | J86: =IF(I86="NA","NA",IF(I86<$I$103,0,I86-$I$103)) -> 0.0112
A87: ='Sovereign Ratings (Moody''s,S&P)'!A87 -> Luxembourg | B87: ='Sovereign Ratings (Moody''s,S&P)'!D87 -> Aaa | C87: NA | D87: =IF(C87="NA","NA",IF(C87>$C$139,C87-$C$139,0)) -> NA | H87: Philippines | I87: 0.0102 | J87: =IF(I87="NA","NA",IF(I87<$I$103,0,I87-$I$103)) -> 0.0088
A88: ='Sovereign Ratings (Moody''s,S&P)'!A88 -> Macao | B88: ='Sovereign Ratings (Moody''s,S&P)'!D88 -> Aa3 | C88: NA | D88: =IF(C88="NA","NA",IF(C88>$C$139,C88-$C$139,0)) -> NA | H88: Poland | I88: 0.01 | J88: =IF(I88="NA","NA",IF(I88<$I$103,0,I88-$I$103)) -> 0.0086
A89: ='Sovereign Ratings (Moody''s,S&P)'!A89 -> Macedonia | B89: ='Sovereign Ratings (Moody''s,S&P)'!D89 -> Ba3 | C89: NA | D89: =IF(C89="NA","NA",IF(C89>$C$139,C89-$C$139,0)) -> NA | H89: Portugal | I89: 0.0045 | J89: =IF(I89="NA","NA",IF(I89<$I$103,0,I89-$I$103)) -> 0.0031
A90: ='Sovereign Ratings (Moody''s,S&P)'!A90 -> Malaysia | B90: ='Sovereign Ratings (Moody''s,S&P)'!D90 -> A3 | C90: =VLOOKUP(A90,$H$24:$J$113,2,FALSE()) -> 0.0067 | D90: =IF(C90="NA","NA",IF(C90>$C$139,C90-$C$139,0)) -> 0.0053 | H90: Qatar | I90: 0.0061 | J90: =IF(I90="NA","NA",IF(I90<$I$103,0,I90-$I$103)) -> 0.0047
A91: ='Sovereign Ratings (Moody''s,S&P)'!A91 -> Maldives | B91: ='Sovereign Ratings (Moody''s,S&P)'!D91 -> Caa2 | C91: NA | D91: =IF(C91="NA","NA",IF(C91>$C$139,C91-$C$139,0)) -> NA | H91: Romania | I91: 0.0211 | J91: =IF(#REF!="NA","NA",IF(#REF!<$I$103,0,#REF!-$I$103)) -> #REF!
A92: ='Sovereign Ratings (Moody''s,S&P)'!A92 -> Mali | B92: ='Sovereign Ratings (Moody''s,S&P)'!D92 -> Caa2 | C92: NA | D92: =IF(C92="NA","NA",IF(C92>$C$139,C92-$C$139,0)) -> NA | H92: Russia | I92: NA | J92: =IF(I91="NA","NA",IF(I91<$I$103,0,I91-$I$103)) -> 0.0197
A93: ='Sovereign Ratings (Moody''s,S&P)'!A93 -> Malta | B93: ='Sovereign Ratings (Moody''s,S&P)'!D93 -> A2 | C93: NA | D93: =IF(C93="NA","NA",IF(C93>$C$139,C93-$C$139,0)) -> NA | H93: Rwanda | I93: 0.0403 | J93: =IF(I93="NA","NA",IF(I93<$I$103,0,I93-$I$103)) -> 0.0389
A94: ='Sovereign Ratings (Moody''s,S&P)'!A94 -> Mauritius | B94: ='Sovereign Ratings (Moody''s,S&P)'!D94 -> Baa3 | C94: NA | D94: =IF(C94="NA","NA",IF(C94>$C$139,C94-$C$139,0)) -> NA | H94: Saudi Arabia | I94: 0.0112 | J94: =IF(I94="NA","NA",IF(I94<$I$103,0,I94-$I$103)) -> 0.0098
A95: ='Sovereign Ratings (Moody''s,S&P)'!A95 -> Mexico | B95: ='Sovereign Ratings (Moody''s,S&P)'!D95 -> Baa2 | C95: =VLOOKUP(A95,$H$24:$J$113,2,FALSE()) -> 0.0166 | D95: =IF(C95="NA","NA",IF(C95>$C$139,C95-$C$139,0)) -> 0.0152 | H95: Senegal | I95: 0.0993 | J95: =IF(I95="NA","NA",IF(I95<$I$103,0,I95-$I$103)) -> 0.0979
A96: ='Sovereign Ratings (Moody''s,S&P)'!A96 -> Moldova | B96: ='Sovereign Ratings (Moody''s,S&P)'!D96 -> B3 | C96: NA | D96: =IF(C96="NA","NA",IF(C96>$C$139,C96-$C$139,0)) -> NA | H96: Serbia | I96: 0.0196 | J96: =IF(I96="NA","NA",IF(I96<$I$103,0,I96-$I$103)) -> 0.0182
A97: ='Sovereign Ratings (Moody''s,S&P)'!A97 -> Mongolia | B97: ='Sovereign Ratings (Moody''s,S&P)'!D97 -> B1 | C97: NA | D97: =IF(C97="NA","NA",IF(C97>$C$139,C97-$C$139,0)) -> NA | H97: Slovakia | I97: 0.0057 | J97: =IF(I97="NA","NA",IF(I97<$I$103,0,I97-$I$103)) -> 0.0043
A98: ='Sovereign Ratings (Moody''s,S&P)'!A98 -> Montenegro | B98: ='Sovereign Ratings (Moody''s,S&P)'!D98 -> B1 | C98: NA | D98: =IF(C98="NA","NA",IF(C98>$C$139,C98-$C$139,0)) -> NA | H98: Slovenia | I98: 0.0067 | J98: =IF(I98="NA","NA",IF(I98<$I$103,0,I98-$I$103)) -> 0.0053
A99: ='Sovereign Ratings (Moody''s,S&P)'!A99 -> Montserrat | B99: ='Sovereign Ratings (Moody''s,S&P)'!D99 -> Baa3 | C99: NA | D99: =IF(C99="NA","NA",IF(C99>$C$139,C99-$C$139,0)) -> NA | H99: South Africa | I99: 0.024 | J99: =IF(I99="NA","NA",IF(I99<$I$103,0,I99-$I$103)) -> 0.0226
A100: ='Sovereign Ratings (Moody''s,S&P)'!A100 -> Morocco | B100: ='Sovereign Ratings (Moody''s,S&P)'!D100 -> Ba1 | C100: =VLOOKUP(A100,$H$24:$J$113,2,FALSE()) -> 0.013 | D100: =IF(C100="NA","NA",IF(C100>$C$139,C100-$C$139,0)) -> 0.0116 | H100: Spain | I100: 0.0045 | J100: =IF(I100="NA","NA",IF(I100<$I$103,0,I100-$I$103)) -> 0.0031
...

Sheet Equity vs Govt Bond vol Risky
A1: Date: | B1: 43861 | D1: Just Risky markets
A3: Country | B3: sEquity | C3: sBond | D3: sEquity/ sBond | E3: s (CDS) | F3: CDS | G3: CV(CDS) | H3: sEquity/ sCDS
A4: Argentina | B4: 0.5652 | C4: 0.48055 | D4: =IF(C4="NA","NA",IF(B4="NA","NA",B4/C4)) -> 1.1761523 | E4: NA | F4: NA | G4: =IF(F4="NA","NA",E4/F4) -> NA | H4: =IF(G4="NA","NA",IF(B4="NA","NA",B4/G4)) -> NA
A5: Bahrain | B5: 0.0511 | C5: NA | D5: =IF(C5="NA","NA",IF(B5="NA","NA",B5/C5)) -> NA | E5: 0.0029 | F5: 0.0269 | G5: =IF(F5="NA","NA",E5/F5) -> 0.10780669 | H5: =IF(G5="NA","NA",IF(B5="NA","NA",B5/G5)) -> 0.47399655
A6: Brazil | B6: 0.1621 | C6: 0.1332 | D6: =IF(C6="NA","NA",IF(B6="NA","NA",B6/C6)) -> 1.216967 | E6: 0.0021 | F6: 0.0231 | G6: =IF(F6="NA","NA",E6/F6) -> 0.090909091 | H6: =IF(G6="NA","NA",IF(B6="NA","NA",B6/G6)) -> 1.7831
A7: Colombia | B7: 0.1744 | C7: NA | D7: =IF(C7="NA","NA",IF(B7="NA","NA",B7/C7)) -> NA | E7: 0.0023 | F7: 0.0275 | G7: =IF(F7="NA","NA",E7/F7) -> 0.083636364 | H7: =IF(G7="NA","NA",IF(B7="NA","NA",B7/G7)) -> 2.0852174
A8: Costa Rica | B8: 0.0714 | C8: 0.0492 | D8: =IF(C8="NA","NA",IF(B8="NA","NA",B8/C8)) -> 1.4512195 | E8: 0.0045 | F8: 0.0242 | G8: =IF(F8="NA","NA",E8/F8) -> 0.18595041 | H8: =IF(G8="NA","NA",IF(B8="NA","NA",B8/G8)) -> 0.38397333
A9: Egypt | B9: 0.2733 | C9: NA | D9: =IF(C9="NA","NA",IF(B9="NA","NA",B9/C9)) -> NA | E9: 0.0065 | F9: 0.0633 | G9: =IF(F9="NA","NA",E9/F9) -> 0.10268562 | H9: =IF(G9="NA","NA",IF(B9="NA","NA",B9/G9)) -> 2.6615215
A10: Hungary | B10: 0.1441 | C10: 0.1226 | D10: =IF(C10="NA","NA",IF(B10="NA","NA",B10/C10)) -> 1.175367 | E10: 0.0027 | F10: 0.0175 | G10: =IF(F10="NA","NA",E10/F10) -> 0.15428571 | H10: =IF(G10="NA","NA",IF(B10="NA","NA",B10/G10)) -> 0.93398148
A11: Jamaica | B11: 0.1124 | C11: 0.0908 | D11: =IF(C11="NA","NA",IF(B11="NA","NA",B11/C11)) -> 1.2378855 | E11: 0.0038 | F11: 0.0156 | G11: =IF(F11="NA","NA",E11/F11) -> 0.24358974 | H11: =IF(G11="NA","NA",IF(B11="NA","NA",B11/G11)) -> 0.46143158
A12: Kenya | B12: 0.1767 | C12: NA | D12: =IF(C12="NA","NA",IF(B12="NA","NA",B12/C12)) -> NA | E12: 0.0072 | F12: 0.0457 | G12: =IF(F12="NA","NA",E12/F12) -> 0.15754923 | H12: =IF(G12="NA","NA",IF(B12="NA","NA",B12/G12)) -> 1.1215542
A13: Lebanon | B13: 0.31 | C13: 0.1646 | D13: =IF(C13="NA","NA",IF(B13="NA","NA",B13/C13)) -> 1.8833536 | E13: NA | F13: NA | G13: =IF(F13="NA","NA",E13/F13) -> NA | H13: =IF(G13="NA","NA",IF(B13="NA","NA",B13/G13)) -> NA
A14: Mexico | B14: 0.1414 | C14: 0.0801 | D14: =IF(C14="NA","NA",IF(B14="NA","NA",B14/C14)) -> 1.7652934 | E14: 0.0025 | F14: 0.0158 | G14: =IF(F14="NA","NA",E14/F14) -> 0.15822785 | H14: =IF(G14="NA","NA",IF(B14="NA","NA",B14/G14)) -> 0.893648
A15: Mongolia | B15: 0.1545 | C15: NA | D15: =IF(C15="NA","NA",IF(B15="NA","NA",B15/C15)) -> NA | E15: 0.005 | F15: 0.0365 | G15: =IF(F15="NA","NA",E15/F15) -> 0.1369863 | H15: =IF(G15="NA","NA",IF(B15="NA","NA",B15/G15)) -> 1.12785
A16: Morocco | B16: 0.099 | C16: NA | D16: =IF(C16="NA","NA",IF(B16="NA","NA",B16/C16)) -> NA | E16: 0.0045 | F16: 0.0153 | G16: =IF(F16="NA","NA",E16/F16) -> 0.29411765 | H16: =IF(G16="NA","NA",IF(B16="NA","NA",B16/G16)) -> 0.3366
A17: Nigeria | B17: 0.1674 | C17: NA | D17: =IF(C17="NA","NA",IF(B17="NA","NA",B17/C17)) -> NA | E17: 0.0049 | F17: 0.0694 | G17: =IF(F17="NA","NA",E17/F17) -> 0.070605187 | H17: =IF(G17="NA","NA",IF(B17="NA","NA",B17/G17)) -> 2.3709306
A18: Oman | B18: 0.0733 | C18: NA | D18: =IF(C18="NA","NA",IF(B18="NA","NA",B18/C18)) -> NA | E18: 0.0041 | F18: 0.0168 | G18: =IF(F18="NA","NA",E18/F18) -> 0.24404762 | H18: =IF(G18="NA","NA",IF(B18="NA","NA",B18/G18)) -> 0.30035122
A19: Panama | B19: 0.0794 | C19: 0.089 | D19: =IF(C19="NA","NA",IF(B19="NA","NA",B19/C19)) -> 0.89213483 | E19: 0.0026 | F19: 0.0268 | G19: =IF(F19="NA","NA",E19/F19) -> 0.097014925 | H19: =IF(G19="NA","NA",IF(B19="NA","NA",B19/G19)) -> 0.81843077
A20: Romania | B20: 0.1109 | C20: 0.0803 | D20: =IF(C20="NA","NA",IF(B20="NA","NA",B20/C20)) -> 1.381071 | E20: NA | F20: NA | G20: =IF(F20="NA","NA",E20/F20) -> NA | H20: =IF(G20="NA","NA",IF(B20="NA","NA",B20/G20)) -> NA
A21: Serbia | B21: 0.0712 | C21: NA | D21: =IF(C21="NA","NA",IF(B21="NA","NA",B21/C21)) -> NA | E21: 0.0032 | F21: 0.0263 | G21: =IF(F21="NA","NA",E21/F21) -> 0.121673 | H21: =IF(G21="NA","NA",IF(B21="NA","NA",B21/G21)) -> 0.585175
A22: Singapore | B22: 0.1162 | C22: 0.0599 | D22: =IF(C22="NA","NA",IF(B22="NA","NA",B22/C22)) -> 1.9398998 | E22: NA | F22: NA | G22: =IF(F22="NA","NA",E22/F22) -> NA | H22: =IF(G22="NA","NA",IF(B22="NA","NA",B22/G22)) -> NA
A23: South Africa | B23: 0.1729 | C23: NA | D23: =IF(C23="NA","NA",IF(B23="NA","NA",B23/C23)) -> NA | E23: 0.0027 | F23: 0.0347 | G23: =IF(F23="NA","NA",E23/F23) -> 0.077809798 | H23: =IF(G23="NA","NA",IF(B23="NA","NA",B23/G23)) -> 2.2220852
A24: Taiwan | B24: 0.1398 | C24: 0.1373 | D24: =IF(C24="NA","NA",IF(B24="NA","NA",B24/C24)) -> 1.0182083 | E24: NA | F24: NA | G24: =IF(F24="NA","NA",E24/F24) -> NA | H24: =IF(G24="NA","NA",IF(B24="NA","NA",B24/G24)) -> NA
A25: Tunisia | B25: 0.0539 | C25: NA | D25: =IF(C25="NA","NA",IF(B25="NA","NA",B25/C25)) -> NA | E25: 0.004 | F25: 0.0816 | G25: =IF(F25="NA","NA",E25/F25) -> 0.049019608 | H25: =IF(G25="NA","NA",IF(B25="NA","NA",B25/G25)) -> 1.09956
A26: Turkey | B26: 0.3189 | C26: 0.148 | D26: =IF(C26="NA","NA",IF(B26="NA","NA",B26/C26)) -> 2.1547297 | E26: 0.0036 | F26: 0.0414 | G26: =IF(F26="NA","NA",E26/F26) -> 0.086956522 | H26: =IF(G26="NA","NA",IF(B26="NA","NA",B26/G26)) -> 3.66735
A27: Venezuela | B27: 0.3081 | C27: 0.6973 | D27: =IF(C27="NA","NA",IF(B27="NA","NA",B27/C27)) -> 0.44184712 | E27: 0.0123 | F27: 0.1065 | G27: =IF(F27="NA","NA",E27/F27) -> 0.11549296 | H27: =IF(G27="NA","NA",IF(B27="NA","NA",B27/G27)) -> 2.6676951
A28: Vietnam | B28: 0.1596 | C28: NA | D28: =IF(C28="NA","NA",IF(B28="NA","NA",B28/C28)) -> NA | E28: 0.0024 | F28: 0.018 | G28: =IF(F28="NA","NA",E28/F28) -> 0.13333333 | H28: =IF(G28="NA","NA",IF(B28="NA","NA",B28/G28)) -> 1.197
A29: Average | D29: =AVERAGE(D4:D28) -> 1.3641638 | H29: =AVERAGE(H4:H28) -> 1.3595726
A30: Median | D30: =MEDIAN(D4:D28) -> 1.2378855 | H30: =MEDIAN(H4:H28) -> 1.1105571
A31: High | D31: =MAX(D4:D28) -> 2.1547297 | H31: =MAX(H4:H28) -> 3.66735
A32: Low | D32: =MIN(D4:D28) -> 0.44184712 | H32: =MIN(H4:H28) -> 0.30035122

Sheet Country GDP
A1: Country | B1: GDP (in millions) in 2024 | E1: Country Name | F1: GDP in 2024 | J1: Country | K1: GDP (in millions) in 2022 | N1: GDP (in millions) in 2023
A2: Abu Dhabi | B2: =N2 -> 310000 | E2: Afghanistan | F2: 17152.235 | J2: Abu Dhabi | K2: 299500 | N2: 310000
A3: Albania | B3: =VLOOKUP(A3,$E$2:$F$266,2,FALSE()) -> 27046.429 | C3: Source: | D3: World Bank | E3: Africa Eastern and Southern | F3: 1242693.5 | J3: Albania | K3: =VLOOKUP(J3,$E$2:$F$214,2,FALSE()) -> 27046.429 | N3: 27046.429
A4: Andorra (Principality of) | B4: =F8 -> 4039.8424 | C4: Year | D4: 2024 | E4: Africa Western and Central | F4: 736384.96 | J4: Andorra (Principality of) | K4: 3330 | N4: 3352
A5: Angola | B5: =VLOOKUP(A5,$E$2:$F$266,2,FALSE()) -> 100998.92 | E5: Albania | F5: 27046.429 | J5: Angola | K5: =VLOOKUP(J5,$E$2:$F$214,2,FALSE()) -> 100998.92 | N5: 100998.92
A6: Argentina | B6: =VLOOKUP(A6,$E$2:$F$266,2,FALSE()) -> 638365.46 | E6: Algeria | F6: 269322.28 | J6: Argentina | K6: =VLOOKUP(J6,$E$2:$F$214,2,FALSE()) -> 638365.46 | N6: 638365.46
A7: Armenia | B7: =VLOOKUP(A7,$E$2:$F$266,2,FALSE()) -> 25955.275 | E7: American Samoa | F7: 871 | J7: Armenia | K7: =VLOOKUP(J7,$E$2:$F$214,2,FALSE()) -> 25955.275 | N7: 25955.275
A8: Aruba | B8: =VLOOKUP(A8,$E$2:$F$266,2,FALSE()) -> 4265.6507 | E8: Andorra | F8: 4039.8424 | J8: Aruba | K8: =VLOOKUP(J8,$E$2:$F$214,2,FALSE()) -> 4265.6507 | N8: 4265.6507
A9: Australia | B9: =VLOOKUP(A9,$E$2:$F$266,2,FALSE()) -> 1757022.5 | E9: Angola | F9: 100998.92 | J9: Australia | K9: =VLOOKUP(J9,$E$2:$F$214,2,FALSE()) -> 1757022.5 | N9: 1757022.5
A10: Austria | B10: =VLOOKUP(A10,$E$2:$F$266,2,FALSE()) -> 534790.72 | E10: Antigua and Barbuda | F10: 2207.6229 | J10: Austria | K10: =VLOOKUP(J10,$E$2:$F$214,2,FALSE()) -> 534790.72 | N10: 534790.72
A11: Azerbaijan | B11: =VLOOKUP(A11,$E$2:$F$266,2,FALSE()) -> 74315.882 | E11: Arab World | F11: 3735881.4 | J11: Azerbaijan | K11: =VLOOKUP(J11,$E$2:$F$214,2,FALSE()) -> 74315.882 | N11: 74315.882
A12: Bahamas | B12: =F18 -> 15832.8 | E12: Argentina | F12: 638365.46 | J12: Bahamas | K12: 11210 | N12: 11210
A13: Bahrain | B13: =VLOOKUP(A13,$E$2:$F$266,2,FALSE()) -> 47109.734 | E13: Armenia | F13: 25955.275 | J13: Bahrain | K13: =VLOOKUP(J13,$E$2:$F$214,2,FALSE()) -> 47109.734 | N13: 47109.734
A14: Bangladesh | B14: =VLOOKUP(A14,$E$2:$F$266,2,FALSE()) -> 450119.43 | E14: Aruba | F14: 4265.6507 | J14: Bangladesh | K14: =VLOOKUP(J14,$E$2:$F$214,2,FALSE()) -> 450119.43 | N14: 450119.43
A15: Barbados | B15: =VLOOKUP(A15,$E$2:$F$266,2,FALSE()) -> 7498.05 | E15: Australia | F15: 1757022.5 | J15: Barbados | K15: =VLOOKUP(J15,$E$2:$F$214,2,FALSE()) -> 7498.05 | N15: 7498.05
A16: Belarus | B16: =VLOOKUP(A16,$E$2:$F$266,2,FALSE()) -> 75961.865 | E16: Austria | F16: 534790.72 | J16: Belarus | K16: =VLOOKUP(J16,$E$2:$F$214,2,FALSE()) -> 75961.865 | N16: 75961.865
A17: Belgium | B17: =VLOOKUP(A17,$E$2:$F$266,2,FALSE()) -> 671370.08 | E17: Azerbaijan | F17: 74315.882 | J17: Belgium | K17: =VLOOKUP(J17,$E$2:$F$214,2,FALSE()) -> 671370.08 | N17: 671370.08
A18: Belize | B18: =VLOOKUP(A18,$E$2:$F$266,2,FALSE()) -> 3203.6318 | E18: Bahamas, The | F18: 15832.8 | J18: Belize | K18: =VLOOKUP(J18,$E$2:$F$214,2,FALSE()) -> 3203.6318 | N18: 3203.6318
A19: Benin | B19: =VLOOKUP(A19,$E$2:$F$266,2,FALSE()) -> 21482.644 | E19: Bahrain | F19: 47109.734 | J19: Benin | K19: =VLOOKUP(J19,$E$2:$F$214,2,FALSE()) -> 21482.644 | N19: 21482.644
A20: Bermuda | B20: =VLOOKUP(A20,$E$2:$F$266,2,FALSE()) -> 9233.6 | E20: Bangladesh | F20: 450119.43 | J20: Bermuda | K20: =VLOOKUP(J20,$E$2:$F$214,2,FALSE()) -> 9233.6 | N20: 9233.6
A21: Bolivia | B21: =VLOOKUP(A21,$E$2:$F$266,2,FALSE()) -> 54881.327 | E21: Barbados | F21: 7498.05 | J21: Bolivia | K21: =VLOOKUP(J21,$E$2:$F$214,2,FALSE()) -> 54881.327 | N21: 54881.327
A22: Bosnia and Herzegovina | B22: =VLOOKUP(A22,$E$2:$F$266,2,FALSE()) -> 29613.572 | E22: Belarus | F22: 75961.865 | J22: Bosnia and Herzegovina | K22: =VLOOKUP(J22,$E$2:$F$214,2,FALSE()) -> 29613.572 | N22: 29613.572
A23: Botswana | B23: =VLOOKUP(A23,$E$2:$F$266,2,FALSE()) -> 19402.064 | E23: Belgium | F23: 671370.08 | J23: Botswana | K23: =VLOOKUP(J23,$E$2:$F$214,2,FALSE()) -> 19402.064 | N23: 19402.064
A24: Brazil | B24: =VLOOKUP(A24,$E$2:$F$266,2,FALSE()) -> 2185821.6 | E24: Belize | F24: 3203.6318 | J24: Brazil | K24: =VLOOKUP(J24,$E$2:$F$214,2,FALSE()) -> 2185821.6 | N24: 2185821.6
... A29: Canada | B29: =VLOOKUP(A29,$E$2:$F$266,2,FALSE()) -> 2243636.8 | E29: Bosnia and Herzegovina | F29: 29613.572 | J29: Canada | K29: =VLOOKUP(J29,$E$2:$F$214,2,FALSE()) -> 2243636.8 | N29: 2243636.8
A30: Cape Verde | B30: =F37 -> 2725.4142 | E30: Botswana | F30: 19402.064 | J30: Cape Verde | K30: 1936 | N30: 1936
A31: Cayman Islands | B31: =VLOOKUP(A31,$E$2:$F$266,2,FALSE()) -> 7241.2443 | E31: Brazil | F31: 2185821.6 | J31: Cayman Islands | K31: =VLOOKUP(J31,$E$2:$F$214,2,FALSE()) -> 7241.2443 | N31: 7241.2443
A32: Chile | B32: =VLOOKUP(A32,$E$2:$F$266,2,FALSE()) -> 330267.14 | E32: British Virgin Islands | F32: 0 | J32: Chile | K32: =VLOOKUP(J32,$E$2:$F$214,2,FALSE()) -> 330267.14 | N32: 330267.14
A33: China | B33: =VLOOKUP(A33,$E$2:$F$266,2,FALSE()) -> 18743803 | E33: Brunei Darussalam | F33: 15340.809 | J33: China | K33: =VLOOKUP(J33,$E$2:$F$214,2,FALSE()) -> 18743803 | N33: 18743803
A34: Colombia | B34: =VLOOKUP(A34,$E$2:$F$266,2,FALSE()) -> 418818.15 | E34: Bulgaria | F34: 113343.36 | J34: Colombia | K34: =VLOOKUP(J34,$E$2:$F$214,2,FALSE()) -> 418818.15 | N34: 418818.15
A35: Congo (Democratic Republic of) | B35: =F51 -> 70962.186 | E35: Burkina Faso | F35: 23124.73 | J35: Congo (Democratic Republic of) | K35: =O51 -> 0 | N35: 12507.321
A36: Congo (Republic of) | B36: =F52 -> 15719.986 | E36: Burundi | F36: 3082.4331 | J36: Congo (Republic of) | K36: 14616 | N36: 330267.14
A37: Cook Islands | B37: =N37 -> 1414 | E37: Cabo Verde | F37: 2725.4142 | J37: Cook Islands | K37: 1414 | N37: 1414
A38: Costa Rica | B38: =VLOOKUP(A38,$E$2:$F$266,2,FALSE()) -> 95350.423 | E38: Cambodia | F38: 46352.647 | J38: Costa Rica | K38: =VLOOKUP(J38,$E$2:$F$214,2,FALSE()) -> 95350.423 | N38: 95350.423
A39: Côte d'Ivoire | B39: =F54 -> 87113.179 | E39: Cameroon | F39: 53296.694 | J39: Côte d'Ivoire | K39: 70019 | N39: 418818.15
A40: Croatia | B40: =VLOOKUP(A40,$E$2:$F$266,2,FALSE()) -> 92983.81 | E40: Canada | F40: 2243636.8 | J40: Croatia | K40: =VLOOKUP(J40,$E$2:$F$214,2,FALSE()) -> 92983.81 | N40: 92983.81
A41: Cuba | B41: =VLOOKUP(A41,$E$2:$F$266,2,FALSE()) -> 107352 | E41: Caribbean small states | F41: 90344.593 | J41: Cuba | K41: =VLOOKUP(J41,$E$2:$F$214,2,FALSE()) -> 107352 | N41: 107351
A42: Curacao | B42: =VLOOKUP(A42,$E$2:$F$266,2,FALSE()) -> 3561.1782 | E42: Cayman Islands | F42: 7241.2443 | J42: Curacao | K42: =VLOOKUP(J42,$E$2:$F$214,2,FALSE()) -> 3561.1782 | N42: 3561.1782
A43: Cyprus | B43: =VLOOKUP(A43,$E$2:$F$266,2,FALSE()) -> 37634.533 | E43: Central African Republic | F43: 2751.4943 | J43: Cyprus | K43: =VLOOKUP(J43,$E$2:$F$214,2,FALSE()) -> 37634.533 | N43: 37634.533
A44: Czech Republic | B44: =F59 -> 347034.06 | E44: Central Europe and the Baltics | F44: 2462005.3 | J44: Czech Republic | K44: =O59 -> 0 | N44: 87113.179
A45: Denmark | B45: =VLOOKUP(A45,$E$2:$F$266,2,FALSE()) -> 424524.72 | E45: Chad | F45: 19518.82 | J45: Denmark | K45: =VLOOKUP(J45,$E$2:$F$214,2,FALSE()) -> 424524.72 | N45: 424524.72
A46: Dominican Republic | B46: =VLOOKUP(A46,$E$2:$F$266,2,FALSE()) -> 124282.25 | E46: Channel Islands | F46: 12507.321 | J46: Dominican Republic | K46: =VLOOKUP(J46,$E$2:$F$214,2,FALSE()) -> 124282.25 | N46: 124282.25
A47: Ecuador | B47: =VLOOKUP(A47,$E$2:$F$266,2,FALSE()) -> 124676.07 | E47: Chile | F47: 330267.14 | J47: Ecuador | K47: =VLOOKUP(J47,$E$2:$F$214,2,FALSE()) -> 124676.07 | N47: 124676.07
A48: Egypt | B48: =F69 -> 389059.91 | E48: China | F48: 18743803 | J48: Egypt | K48: =O69 -> 0 | N48: 424524.72
A49: El Salvador | B49: =VLOOKUP(A49,$E$2:$F$266,2,FALSE()) -> 35364.96 | E49: Colombia | F49: 418818.15 | J49: El Salvador | K49: =VLOOKUP(J49,$E$2:$F$214,2,FALSE()) -> 35364.96 | N49: 35364.96
A50: Estonia | B50: =VLOOKUP(A50,$E$2:$F$266,2,FALSE()) -> 43130.42 | E50: Comoros | F50: 1440.9915 | J50: Estonia | K50: =VLOOKUP(J50,$E$2:$F$214,2,FALSE()) -> 43130.42 | N50: 43130.42
A51: Ethiopia | B51: =VLOOKUP(A51,$E$2:$F$266,2,FALSE()) -> 149740.3 | E51: Congo, Dem. Rep. | F51: 70962.186 | J51: Ethiopia | K51: =VLOOKUP(J51,$E$2:$F$214,2,FALSE()) -> 149740.3 | N51: 149740.3
A52: Fiji | B52: =VLOOKUP(A52,$E$2:$F$266,2,FALSE()) -> 5968.1259 | E52: Congo, Rep. | F52: 15719.986 | J52: Fiji | K52: =VLOOKUP(J52,$E$2:$F$214,2,FALSE()) -> 5968.1259 | N52: 5968.1259
A53: Finland | B53: =VLOOKUP(A53,$E$2:$F$266,2,FALSE()) -> 298696.96 | E53: Costa Rica | F53: 95350.423 | J53: Finland | K53: =VLOOKUP(J53,$E$2:$F$214,2,FALSE()) -> 298696.96 | N53: 298696.96
A54: France | B54: =VLOOKUP(A54,$E$2:$F$266,2,FALSE()) -> 3160442.6 | E54: Cote d'Ivoire | F54: 87113.179 | J54: France | K54: =VLOOKUP(J54,$E$2:$F$214,2,FALSE()) -> 3160442.6 | N54: 3160442.6
A55: Gabon | B55: =VLOOKUP(A55,$E$2:$F$266,2,FALSE()) -> 20895.684 | E55: Croatia | F55: 92983.81 | J55: Gabon | K55: =VLOOKUP(J55,$E$2:$F$214,2,FALSE()) -> 20895.684 | N55: 20895.684
A56: Georgia | B56: =VLOOKUP(A56,$E$2:$F$266,2,FALSE()) -> 34189.424 | E56: Cuba | F56: 107352 | J56: Georgia | K56: =VLOOKUP(J56,$E$2:$F$214,2,FALSE()) -> 34189.424 | N56: 34189.424
A57: Germany | B57: =VLOOKUP(A57,$E$2:$F$266,2,FALSE()) -> 4685592.6 | E57: Curacao | F57: 3561.1782 | J57: Germany | K57: =VLOOKUP(J57,$E$2:$F$214,2,FALSE()) -> 4685592.6 | N57: 4685592.6
A58: Ghana | B58: =VLOOKUP(A58,$E$2:$F$266,2,FALSE()) -> 82308.11 | E58: Cyprus | F58: 37634.533 | J58: Ghana | K58: =VLOOKUP(J58,$E$2:$F$214,2,FALSE()) -> 82308.11 | N58: 82308.11
A59: Greece | B59: =VLOOKUP(A59,$E$2:$F$266,2,FALSE()) -> 256238.37 | E59: Czechia | F59: 347034.06 | J59: Greece | K59: =VLOOKUP(J59,$E$2:$F$214,2,FALSE()) -> 256238.37 | N59: 256238.37
A60: Guatemala | B60: =VLOOKUP(A60,$E$2:$F$266,2,FALSE()) -> 113199.58 | E60: Denmark | F60: 424524.72 | J60: Guatemala | K60: =VLOOKUP(J60,$E$2:$F$214,2,FALSE()) -> 113199.58 | N60: 113199.58
A61: Guernsey (States of) | B61: =N61 -> 3446 | E61: Djibouti | F61: 4152.1459 | J61: Guernsey (States of) | K61: 3446 | N61: 3446
A62: Honduras | B62: =VLOOKUP(A62,$E$2:$F$266,2,FALSE()) -> 37093.566 | E62: Dominica | F62: 688.88148 | J62: Honduras | K62: =VLOOKUP(J62,$E$2:$F$214,2,FALSE()) -> 37093.566 | N62: 37093.566
A63: Hong Kong | B63: =F105 -> 406863.4 | E63: Dominican Republic | F63: 124282.25 | J63: Hong Kong | K63: =O105 -> 0 | N63: 2404.8887
A64: Hungary | B64: =VLOOKUP(A64,$E$2:$F$266,2,FALSE()) -> 222722.74 | E64: Early-demographic dividend | F64: 15808304 | J64: Hungary | K64: =VLOOKUP(J64,$E$2:$F$214,2,FALSE()) -> 222722.74 | N64: 222722.74
A65: Iceland | B65: =VLOOKUP(A65,$E$2:$F$266,2,FALSE()) -> 33255.181 | E65: East Asia & Pacific | F65: 32017180 | J65: Iceland | K65: =VLOOKUP(J65,$E$2:$F$214,2,FALSE()) -> 33255.181 | N65: 33255.181
A66: India | B66: =VLOOKUP(A66,$E$2:$F$266,2,FALSE()) -> 3909891.5 | E66: East Asia & Pacific (excluding high income) | F66: 22260811 | J66: India | K66: =VLOOKUP(J66,$E$2:$F$214,2,FALSE()) -> 3909891.5 | N66: 3909891.5
A67: Indonesia | B67: =VLOOKUP(A67,$E$2:$F$266,2,FALSE()) -> 1396300.1 | E67: East Asia & Pacific (IDA & IBRD countries) | F67: 22233363 | J67: Indonesia | K67: =VLOOKUP(J67,$E$2:$F$214,2,FALSE()) -> 1396300.1 | N67: 1396300.1
A68: Iraq | B68: =VLOOKUP(A68,$E$2:$F$266,2,FALSE()) -> 279641.26 | E68: Ecuador | F68: 124676.07 | J68: Iraq | K68: =VLOOKUP(J68,$E$2:$F$214,2,FALSE()) -> 279641.26 | N68: 279641.26
A69: Ireland | B69: =VLOOKUP(A69,$E$2:$F$266,2,FALSE()) -> 609157.46 | E69: Egypt, Arab Rep. | F69: 389059.91 | J69: Ireland | K69: =VLOOKUP(J69,$E$2:$F$214,2,FALSE()) -> 609157.46 | N69: 609157.46
A70: Isle of Man | B70: =VLOOKUP(A70,$E$2:$F$266,2,FALSE()) -> 7431.2574 | E70: El Salvador | F70: 35364.96 | J70: Isle of Man | K70: =VLOOKUP(J70,$E$2:$F$214,2,FALSE()) -> 7431.2574 | N70: 7431.2574
A71: Israel | B71: =VLOOKUP(A71,$E$2:$F$266,2,FALSE()) -> 540379.92 | E71: Equatorial Guinea | F71: 12765.778 | J71: Israel | K71: =VLOOKUP(J71,$E$2:$F$214,2,FALSE()) -> 540379.92 | N71: 540379.92
A72: Italy | B72: =VLOOKUP(A72,$E$2:$F$266,2,FALSE()) -> 2380825.1 | E72: Eritrea | F72: 0 | J72: Italy | K72: =VLOOKUP(J72,$E$2:$F$214,2,FALSE()) -> 2380825.1 | N72: 2380825.1
A73: Jamaica | B73: =VLOOKUP(A73,$E$2:$F$266,2,FALSE()) -> 22014.397 | E73: Estonia | F73: 43130.42 | J73: Jamaica | K73: =VLOOKUP(J73,$E$2:$F$214,2,FALSE()) -> 22014.397 | N73: 22014.397
A74: Japan | B74: =VLOOKUP(A74,$E$2:$F$266,2,FALSE()) -> 4027597.5 | E74: Eswatini | F74: 4858.8858 | J74: Japan | K74: =VLOOKUP(J74,$E$2:$F$214,2,FALSE()) -> 4027597.5 | N74: 4027597.5
A75: Jersey (States of) | B75: =N75 -> 4890 | E75: Ethiopia | F75: 149740.3 | J75: Jersey (States of) | K75: 4890 | N75: 4890
A76: Jordan | B76: =VLOOKUP(A76,$E$2:$F$266,2,FALSE()) -> 53352.29 | E76: Euro area | F76: 16485444 | J76: Jordan | K76: =VLOOKUP(J76,$E$2:$F$214,2,FALSE()) -> 53352.29 | N76: 53352.29
A77: Kazakhstan | B77: =VLOOKUP(A77,$E$2:$F$266,2,FALSE()) -> 291480.27 | E77: Europe & Central Asia | F77: 29291829 | J77: Kazakhstan | K77: =VLOOKUP(J77,$E$2:$F$214,2,FALSE()) -> 291480.27 | N77: 291480.27
A78: Kenya | B78: =VLOOKUP(A78,$E$2:$F$266,2,FALSE()) -> 120339.56 | E78: Europe & Central Asia (excluding high income) | F78: 2451180.1 | J78: Kenya | K78: =VLOOKUP(J78,$E$2:$F$214,2,FALSE()) -> 120339.56 | N78: 120339.56
A79: Korea | B79: =F128 -> 1875388.2 | E79: Europe & Central Asia (IDA & IBRD countries) | F79: 6131674.4 | J79: Korea | K79: =O128 -> 0 | N79: 222722.74
A80: Kuwait | B80: =VLOOKUP(A80,$E$2:$F$266,2,FALSE()) -> 160227.27 | E80: European Union | F80: 19497116 | J80: Kuwait | K80: =VLOOKUP(J80,$E$2:$F$214,2,FALSE()) -> 160227.27 | N80: 11000
A81: Kyrgyzstan | B81: =F131 -> 17478.26 | E81: Faroe Islands | F81: 4052.9372 | J81: Kyrgyzstan | K81: =O131 -> 0 | N81: 43823205
A82: Laos | B82: =F132 -> 16502.933 | E82: Fiji | F82: 5968.1259 | J82: Laos | K82: =O132 -> 0 | N82: 1117411.9
A83: Latvia | B83: =VLOOKUP(A83,$E$2:$F$266,2,FALSE()) -> 43684.254 | E83: Finland | F83: 298696.96 | J83: Latvia | K83: =VLOOKUP(J83,$E$2:$F$214,2,FALSE()) -> 43684.254 | N83: 43684.254
A84: Lebanon | B84: =20078620357/1000000 -> 20078.62 | E84: Fragile and conflict affected situations | F84: 1652895.5 | J84: Lebanon | K84: =VLOOKUP(J84,$E$2:$F$214,2,FALSE()) -> 0 | N84: 0
A85: Liechtenstein | B85: =8239379403/1000000 -> 8239.3794 | E85: France | F85: 3160442.6 | J85: Liechtenstein | K85: =VLOOKUP(J85,$E$2:$F$214,2,FALSE()) -> 0 | N85: 0
A86: Lithuania | B86: =VLOOKUP(A86,$E$2:$F$266,2,FALSE()) -> 84869.216 | E86: French Polynesia | F86: 6323.7164 | J86: Lithuania | K86: =VLOOKUP(J86,$E$2:$F$214,2,FALSE()) -> 84869.216 | N86: 84869.216
A87: Luxembourg | B87: =VLOOKUP(A87,$E$2:$F$266,2,FALSE()) -> 93279.852 | E87: Gabon | F87: 20895.684 | J87: Luxembourg | K87: =VLOOKUP(J87,$E$2:$F$214,2,FALSE()) -> 93279.852 | N87: 93279.852
A88: Macao | B88: =F149 -> 49467.259 | E88: Gambia, The | F88: 2404.8887 | J88: Macao | K88: =O149 -> 0 | N88: 540379.92
A89: Macedonia | B89: =F182 -> 16951.682 | E89: Georgia | F89: 34189.424 | J89: Macedonia | K89: =O182 -> 0 | N89: 7941312.4
A90: Malaysia | B90: =VLOOKUP(A90,$E$2:$F$266,2,FALSE()) -> 422227.01 | E90: Germany | F90: 4685592.6 | J90: Malaysia | K90: =VLOOKUP(J90,$E$2:$F$214,2,FALSE()) -> 422227.01 | N90: 422227.01
A91: Maldives | B91: =VLOOKUP(A91,$E$2:$F$266,2,FALSE()) -> 7061.6083 | E91: Ghana | F91: 82308.11 | J91: Maldives | K91: =VLOOKUP(J91,$E$2:$F$214,2,FALSE()) -> 7061.6083 | N91: 7061.6083
A92: Mali | B92: =VLOOKUP(A92,$E$2:$F$266,2,FALSE()) -> 26794.747 | E92: Gibraltar | F92: 0 | J92: Mali | K92: =VLOOKUP(J92,$E$2:$F$214,2,FALSE()) -> 26794.747 | N92: 26794.747
A93: Malta | B93: =VLOOKUP(A93,$E$2:$F$266,2,FALSE()) -> 24971.575 | E93: Greece | F93: 256238.37 | J93: Malta | K93: =VLOOKUP(J93,$E$2:$F$214,2,FALSE()) -> 24971.575 | N93: 24971.575
A94: Mauritius | B94: =VLOOKUP(A94,$E$2:$F$266,2,FALSE()) -> 14937.862 | E94: Greenland | F94: 3326.544 | J94: Mauritius | K94: =VLOOKUP(J94,$E$2:$F$214,2,FALSE()) -> 14937.862 | N94: 14937.862
A95: Mexico | B95: =VLOOKUP(A95,$E$2:$F$266,2,FALSE()) -> 1856365.6 | E95: Grenada | F95: 1371.9185 | J95: Mexico | K95: =VLOOKUP(J95,$E$2:$F$214,2,FALSE()) -> 1856365.6 | N95: 1856365.6
A96: Moldova | B96: =VLOOKUP(A96,$E$2:$F$266,2,FALSE()) -> 18200.341 | E96: Guam | F96: 6910 | J96: Moldova | K96: =VLOOKUP(J96,$E$2:$F$214,2,FALSE()) -> 18200.341 | N96: 18200.341
A97: Mongolia | B97: =VLOOKUP(A97,$E$2:$F$266,2,FALSE()) -> 23794.54 | E97: Guatemala | F97: 113199.58 | J97: Mongolia | K97: =VLOOKUP(J97,$E$2:$F$214,2,FALSE()) -> 23794.54 | N97: 23794.54
A98: Montenegro | B98: =VLOOKUP(A98,$E$2:$F$266,2,FALSE()) -> 8270.0167 | E98: Guinea | F98: 25008.678 | J98: Montenegro | K98: =VLOOKUP(J98,$E$2:$F$214,2,FALSE()) -> 8270.0167 | N98: 8270.0167
A99: Montserrat | B99: =N99 -> 16199 | E99: Guinea-Bissau | F99: 2218.3938 | J99: Montserrat | K99: 16199 | N99: 16199
A100: Morocco | B100: =VLOOKUP(A100,$E$2:$F$266,2,FALSE()) -> 160610.99 | E100: Guyana | F100: 24662.71 | J100: Morocco | K100: =VLOOKUP(J100,$E$2:$F$214,2,FALSE()) -> 160610.99 | N100: 160610.99
A101: Mozambique | B101: =VLOOKUP(A101,$E$2:$F$266,2,FALSE()) -> 22745.341 | E101: Haiti | F101: 25224.155 | J101: Mozambique | K101: =VLOOKUP(J101,$E$2:$F$214,2,FALSE()) -> 22745.341 | N101: 22745.341
A102: Namibia | B102: =VLOOKUP(A102,$E$2:$F$266,2,FALSE()) -> 13372.355 | E102: Heavily indebted poor countries (HIPC) | F102: 1145111.3 | J102: Namibia | K102: =VLOOKUP(J102,$E$2:$F$214,2,FALSE()) -> 13372.355 | N102: 13372.355
A103: Nepal | B103: =VLOOKUP(A103,$E$2:$F$266,2,FALSE()) -> 42914.268 | E103: High income | F103: 71321143 | J103: Netherlands | K103: =VLOOKUP(J103,$E$2:$F$214,2,FALSE()) -> 1214927.7 | N103: 42914.268
A104: Netherlands | B104: =VLOOKUP(A104,$E$2:$F$266,2,FALSE()) -> 1214927.7 | E104: Honduras | F104: 37093.566 | J104: New Zealand | K104: =VLOOKUP(J104,$E$2:$F$214,2,FALSE()) -> 260172.39 | N104: 1214927.7
...

Sheet Ratings worksheet
A1: Country | B1: S&P Rating | C1: Moody's Rating | E1: Country | F1: Moody's | G1: S&P | H1: FITCH | L1: FC | M1: LC | O1: Country | P1: S&P | R1: Fitch
A2: Abu Dhabi | B2: =G2 -> #N/A | C2: =F2 -> Aa2 | E2: Abu Dhabi | F2: =VLOOKUP(E2,$K$2:$M$154,3,FALSE()) -> Aa2 | G2: =VLOOKUP(E2,$O$2:$P$155,2,FALSE()) -> #N/A | H2: =VLOOKUP(E2,$Q$2:$R$161,2,FALSE()) -> #N/A | K2: Abu Dhabi | L2: Aa2 | M2: Aa2 | O2: Albania | P2: BB | Q2: Albania | R2: NR
A3: Albania | B3: =G3 -> BB | C3: =F3 -> Ba3 | E3: Albania | F3: =VLOOKUP(E3,$K$2:$M$154,3,FALSE()) -> Ba3 | G3: =VLOOKUP(E3,$O$2:$P$155,2,FALSE()) -> BB | H3: =VLOOKUP(E3,$Q$2:$R$161,2,FALSE()) -> NR | K3: Albania | L3: Ba3 | M3: Ba3 | O3: Andorra | P3: A- | Q3: Andorra | R3: A-
A4: Andorra (Principality of) | B4: =G4 -> A- | C4: =F4 -> Baa1 | E4: Andorra | F4: =VLOOKUP(E4,$K$2:$M$154,3,FALSE()) -> Baa1 | G4: =VLOOKUP(E4,$O$2:$P$155,2,FALSE()) -> A- | H4: =VLOOKUP(E4,$Q$2:$R$161,2,FALSE()) -> A- | K4: Andorra | L4: Baa1 | M4: Baa1 | O4: Angola | P4: B- | Q4: Angola | R4: B-
A5: Angola | B5: =G5 -> B- | C5: =F5 -> B3 | E5: Angola | F5: =VLOOKUP(E5,$K$2:$M$154,3,FALSE()) -> B3 | G5: =VLOOKUP(E5,$O$2:$P$155,2,FALSE()) -> B- | H5: =VLOOKUP(E5,$Q$2:$R$161,2,FALSE()) -> B- | K5: Angola | L5: B3 | M5: B3 | O5: Argentina | P5: CCC+ | Q5: Argentina | R5: CCC+
A6: Argentina | B6: =G6 -> CCC+ | C6: =F6 -> Caa1 | E6: Argentina | F6: =VLOOKUP(E6,$K$2:$M$154,3,FALSE()) -> Caa1 | G6: =VLOOKUP(E6,$O$2:$P$155,2,FALSE()) -> CCC+ | H6: =VLOOKUP(E6,$Q$2:$R$161,2,FALSE()) -> CCC+ | K6: Argentina | L6: Caa1 | M6: Caa1 | O6: Armenia | P6: BB- | Q6: Armenia | R6: BB-
A7: Armenia | B7: =G7 -> BB- | C7: =F7 -> Ba3 | E7: Armenia | F7: =VLOOKUP(E7,$K$2:$M$154,3,FALSE()) -> Ba3 | G7: =VLOOKUP(E7,$O$2:$P$155,2,FALSE()) -> BB- | H7: =VLOOKUP(E7,$Q$2:$R$161,2,FALSE()) -> BB- | K7: Armenia | L7: Ba3 | M7: Ba3 | O7: Aruba | P7: BBB+ | Q7: Aruba | R7: BBB-
A8: Aruba | B8: =G8 -> BBB+ | C8: =F8 -> Baa3 | E8: Aruba | F8: =VLOOKUP(E8,$K$2:$M$154,3,FALSE()) -> Baa3 | G8: =VLOOKUP(E8,$O$2:$P$155,2,FALSE()) -> BBB+ | H8: =VLOOKUP(E8,$Q$2:$R$161,2,FALSE()) -> BBB- | K8: Aruba | L8: Baa3 | M8: Baa3 | O8: Australia | P8: AAA | Q8: Australia | R8: AAA
A9: Australia | B9: =G9 -> AAA | C9: =F9 -> Aaa | E9: Australia | F9: =VLOOKUP(E9,$K$2:$M$154,3,FALSE()) -> Aaa | G9: =VLOOKUP(E9,$O$2:$P$155,2,FALSE()) -> AAA | H9: =VLOOKUP(E9,$Q$2:$R$161,2,FALSE()) -> AAA | K9: Australia | L9: Aaa | M9: Aaa | O9: Austria | P9: AA+ | Q9: Austria | R9: AA
A10: Austria | B10: =G10 -> AA+ | C10: =F10 -> Aa1 | E10: Austria | F10: =VLOOKUP(E10,$K$2:$M$154,3,FALSE()) -> Aa1 | G10: =VLOOKUP(E10,$O$2:$P$155,2,FALSE()) -> AA+ | H10: =VLOOKUP(E10,$Q$2:$R$161,2,FALSE()) -> AA | K10: Austria | L10: Aa1 | M10: Aa1 | O10: Azerbaijan | P10: NR | Q10: Azerbaijan | R10: BBB-
A11: Azerbaijan | B11: =G11 -> NR | C11: =F11 -> Baa3 | E11: Azerbaijan | F11: =VLOOKUP(E11,$K$2:$M$154,3,FALSE()) -> Baa3 | G11: =VLOOKUP(E11,$O$2:$P$155,2,FALSE()) -> NR | H11: =VLOOKUP(E11,$Q$2:$R$161,2,FALSE()) -> BBB- | K11: Azerbaijan | L11: Baa3 | M11: Baa3 | O11: Bahamas | P11: BB- | Q11: Bahamas | R11: BB-
A12: Bahamas | B12: =G12 -> BB- | C12: =F12 -> B1 | E12: Bahamas | F12: =VLOOKUP(E12,$K$2:$M$154,3,FALSE()) -> B1 | G12: =VLOOKUP(E12,$O$2:$P$155,2,FALSE()) -> BB- | H12: =VLOOKUP(E12,$Q$2:$R$161,2,FALSE()) -> BB- | K12: Bahamas | L12: B1 | M12: B1 | O12: Bahrain | P12: B | Q12: Bahrain | R12: B+
A13: Bahrain | B13: =G13 -> B | C13: =F13 -> B2 | E13: Bahrain | F13: =VLOOKUP(E13,$K$2:$M$154,3,FALSE()) -> B2 | G13: =VLOOKUP(E13,$O$2:$P$155,2,FALSE()) -> B | H13: =VLOOKUP(E13,$Q$2:$R$161,2,FALSE()) -> B+ | K13: Bahamas-Offshore Banks | L13: - | M13: - | O13: Bangladesh | P13: B+ | Q13: Bangladesh | R13: B+
... A25: Bulgaria | B25: =G25 -> BBB+ | C25: =F25 -> Baa1 | E25: Bulgaria | F25: =VLOOKUP(E25,$K$2:$M$154,3,FALSE()) -> Baa1 | G25: =VLOOKUP(E25,$O$2:$P$155,2,FALSE()) -> BBB+ | H25: =VLOOKUP(E25,$Q$2:$R$161,2,FALSE()) -> BBB+ | K25: Botswana | L25: Baa1 | M25: Baa1 | O25: Burkina Faso | P25: CCC+ | Q25: Burkina Faso | R25: NR
A26: Burkina Faso | B26: =G26 -> CCC+ | C26: =F26 -> NR | E26: Burkina Faso | F26: NR | G26: =VLOOKUP(E26,$O$2:$P$155,2,FALSE()) -> CCC+ | H26: =VLOOKUP(E26,$Q$2:$R$161,2,FALSE()) -> NR | K26: Brazil | L26: Ba1 | M26: Ba1 | O26: Cambodia | P26: N/A | Q26: Cambodia | R26: NR
A27: Cambodia | B27: =G27 -> N/A | C27: =F27 -> B2 | E27: Cambodia | F27: =VLOOKUP(E27,$K$2:$M$154,3,FALSE()) -> B2 | G27: =VLOOKUP(E27,$O$2:$P$155,2,FALSE()) -> N/A | H27: =VLOOKUP(E27,$Q$2:$R$161,2,FALSE()) -> NR | K27: Bulgaria | L27: Baa1 | M27: Baa1 | O27: Cameroon | P27: B- | Q27: Cameroon | R27: B
A28: Cameroon | B28: =G28 -> B- | C28: =F28 -> Caa1 | E28: Cameroon | F28: =VLOOKUP(E28,$K$2:$M$154,3,FALSE()) -> Caa1 | G28: =VLOOKUP(E28,$O$2:$P$155,2,FALSE()) -> B- | H28: =VLOOKUP(E28,$Q$2:$R$161,2,FALSE()) -> B | K28: Cambodia | L28: B2 | M28: B2 | O28: Canada | P28: AAA | Q28: Canada | R28: AA+
A29: Canada | B29: =G29 -> AAA | C29: =F29 -> Aaa | E29: Canada | F29: =VLOOKUP(E29,$K$2:$M$154,3,FALSE()) -> Aaa | G29: =VLOOKUP(E29,$O$2:$P$155,2,FALSE()) -> AAA | H29: =VLOOKUP(E29,$Q$2:$R$161,2,FALSE()) -> AA+ | K29: Cameroon | L29: Caa1 | M29: Caa1 | O29: Cape Verde | P29: B | Q29: Cape Verde | R29: B
A30: Cape Verde | B30: =G30 -> B | C30: =F30 -> NR | E30: Cape Verde | F30: NR | G30: =VLOOKUP(E30,$O$2:$P$155,2,FALSE()) -> B | H30: =VLOOKUP(E30,$Q$2:$R$161,2,FALSE()) -> B | K30: Canada | L30: Aaa | M30: Aaa | O30: Cayman Islands | Q30: Chad | R30: B-
A31: Cayman Islands | B31: =G31 -> 0 | C31: =F31 -> Aa3 | E31: Cayman Islands | F31: =VLOOKUP(E31,$K$2:$M$154,3,FALSE()) -> Aa3 | G31: =VLOOKUP(E31,$O$2:$P$155,2,FALSE()) -> 0 | H31: =VLOOKUP(E31,$Q$2:$R$161,2,FALSE()) -> #N/A | K31: Cayman Islands | L31: Aa3 | M31: Aa3 | O31: Chad | P31: B- | Q31: Chile | R31: A-
A32: Chile | B32: =G32 -> A | C32: =F32 -> A2 | E32: Chile | F32: =VLOOKUP(E32,$K$2:$M$154,3,FALSE()) -> A2 | G32: =VLOOKUP(E32,$O$2:$P$155,2,FALSE()) -> A | H32: =VLOOKUP(E32,$Q$2:$R$161,2,FALSE()) -> A- | K32: Cayman Islands-Offshore Banks | L32: - | M32: - | O32: Chile | P32: A | Q32: China | R32: A
A33: China | B33: =G33 -> A+ | C33: =F33 -> A1 | E33: China | F33: =VLOOKUP(E33,$K$2:$M$154,3,FALSE()) -> A1 | G33: =VLOOKUP(E33,$O$2:$P$155,2,FALSE()) -> A+ | H33: =VLOOKUP(E33,$Q$2:$R$161,2,FALSE()) -> A | K33: Chile | L33: A2 | M33: A2 | O33: China | P33: A+ | Q33: Colombia | R33: BB
A34: Colombia | B34: =G34 -> BB | C34: =F34 -> Baa3 | E34: Colombia | F34: =VLOOKUP(E34,$K$2:$M$154,3,FALSE()) -> Baa3 | G34: =VLOOKUP(E34,$O$2:$P$155,2,FALSE()) -> BB | H34: =VLOOKUP(E34,$Q$2:$R$161,2,FALSE()) -> BB | K34: China | L34: A1 | M34: A1 | O34: Colombia | P34: BB | Q34: Costa Rica | R34: BB
A35: Congo (Democratic Republic of) | B35: =G35 -> #N/A | C35: =F35 -> B3 | E35: Congo (Democratic Republic of) | F35: B3 | G35: =VLOOKUP(E35,$O$2:$P$155,2,FALSE()) -> #N/A | H35: =VLOOKUP(E35,$Q$2:$R$161,2,FALSE()) -> #N/A | K35: Colombia | L35: Baa3 | M35: Baa3 | O35: Congo | P35: B- | Q35: Croatia | R35: A-
A36: Congo (Republic of) | B36: =G36 -> CCC+ | C36: =F36 -> Caa2 | E36: Congo (Republic of) | F36: Caa2 | G36: CCC+ | H36: =VLOOKUP(E36,$Q$2:$R$161,2,FALSE()) -> #N/A | K36: Costa Rica | L36: Ba2 | M36: Ba2 | O36: Costa Rica | P36: BB | Q36: Cuba | R36: NR
A37: Cook Islands | B37: =G37 -> #N/A | C37: =F37 -> B1 | E37: Cook Islands | F37: B1 | G37: =VLOOKUP(E37,$O$2:$P$155,2,FALSE()) -> #N/A | H37: =VLOOKUP(E37,$Q$2:$R$161,2,FALSE()) -> #N/A | K37: Cote d'Ivoire | L37: Ba2 | M37: Ba2 | O37: Croatia | P37: A- | Q37: Cyprus | R37: A-
A38: Costa Rica | B38: =G38 -> BB | C38: =F38 -> Ba2 | E38: Costa Rica | F38: =VLOOKUP(E38,$K$2:$M$154,3,FALSE()) -> Ba2 | G38: =VLOOKUP(E38,$O$2:$P$155,2,FALSE()) -> BB | H38: =VLOOKUP(E38,$Q$2:$R$161,2,FALSE()) -> BB | K38: Croatia | L38: A3 | M38: A3 | O38: Cyprus | P38: A- | Q38: Czechia | R38: AA-
A39: Côte d'Ivoire | B39: =G39 -> #N/A | C39: =F39 -> Ba2 | E39: Cote d'Ivoire | F39: =VLOOKUP(E39,$K$2:$M$154,3,FALSE()) -> Ba2 | G39: =VLOOKUP(E39,$O$2:$P$155,2,FALSE()) -> #N/A | H39: =VLOOKUP(E39,$Q$2:$R$161,2,FALSE()) -> #N/A | K39: Cuba | L39: WR | M39: WR | O39: Czech Republic | P39: AA- | Q39: Democratic Republic of the Congo | R39: NR
A40: Croatia | B40: =G40 -> A- | C40: =F40 -> A3 | E40: Croatia | F40: =VLOOKUP(E40,$K$2:$M$154,3,FALSE()) -> A3 | G40: =VLOOKUP(E40,$O$2:$P$155,2,FALSE()) -> A- | H40: =VLOOKUP(E40,$Q$2:$R$161,2,FALSE()) -> A- | K40: Cyprus | L40: A3 | M40: A3 | O40: Denmark | P40: AAA | Q40: Denmark | R40: AAA
A41: Cuba | B41: =G41 -> #N/A | C41: =F41 -> Ca | E41: Cuba | F41: Ca | G41: =VLOOKUP(E41,$O$2:$P$155,2,FALSE()) -> #N/A | H41: =VLOOKUP(E41,$Q$2:$R$161,2,FALSE()) -> NR | K41: Czech Republic | L41: Aa3 | M41: Aa3 | O41: Dominican Republic | P41: BB | Q41: Dominican Republic | R41: BB-
A42: Curacao | B42: BBB- | C42: =F42 -> NR | E42: Curacao | F42: NR | G42: =VLOOKUP(E42,$O$2:$P$155,2,FALSE()) -> #N/A | H42: =VLOOKUP(E42,$Q$2:$R$161,2,FALSE()) -> #N/A | K42: Democratic Republic of the Congo | L42: B3 | M42: B3 | O42: Ecuador | P42: B- | Q42: Ecuador | R42: CCC+
A43: Cyprus | B43: =G43 -> A- | C43: =F43 -> A3 | E43: Cyprus | F43: =VLOOKUP(E43,$K$2:$M$154,3,FALSE()) -> A3 | G43: =VLOOKUP(E43,$O$2:$P$155,2,FALSE()) -> A- | H43: =VLOOKUP(E43,$Q$2:$R$161,2,FALSE()) -> A- | K43: Denmark | L43: Aaa | M43: Aaa | O43: Egypt | P43: B | Q43: Egypt | R43: B
A44: Czech Republic | B44: =G44 -> AA- | C44: =F44 -> Aa3 | E44: Czech Republic | F44: =VLOOKUP(E44,$K$2:$M$154,3,FALSE()) -> Aa3 | G44: =VLOOKUP(E44,$O$2:$P$155,2,FALSE()) -> AA- | H44: =VLOOKUP(E44,$Q$2:$R$161,2,FALSE()) -> #N/A | K44: Dominican Republic | L44: Ba2 | M44: Ba2 | O44: El Salvador | P44: B- | Q44: El Salvador | R44: B-
A45: Denmark | B45: =G45 -> AAA | C45: =F45 -> Aaa | E45: Denmark | F45: =VLOOKUP(E45,$K$2:$M$154,3,FALSE()) -> Aaa | G45: =VLOOKUP(E45,$O$2:$P$155,2,FALSE()) -> AAA | H45: =VLOOKUP(E45,$Q$2:$R$161,2,FALSE()) -> AAA | K45: Ecuador | L45: Caa1 | M45: - | O45: Estonia | P45: NR | Q45: Estonia | R45: A+
A46: Dominican Republic | B46: =G46 -> BB | C46: =F46 -> Ba2 | E46: Dominican Republic | F46: =VLOOKUP(E46,$K$2:$M$154,3,FALSE()) -> Ba2 | G46: =VLOOKUP(E46,$O$2:$P$155,2,FALSE()) -> BB | H46: =VLOOKUP(E46,$Q$2:$R$161,2,FALSE()) -> BB- | K46: Egypt | L46: Caa1 | M46: Caa1 | O46: Ethiopia | P46: SD | Q46: Ethiopia | R46: RD
A47: Ecuador | B47: =G47 -> B- | C47: =F47 -> Caa3 | E47: Ecuador | F47: Caa3 | G47: =VLOOKUP(E47,$O$2:$P$155,2,FALSE()) -> B- | H47: =VLOOKUP(E47,$Q$2:$R$161,2,FALSE()) -> CCC+ | K47: El Salvador | L47: B3 | M47: - | O47: European Union | P47: AA+ | Q47: Fiji | R47: NR
A48: Egypt | B48: =G48 -> B | C48: =F48 -> Caa1 | E48: Egypt | F48: =VLOOKUP(E48,$K$2:$M$154,3,FALSE()) -> Caa1 | G48: =VLOOKUP(E48,$O$2:$P$155,2,FALSE()) -> B | H48: =VLOOKUP(E48,$Q$2:$R$161,2,FALSE()) -> B | K48: Estonia | L48: A1 | M48: A1 | O48: Fiji | P48: B+ | Q48: Finland | R48: AA
A49: El Salvador | B49: =G49 -> B- | C49: NR | E49: El Salvador | F49: =VLOOKUP(E49,$K$2:$M$154,3,FALSE()) -> - | G49: =VLOOKUP(E49,$O$2:$P$155,2,FALSE()) -> B- | H49: =VLOOKUP(E49,$Q$2:$R$161,2,FALSE()) -> B- | K49: eSwatini | L49: B2 | M49: B2 | O49: Finland | P49: AA+ | Q49: France | R49: A+
A50: Estonia | B50: =G50 -> NR | C50: =F50 -> A1 | E50: Estonia | F50: =VLOOKUP(E50,$K$2:$M$154,3,FALSE()) -> A1 | G50: =VLOOKUP(E50,$O$2:$P$155,2,FALSE()) -> NR | H50: =VLOOKUP(E50,$Q$2:$R$161,2,FALSE()) -> A+ | K50: Ethiopia | L50: Caa3 | M50: Caa2 | O50: France | P50: A+ | Q50: Gabon | R50: CCC-
A51: Ethiopia | B51: =G51 -> SD | C51: =F51 -> Caa2 | E51: Ethiopia | F51: =VLOOKUP(E51,$K$2:$M$154,3,FALSE()) -> Caa2 | G51: =VLOOKUP(E51,$O$2:$P$155,2,FALSE()) -> SD | H51: =VLOOKUP(E51,$Q$2:$R$161,2,FALSE()) -> RD | K51: Fiji | L51: B1 | M51: B1 | O51: Gabon | P51: N/A | Q51: Gambia | R51: CCC
A52: Fiji | B52: =G52 -> B+ | C52: =F52 -> B1 | E52: Fiji | F52: =VLOOKUP(E52,$K$2:$M$154,3,FALSE()) -> B1 | G52: =VLOOKUP(E52,$O$2:$P$155,2,FALSE()) -> B+ | H52: =VLOOKUP(E52,$Q$2:$R$161,2,FALSE()) -> NR | K52: Finland | L52: Aa1 | M52: Aa1 | O52: Georgia | P52: BB | Q52: Georgia | R52: BB
A53: Finland | B53: =G53 -> AA+ | C53: =F53 -> Aa1 | E53: Finland | F53: =VLOOKUP(E53,$K$2:$M$154,3,FALSE()) -> Aa1 | G53: =VLOOKUP(E53,$O$2:$P$155,2,FALSE()) -> AA+ | H53: =VLOOKUP(E53,$Q$2:$R$161,2,FALSE()) -> AA | K53: France | L53: Aa3 | M53: Aa3 | O53: Germany | P53: AAA | Q53: Germany | R53: AAA
A54: France | B54: =G54 -> A+ | C54: =F54 -> Aa3 | E54: France | F54: =VLOOKUP(E54,$K$2:$M$154,3,FALSE()) -> Aa3 | G54: =VLOOKUP(E54,$O$2:$P$155,2,FALSE()) -> A+ | H54: =VLOOKUP(E54,$Q$2:$R$161,2,FALSE()) -> A+ | K54: Gabon | L54: Caa2 | M54: Caa2 | O54: Ghana | P54: B- | Q54: Ghana | R54: B-
A55: Gabon | B55: =G55 -> N/A | C55: =F55 -> Caa2 | E55: Gabon | F55: =VLOOKUP(E55,$K$2:$M$154,3,FALSE()) -> Caa2 | G55: =VLOOKUP(E55,$O$2:$P$155,2,FALSE()) -> N/A | H55: =VLOOKUP(E55,$Q$2:$R$161,2,FALSE()) -> CCC- | K55: Georgia | L55: Ba2 | M55: Ba2 | O55: Greece | P55: BBB | Q55: Greece | R55: BBB
A56: Georgia | B56: =G56 -> BB | C56: =F56 -> Ba2 | E56: Georgia | F56: =VLOOKUP(E56,$K$2:$M$154,3,FALSE()) -> Ba2 | G56: =VLOOKUP(E56,$O$2:$P$155,2,FALSE()) -> BB | H56: =VLOOKUP(E56,$Q$2:$R$161,2,FALSE()) -> BB | K56: Germany | L56: Aaa | M56: Aaa | O56: Guatemala | P56: BB+ | Q56: Grenada | R56: NR
A57: Germany | B57: =G57 -> AAA | C57: =F57 -> Aaa | E57: Germany | F57: =VLOOKUP(E57,$K$2:$M$154,3,FALSE()) -> Aaa | G57: =VLOOKUP(E57,$O$2:$P$155,2,FALSE()) -> AAA | H57: =VLOOKUP(E57,$Q$2:$R$161,2,FALSE()) -> AAA | K57: Ghana | L57: Caa1 | M57: Caa1 | O57: Honduras | P57: BB- | Q57: Guatemala | R57: BB+
A58: Ghana | B58: =G58 -> B- | C58: =F58 -> Caa1 | E58: Ghana | F58: =VLOOKUP(E58,$K$2:$M$154,3,FALSE()) -> Caa1 | G58: =VLOOKUP(E58,$O$2:$P$155,2,FALSE()) -> B- | H58: =VLOOKUP(E58,$Q$2:$R$161,2,FALSE()) -> B- | K58: Greece | L58: Baa3 | M58: Baa3 | O58: Hong Kong | P58: AA+ | Q58: Guinea | R58: NR
A59: Greece | B59: =G59 -> BBB | C59: =F59 -> Baa3 | E59: Greece | F59: =VLOOKUP(E59,$K$2:$M$154,3,FALSE()) -> Baa3 | G59: =VLOOKUP(E59,$O$2:$P$155,2,FALSE()) -> BBB | H59: =VLOOKUP(E59,$Q$2:$R$161,2,FALSE()) -> BBB | K59: Guatemala | L59: Ba1 | M59: Ba1 | O59: Hungary | P59: BBB- | Q59: Honduras | R59: B
A60: Guatemala | B60: =G60 -> BB+ | C60: =F60 -> Ba1 | E60: Guatemala | F60: =VLOOKUP(E60,$K$2:$M$154,3,FALSE()) -> Ba1 | G60: =VLOOKUP(E60,$O$2:$P$155,2,FALSE()) -> BB+ | H60: =VLOOKUP(E60,$Q$2:$R$161,2,FALSE()) -> BB+ | K60: Guernsey (Channel Islands) | L60: - | M60: - | O60: Iceland | P60: A+ | Q60: Hong Kong | R60: AA-
A61: Guernsey (States of) | B61: A+ | C61: NR | E61: Guernsey (Channel Islands) | F61: =VLOOKUP(E61,$K$2:$M$154,3,FALSE()) -> - | G61: =VLOOKUP(E61,$O$2:$P$155,2,FALSE()) -> #N/A | H61: =VLOOKUP(E61,$Q$2:$R$161,2,FALSE()) -> #N/A | K61: Honduras | L61: B1 | M61: B1 | O61: India | P61: BBB | Q61: Hungary | R61: BBB
A62: Honduras | B62: =G62 -> BB- | C62: =F62 -> B1 | E62: Honduras | F62: =VLOOKUP(E62,$K$2:$M$154,3,FALSE()) -> B1 | G62: =VLOOKUP(E62,$O$2:$P$155,2,FALSE()) -> BB- | H62: =VLOOKUP(E62,$Q$2:$R$161,2,FALSE()) -> B | K62: Hong Kong SAR, China | L62: Aa3 | M62: Aa3 | O62: Indonesia | P62: BBB | Q62: Iceland | R62: A
A63: Hong Kong | B63: =G63 -> AA+ | C63: =F63 -> Aa3 | E63: Hong Kong | F63: Aa3 | G63: =VLOOKUP(E63,$O$2:$P$155,2,FALSE()) -> AA+ | H63: =VLOOKUP(E63,$Q$2:$R$161,2,FALSE()) -> AA- | K63: Hungary | L63: Baa2 | M63: Baa2 | O63: Iraq | P63: B- | Q63: India | R63: BBB-
A64: Hungary | B64: =G64 -> BBB- | C64: =F64 -> Baa2 | E64: Hungary | F64: =VLOOKUP(E64,$K$2:$M$154,3,FALSE()) -> Baa2 | G64: =VLOOKUP(E64,$O$2:$P$155,2,FALSE()) -> BBB- | H64: =VLOOKUP(E64,$Q$2:$R$161,2,FALSE()) -> BBB | K64: Iceland | L64: A1 | M64: A1 | O64: Ireland | P64: AA | Q64: Indonesia | R64: BBB
A65: Iceland | B65: =G65 -> A+ | C65: =F65 -> A1 | E65: Iceland | F65: =VLOOKUP(E65,$K$2:$M$154,3,FALSE()) -> A1 | G65: =VLOOKUP(E65,$O$2:$P$155,2,FALSE()) -> A+ | H65: =VLOOKUP(E65,$Q$2:$R$161,2,FALSE()) -> A | K65: India | L65: Baa3 | M65: Baa3 | O65: Isle of Man | P65: N/A | Q65: Iran | R65: B+
A66: India | B66: =G66 -> BBB | C66: =F66 -> Baa3 | E66: India | F66: =VLOOKUP(E66,$K$2:$M$154,3,FALSE()) -> Baa3 | G66: =VLOOKUP(E66,$O$2:$P$155,2,FALSE()) -> BBB | H66: =VLOOKUP(E66,$Q$2:$R$161,2,FALSE()) -> BBB- | K66: Indonesia | L66: Baa2 | M66: Baa2 | O66: Israel | P66: A | Q66: Iraq | R66: B-
A67: Indonesia | B67: =G67 -> BBB | C67: =F67 -> Baa2 | E67: Indonesia | F67: =VLOOKUP(E67,$K$2:$M$154,3,FALSE()) -> Baa2 | G67: =VLOOKUP(E67,$O$2:$P$155,2,FALSE()) -> BBB | H67: =VLOOKUP(E67,$Q$2:$R$161,2,FALSE()) -> BBB | K67: Iraq | L67: Caa1 | M67: Caa1 | O67: Italy | P67: BBB+ | Q67: Ireland | R67: AA
A68: Iraq | B68: =G68 -> B- | C68: =F68 -> Caa1 | E68: Iraq | F68: =VLOOKUP(E68,$K$2:$M$154,3,FALSE()) -> Caa1 | G68: =VLOOKUP(E68,$O$2:$P$155,2,FALSE()) -> B- | H68: =VLOOKUP(E68,$Q$2:$R$161,2,FALSE()) -> B- | K68: Ireland | L68: Aa3 | M68: Aa3 | O68: Ivory Coast | P68: BB | Q68: Israel | R68: A
